Workbook

Sheet COVER
C3: =UPPER(NAMA_USAHA) -> KOPI PARANG
C5: LAPORAN KEUANGAN
C6: ="Periode 1 Januari – "&TEXT(DATE(TAHUN,BLN+1,0),"d")&" "&NAMA_BLN&" "&TAHUN -> Periode 1 Januari – 30 September 2026
C10: DAFTAR ISI
B11: 1 | C11: PENGATURAN | D11: Tahun, bulan tutup buku, tarif pajak, target
B12: 2 | C12: DASHBOARD | D12: Ringkasan kinerja, grafik, cek kesehatan data
B13: 3 | C13: LABA RUGI | D13: Laporan laba rugi bulanan (multi-step)
B14: 4 | C14: NERACA | D14: Laporan posisi keuangan
B15: 5 | C15: ARUS KAS | D15: Arus kas metode langsung
B16: 6 | C16: PERUBAHAN EKUITAS | D16: Mutasi modal pemilik
B17: 7 | C17: CALK | D17: Catatan atas laporan keuangan
B18: 8 | C18: REVIEW | D18: Temuan review & tindak lanjut
B19: 9 | C19: PAJAK | D19: Rekonsiliasi pajak restoran (PBJT)
B20: 10 | C20: ANALISIS EVENT | D20: Laba rugi per event
B21: 11 | C21: REKAP OMZET | D21: Rekap omzet bulanan & KPI penjualan
B22: 12 | C22: OMZET HARIAN | D22: INPUT — omzet & realisasi harian
... B28: 18 | C28: MUTASI | D28: Sheet hitung (jangan diubah)
C30: CARA PAKAI
C31: 1. Setiap hari: isi OMZET HARIAN (angka POS, lalu realisasi setoran H+1).
C32: 2. Setiap transaksi: isi satu baris di JURNAL (tanggal, akun debet, akun kredit, nominal, keterangan, tag event bila ada).
C33: 3. Akhir bulan: stok opname, cek kas opname, isi gaji & sewa, lalu ubah "bulan tutup buku" di PENGATURAN.
C34: 4. Buka DASHBOARD → pastikan semua cek kesehatan data ✔ sebelum laporan dibagikan.
C36: KODE WARNA
C37: Teks biru | D37: Data input manual
C38: Latar kuning | D38: Pengaturan / input penting
C39: Teks hitam | D39: Rumus — jangan ditimpa
C40: Latar abu-abu | D40: Kolom bantu rumus
C41: Baris coklat muda miring | D41: Jurnal otomatis / penyesuaian
C44: Disusun mengacu SAK EMKM. Dibuat ulang dari file KOPI_PARANG_FINANCIAL_REPORT_1.xlsx.

Sheet PENGATURAN
A1: PENGATURAN
A2: Sel kuning = boleh diubah. Semua laporan otomatis menyesuaikan.
B3: Parameter | C3: Nilai | D3: Keterangan
B4: Nama usaha | C4: Kopi Parang | D4: Nama yang tampil di semua laporan | F4: No | G4: Bulan
B5: Tahun buku | C5: 2026 | D5: Tahun laporan | F5: 1 | G5: Januari
B6: Bulan tutup buku terakhir (1–12) | C6: 9 | D6: Laporan dihitung s.d. bulan ini. Oktober belum lengkap (gaji, sewa, pajak belum dicatat), jadi diset ke 9 = September. | F6: 2 | G6: Februari
B7: Nama bulan tutup buku | C7: =INDEX($G$5:$G$16,$C$6) -> September | D7: Otomatis | F7: 3 | G7: Maret
B8: Tarif PBJT makanan & minuman | C8: 0.1 | D8: Pajak Barang & Jasa Tertentu (pajak restoran) daerah | F8: 4 | G8: April
B9: Harga menu sudah termasuk PBJT? (YA/TIDAK) | C9: YA | D9: YA = pajak dihitung 10/110 dari omzet; TIDAK = 10% dari omzet. Pastikan sesuai praktik di kasir. | F9: 5 | G9: Mei
B10: Akui estimasi PBJT kurang bayar di laporan? (YA/TIDAK) | C10: YA | D10: Disarankan YA: laporan yang ditunjukkan ke pihak luar harus memuat kewajiban ini. Lihat sheet PAJAK & REVIEW. | F10: 6 | G10: Juni
F11: 7 | G11: Juli
B12: Target omzet bulanan (Rp) | C12: 100000000 | D12: CONTOH — ganti dengan target kamu sendiri | F12: 8 | G12: Agustus
F13: 9 | G13: September
B14: Batas food cost (HPP / pendapatan) | C14: 0.35 | D14: Patokan umum F&B 28–35%; sesuaikan | F14: 10 | G14: Oktober
B15: Batas biaya gaji (payroll / pendapatan) | C15: 0.3 | D15: Patokan umum F&B 25–30%; sesuaikan | F15: 11 | G15: November
B16: Batas sewa (occupancy / pendapatan) | C16: 0.1 | D16: Patokan umum F&B 6–10%; sesuaikan | F16: 12 | G16: Desember
B17: Batas prime cost (HPP + gaji) | C17: 0.65 | D17: Patokan umum F&B 60–65%; sesuaikan
B18: Target net margin minimal | C18: 0.1 | D18: Patokan umum cafe sehat 10–15%; sesuaikan

Sheet DASHBOARD
B1: =UPPER(NAMA_USAHA)&" — RINGKASAN KEUANGAN" -> KOPI PARANG — RINGKASAN KEUANGAN
B2: ="Periode 1 Januari – "&TEXT(DATE(TAHUN,BLN+1,0),"d")&" "&NAMA_BLN&" "&TAHUN -> Periode 1 Januari – 30 September 2026
B4: Pendapatan Bersih | E4: Laba Kotor | H4: Laba (Rugi) Bersih | K4: Total Kas
B5: ='LABA RUGI'!$O$11 -> 795505902 | E5: ='LABA RUGI'!$O$18 -> 456926368 | H5: ='LABA RUGI'!$O$43 -> -54996702 | K5: =NERACA!D7+NERACA!D8+NERACA!D9 -> 53281608
B6: ="Rata-rata "&TEXT('LABA RUGI'!$O$11/BLN,"#,##0")&" / bulan" -> Rata-rata 88,389,545 / bulan | E6: ="Margin "&TEXT('LABA RUGI'!$O$19,"0.0%") -> Margin 57.4% | H6: ="Margin "&TEXT('LABA RUGI'!$O$44,"0.0%") -> Margin -6.9% | K6: ="Tunai "&TEXT(NERACA!D7,"#,##0") -> Tunai 51,913,400
B8: Omzet Bersih / Hari | E8: Rata-rata / Transaksi | H8: Food Cost | K8: Prime Cost
B9: =IFERROR(SUMPRODUCT(('REKAP OMZET'!$C$5:$N$5<=BLN)*'REKAP OMZET'!$C$16:$N$16)/SUMPRODUCT(('REKAP OMZET'!$C$5:$N$5<=BLN)*'REKAP OMZET'!$C$18:$N$18),0) -> 3179316.8 | E9: =IFERROR(SUMPRODUCT(('REKAP OMZET'!$C$5:$N$5<=BLN)*'REKAP OMZET'!$C$16:$N$16)/SUMPRODUCT(('REKAP OMZET'!$C$5:$N$5<=BLN)*'REKAP OMZET'!$C$20:$N$20),0) -> 48707.191 | H9: ='LABA RUGI'!$O$47 -> 0.42561536 | K9: ='LABA RUGI'!$O$50 -> 0.74480114
B10: ="rata-rata hari buka" -> rata-rata hari buka | E10: ="avg ticket" -> avg ticket | H10: ="batas "&TEXT(MX_FOOD,"0%") -> batas 35% | K10: ="HPP + gaji, batas "&TEXT(MX_PRIME,"0%") -> HPP + gaji, batas 65%
B12: KINERJA BULANAN
B13: Bulan | C13: Pendapatan Bersih | E13: Laba Kotor | F13: Laba Bersih | H13: Food Cost | I13: Payroll | K13: Kas Akhir
B14: Jan | C14: =IF(1>BLN,0,N('LABA RUGI'!C11)) -> 90280982 | E14: =IF(1>BLN,0,N('LABA RUGI'!C18)) -> 62112682 | F14: =IF(1>BLN,0,N('LABA RUGI'!C43)) -> -51148041 | H14: =IF(1>BLN,"",'LABA RUGI'!C47) -> 0.31200702 | I14: =IF(1>BLN,"",'LABA RUGI'!C48) -> 0.28389146 | K14: =IF(1>BLN,"",'ARUS KAS'!C28) -> 50335039
B15: Feb | C15: =IF(2>BLN,0,N('LABA RUGI'!D11)) -> 68311343 | E15: =IF(2>BLN,0,N('LABA RUGI'!D18)) -> 37077633 | F15: =IF(2>BLN,0,N('LABA RUGI'!D43)) -> -6212118 | H15: =IF(2>BLN,"",'LABA RUGI'!D47) -> 0.45722582 | I15: =IF(2>BLN,"",'LABA RUGI'!D48) -> 0.39077698 | K15: =IF(2>BLN,"",'ARUS KAS'!D28) -> 45123333
B16: Mar | C16: =IF(3>BLN,0,N('LABA RUGI'!E11)) -> 93204021 | E16: =IF(3>BLN,0,N('LABA RUGI'!E18)) -> 60166834 | F16: =IF(3>BLN,0,N('LABA RUGI'!E43)) -> -3403297 | H16: =IF(3>BLN,"",'LABA RUGI'!E47) -> 0.35446096 | I16: =IF(3>BLN,"",'LABA RUGI'!E48) -> 0.46030203 | K16: =IF(3>BLN,"",'ARUS KAS'!E28) -> 43724486
B17: Apr | C17: =IF(4>BLN,0,N('LABA RUGI'!F11)) -> 85954724 | E17: =IF(4>BLN,0,N('LABA RUGI'!F18)) -> 29785930 | F17: =IF(4>BLN,0,N('LABA RUGI'!F43)) -> -20407510 | H17: =IF(4>BLN,"",'LABA RUGI'!F47) -> 0.65346954 | I17: =IF(4>BLN,"",'LABA RUGI'!F48) -> 0.31721351 | K17: =IF(4>BLN,"",'ARUS KAS'!F28) -> 27358556
B18: Mei | C18: =IF(5>BLN,0,N('LABA RUGI'!G11)) -> 102494869 | E18: =IF(5>BLN,0,N('LABA RUGI'!G18)) -> 67769696 | F18: =IF(5>BLN,0,N('LABA RUGI'!G43)) -> 16080376 | H18: =IF(5>BLN,"",'LABA RUGI'!G47) -> 0.33879914 | I18: =IF(5>BLN,"",'LABA RUGI'!G48) -> 0.28689566 | K18: =IF(5>BLN,"",'ARUS KAS'!G28) -> 45262022
B19: Jun | C19: =IF(6>BLN,0,N('LABA RUGI'!H11)) -> 95817091 | E19: =IF(6>BLN,0,N('LABA RUGI'!H18)) -> 50680584 | F19: =IF(6>BLN,0,N('LABA RUGI'!H43)) -> 5382034 | H19: =IF(6>BLN,"",'LABA RUGI'!H47) -> 0.47106948 | I19: =IF(6>BLN,"",'LABA RUGI'!H48) -> 0.31615793 | K19: =IF(6>BLN,"",'ARUS KAS'!H28) -> 50562532
B20: Jul | C20: =IF(7>BLN,0,N('LABA RUGI'!I11)) -> 85381495 | E20: =IF(7>BLN,0,N('LABA RUGI'!I18)) -> 51463451 | F20: =IF(7>BLN,0,N('LABA RUGI'!I43)) -> 4796009 | H20: =IF(7>BLN,"",'LABA RUGI'!I47) -> 0.39725287 | I20: =IF(7>BLN,"",'LABA RUGI'!I48) -> 0.26658391 | K20: =IF(7>BLN,"",'ARUS KAS'!I28) -> 48081893
B21: Agu | C21: =IF(8>BLN,0,N('LABA RUGI'!J11)) -> 87841757 | E21: =IF(8>BLN,0,N('LABA RUGI'!J18)) -> 64748737 | F21: =IF(8>BLN,0,N('LABA RUGI'!J43)) -> 17725947 | H21: =IF(8>BLN,"",'LABA RUGI'!J47) -> 0.26289342 | I21: =IF(8>BLN,"",'LABA RUGI'!J48) -> 0.27514628 | K21: =IF(8>BLN,"",'ARUS KAS'!J28) -> 68054513
B22: Sep | C22: =IF(9>BLN,0,N('LABA RUGI'!K11)) -> 86219620 | E22: =IF(9>BLN,0,N('LABA RUGI'!K18)) -> 33120821 | F22: =IF(9>BLN,0,N('LABA RUGI'!K43)) -> -17810102 | H22: =IF(9>BLN,"",'LABA RUGI'!K47) -> 0.61585517 | I22: =IF(9>BLN,"",'LABA RUGI'!K48) -> 0.28754862 | K22: =IF(9>BLN,"",'ARUS KAS'!K28) -> 53281608
B23: Okt | C23: =IF(10>BLN,0,N('LABA RUGI'!L11)) -> 0 | E23: =IF(10>BLN,0,N('LABA RUGI'!L18)) -> 0 | F23: =IF(10>BLN,0,N('LABA RUGI'!L43)) -> 0 | H23: =IF(10>BLN,"",'LABA RUGI'!L47) | I23: =IF(10>BLN,"",'LABA RUGI'!L48) | K23: =IF(10>BLN,"",'ARUS KAS'!L28)
B24: Nov | C24: =IF(11>BLN,0,N('LABA RUGI'!M11)) -> 0 | E24: =IF(11>BLN,0,N('LABA RUGI'!M18)) -> 0 | F24: =IF(11>BLN,0,N('LABA RUGI'!M43)) -> 0 | H24: =IF(11>BLN,"",'LABA RUGI'!M47) | I24: =IF(11>BLN,"",'LABA RUGI'!M48) | K24: =IF(11>BLN,"",'ARUS KAS'!M28)
B25: Des | C25: =IF(12>BLN,0,N('LABA RUGI'!N11)) -> 0 | E25: =IF(12>BLN,0,N('LABA RUGI'!N18)) -> 0 | F25: =IF(12>BLN,0,N('LABA RUGI'!N43)) -> 0 | H25: =IF(12>BLN,"",'LABA RUGI'!N47) | I25: =IF(12>BLN,"",'LABA RUGI'!N48) | K25: =IF(12>BLN,"",'ARUS KAS'!N28)
B45: STRUKTUR BIAYA (s.d. tutup buku)
B46: Pos | C46: Rupiah | E46: % Pendapatan
B47: HPP | C47: ='LABA RUGI'!$O$16 -> 338579534 | E47: =IFERROR(C47/'LABA RUGI'!$O$11,"") -> 0.42561536
B48: Gaji | C48: ='LABA RUGI'!$O$22 -> 253914165 | E48: =IFERROR(C48/'LABA RUGI'!$O$11,"") -> 0.31918577
B49: Sewa | C49: ='LABA RUGI'!$O$23 -> 80000000 | E49: =IFERROR(C49/'LABA RUGI'!$O$11,"") -> 0.10056494
B50: Marketing & event | C50: ='LABA RUGI'!$O$25 -> 79193298 | E50: =IFERROR(C50/'LABA RUGI'!$O$11,"") -> 0.099550862
B51: Tagihan bulanan | C51: ='LABA RUGI'!$O$24 -> 45436921 | E51: =IFERROR(C51/'LABA RUGI'!$O$11,"") -> 0.057117013
B52: Beban lainnya | C52: ='LABA RUGI'!$O$33-'LABA RUGI'!$O$22-'LABA RUGI'!$O$23-'LABA RUGI'!$O$25-'LABA RUGI'!$O$24 -> 50765307 | E52: =IFERROR(C52/'LABA RUGI'!$O$11,"") -> 0.063815123
B53: Sisa (laba/rugi) | C53: ='LABA RUGI'!$O$11-SUM(C47:C52) -> -52383323 | E53: =IFERROR(C53/'LABA RUGI'!$O$11,"") -> -0.065849069
B56: CEK KESEHATAN DATA
B57: Neraca seimbang | F57: =IF(NERACA!D38=0,"✔ OK","✘ Selisih "&TEXT(NERACA!D38,"#,##0")) -> ✔ OK
B58: Neraca saldo seimbang | F58: =IF('NERACA SALDO'!G41=0,"✔ OK","✘ Tidak seimbang") -> ✔ OK
B59: Kas di arus kas = kas di neraca | F59: =IF('ARUS KAS'!O29=0,"✔ OK","✘ Selisih") -> ✔ OK
B60: Ekuitas: laporan perubahan = neraca | F60: =IF('PERUBAHAN EKUITAS'!O12=0,"✔ OK","✘ Selisih") -> ✔ OK
B61: Daftar aset tetap = akun Peralatan | F61: =IF('ASET TETAP'!D27=0,"✔ OK","✘ Selisih") -> ✔ OK
B62: Jurnal dengan akun tidak dikenal | F62: =IF(COUNTIF(J_CEK,"⚠*")=0,"✔ Tidak ada",COUNTIF(J_CEK,"⚠*")&" baris — cek kolom R JURNAL") -> ✔ Tidak ada
B63: Hari omzet belum direalisasi / perlu cek | F63: =IF('REKAP OMZET'!O26=0,"✔ Tidak ada",'REKAP OMZET'!O26&" hari — cek OMZET HARIAN") -> 12 hari — cek OMZET HARIAN
B64: Saldo awal aset tetap (pra-2026) | F64: =IF('ASET TETAP'!D24=0,"⚠ Belum diinventarisasi","✔ Terisi") -> ⚠ Belum diinventarisasi
B65: Estimasi PBJT kurang bayar | F65: =IF(PAJAK!J18>0,"⚠ Rp "&TEXT(PAJAK!J18,"#,##0")&" — lihat PAJAK","✔ Tidak ada") -> ⚠ Rp 59,326,181 — lihat PAJAK

Sheet LABA RUGI
A1: LAPORAN LABA RUGI
A2: ="KOPI PARANG • "&"Periode 1 Januari – "&TEXT(DATE(TAHUN,BLN+1,0),"d")&" "&NAMA_BLN&" "&TAHUN&" • dalam Rupiah" -> KOPI PARANG • Periode 1 Januari – 30 September 2026 • dalam Rupiah
B4: Keterangan | C4: Jan | D4: Feb | E4: Mar | F4: Apr | G4: Mei | H4: Jun | I4: Jul | J4: Agu | K4: Sep | L4: Okt | M4: Nov | N4: Des | O4: ="s.d. "&LEFT(NAMA_BLN,3)&" "&TAHUN -> s.d. Sep 2026 | P4: % Pend.
C5: 1 | D5: 2 | E5: 3 | F5: 4 | G5: 5 | H5: 6 | I5: 7 | J5: 8 | K5: 9 | L5: 10 | M5: 11 | N5: 12
B6: PENDAPATAN USAHA
B7: Penjualan cafe | C7: =IF(C$5>BLN,"",-SUMIF(MUTASI!$B$6:$B$45,"Pendapatan Cafe",MUTASI!$E$6:$E$45)) -> 90683177 | D7: =IF(D$5>BLN,"",-SUMIF(MUTASI!$B$6:$B$45,"Pendapatan Cafe",MUTASI!$F$6:$F$45)) -> 73106388 | E7: =IF(E$5>BLN,"",-SUMIF(MUTASI!$B$6:$B$45,"Pendapatan Cafe",MUTASI!$G$6:$G$45)) -> 102509844 | F7: =IF(F$5>BLN,"",-SUMIF(MUTASI!$B$6:$B$45,"Pendapatan Cafe",MUTASI!$H$6:$H$45)) -> 94551888 | G7: =IF(G$5>BLN,"",-SUMIF(MUTASI!$B$6:$B$45,"Pendapatan Cafe",MUTASI!$I$6:$I$45)) -> 111312774 | H7: =IF(H$5>BLN,"",-SUMIF(MUTASI!$B$6:$B$45,"Pendapatan Cafe",MUTASI!$J$6:$J$45)) -> 105398227 | I7: =IF(I$5>BLN,"",-SUMIF(MUTASI!$B$6:$B$45,"Pendapatan Cafe",MUTASI!$K$6:$K$45)) -> 93923281 | J7: =IF(J$5>BLN,"",-SUMIF(MUTASI!$B$6:$B$45,"Pendapatan Cafe",MUTASI!$L$6:$L$45)) -> 94790934 | K7: =IF(K$5>BLN,"",-SUMIF(MUTASI!$B$6:$B$45,"Pendapatan Cafe",MUTASI!$M$6:$M$45)) -> 92214820 | L7: =IF(L$5>BLN,"",-SUMIF(MUTASI!$B$6:$B$45,"Pendapatan Cafe",MUTASI!$N$6:$N$45)) | M7: =IF(M$5>BLN,"",-SUMIF(MUTASI!$B$6:$B$45,"Pendapatan Cafe",MUTASI!$O$6:$O$45)) | N7: =IF(N$5>BLN,"",-SUMIF(MUTASI!$B$6:$B$45,"Pendapatan Cafe",MUTASI!$P$6:$P$45)) | O7: =-SUMIF(MUTASI!$B$6:$B$45,"Pendapatan Cafe",MUTASI!$R$6:$R$45) -> 858491333 | P7: =IFERROR(O7/O11,"") -> 1.0791766
B8: Pendapatan event & non-cafe | C8: =IF(C$5>BLN,"",-SUMIF(MUTASI!$B$6:$B$45,"Pendapatan non Cafe",MUTASI!$E$6:$E$45)) -> 7870000 | D8: =IF(D$5>BLN,"",-SUMIF(MUTASI!$B$6:$B$45,"Pendapatan non Cafe",MUTASI!$F$6:$F$45)) -> 1860000 | E8: =IF(E$5>BLN,"",-SUMIF(MUTASI!$B$6:$B$45,"Pendapatan non Cafe",MUTASI!$G$6:$G$45)) -> 0 | F8: =IF(F$5>BLN,"",-SUMIF(MUTASI!$B$6:$B$45,"Pendapatan non Cafe",MUTASI!$H$6:$H$45)) -> 0 | G8: =IF(G$5>BLN,"",-SUMIF(MUTASI!$B$6:$B$45,"Pendapatan non Cafe",MUTASI!$I$6:$I$45)) -> 1300000 | H8: =IF(H$5>BLN,"",-SUMIF(MUTASI!$B$6:$B$45,"Pendapatan non Cafe",MUTASI!$J$6:$J$45)) -> 0 | I8: =IF(I$5>BLN,"",-SUMIF(MUTASI!$B$6:$B$45,"Pendapatan non Cafe",MUTASI!$K$6:$K$45)) -> 0 | J8: =IF(J$5>BLN,"",-SUMIF(MUTASI!$B$6:$B$45,"Pendapatan non Cafe",MUTASI!$L$6:$L$45)) -> 1678800 | K8: =IF(K$5>BLN,"",-SUMIF(MUTASI!$B$6:$B$45,"Pendapatan non Cafe",MUTASI!$M$6:$M$45)) -> 2394250 | L8: =IF(L$5>BLN,"",-SUMIF(MUTASI!$B$6:$B$45,"Pendapatan non Cafe",MUTASI!$N$6:$N$45)) | M8: =IF(M$5>BLN,"",-SUMIF(MUTASI!$B$6:$B$45,"Pendapatan non Cafe",MUTASI!$O$6:$O$45)) | N8: =IF(N$5>BLN,"",-SUMIF(MUTASI!$B$6:$B$45,"Pendapatan non Cafe",MUTASI!$P$6:$P$45)) | O8: =-SUMIF(MUTASI!$B$6:$B$45,"Pendapatan non Cafe",MUTASI!$R$6:$R$45) -> 15103050 | P8: =IFERROR(O8/O11,"") -> 0.018985466
B9: Pendapatan kotor | C9: =IF(C$5>BLN,"",N(C7)+N(C8)) -> 98553177 | D9: =IF(D$5>BLN,"",N(D7)+N(D8)) -> 74966388 | E9: =IF(E$5>BLN,"",N(E7)+N(E8)) -> 102509844 | F9: =IF(F$5>BLN,"",N(F7)+N(F8)) -> 94551888 | G9: =IF(G$5>BLN,"",N(G7)+N(G8)) -> 112612774 | H9: =IF(H$5>BLN,"",N(H7)+N(H8)) -> 105398227 | I9: =IF(I$5>BLN,"",N(I7)+N(I8)) -> 93923281 | J9: =IF(J$5>BLN,"",N(J7)+N(J8)) -> 96469734 | ... N9: =IF(N$5>BLN,"",N(N7)+N(N8)) | O9: =N(O7)+N(O8) -> 873594383 | P9: =IFERROR(O9/O11,"") -> 1.098162
B10: Dikurangi: pajak restoran (PBJT) | C10: =IF(C$5>BLN,"",SUMIF(MUTASI!$B$6:$B$45,"Pajak Restoran",MUTASI!$E$6:$E$45)) -> 8272195 | D10: =IF(D$5>BLN,"",SUMIF(MUTASI!$B$6:$B$45,"Pajak Restoran",MUTASI!$F$6:$F$45)) -> 6655045 | E10: =IF(E$5>BLN,"",SUMIF(MUTASI!$B$6:$B$45,"Pajak Restoran",MUTASI!$G$6:$G$45)) -> 9305823 | F10: =IF(F$5>BLN,"",SUMIF(MUTASI!$B$6:$B$45,"Pajak Restoran",MUTASI!$H$6:$H$45)) -> 8597164 | G10: =IF(G$5>BLN,"",SUMIF(MUTASI!$B$6:$B$45,"Pajak Restoran",MUTASI!$I$6:$I$45)) -> 10117905 | H10: =IF(H$5>BLN,"",SUMIF(MUTASI!$B$6:$B$45,"Pajak Restoran",MUTASI!$J$6:$J$45)) -> 9581136 | I10: =IF(I$5>BLN,"",SUMIF(MUTASI!$B$6:$B$45,"Pajak Restoran",MUTASI!$K$6:$K$45)) -> 8541786 | J10: =IF(J$5>BLN,"",SUMIF(MUTASI!$B$6:$B$45,"Pajak Restoran",MUTASI!$L$6:$L$45)) -> 8627977 | K10: =IF(K$5>BLN,"",SUMIF(MUTASI!$B$6:$B$45,"Pajak Restoran",MUTASI!$M$6:$M$45)) -> 8389450 | L10: =IF(L$5>BLN,"",SUMIF(MUTASI!$B$6:$B$45,"Pajak Restoran",MUTASI!$N$6:$N$45)) | M10: =IF(M$5>BLN,"",SUMIF(MUTASI!$B$6:$B$45,"Pajak Restoran",MUTASI!$O$6:$O$45)) | N10: =IF(N$5>BLN,"",SUMIF(MUTASI!$B$6:$B$45,"Pajak Restoran",MUTASI!$P$6:$P$45)) | O10: =SUMIF(MUTASI!$B$6:$B$45,"Pajak Restoran",MUTASI!$R$6:$R$45) -> 78088481 | P10: =IFERROR(O10/O11,"") -> 0.098162039
B11: PENDAPATAN BERSIH | C11: =IF(C$5>BLN,"",N(C9)-N(C10)) -> 90280982 | D11: =IF(D$5>BLN,"",N(D9)-N(D10)) -> 68311343 | E11: =IF(E$5>BLN,"",N(E9)-N(E10)) -> 93204021 | F11: =IF(F$5>BLN,"",N(F9)-N(F10)) -> 85954724 | G11: =IF(G$5>BLN,"",N(G9)-N(G10)) -> 102494869 | H11: =IF(H$5>BLN,"",N(H9)-N(H10)) -> 95817091 | I11: =IF(I$5>BLN,"",N(I9)-N(I10)) -> 85381495 | J11: =IF(J$5>BLN,"",N(J9)-N(J10)) -> 87841757 | ... N11: =IF(N$5>BLN,"",N(N9)-N(N10)) | O11: =N(O9)-N(O10) -> 795505902 | P11: =IFERROR(O11/O11,"") -> 1
B13: BEBAN POKOK PENJUALAN
B14: Bahan baku | C14: =IF(C$5>BLN,"",SUMIF(MUTASI!$B$6:$B$45,"Biaya Bahan Baku",MUTASI!$E$6:$E$45)) -> 25310200 | D14: =IF(D$5>BLN,"",SUMIF(MUTASI!$B$6:$B$45,"Biaya Bahan Baku",MUTASI!$F$6:$F$45)) -> 26953700 | E14: =IF(E$5>BLN,"",SUMIF(MUTASI!$B$6:$B$45,"Biaya Bahan Baku",MUTASI!$G$6:$G$45)) -> 28284387 | F14: =IF(F$5>BLN,"",SUMIF(MUTASI!$B$6:$B$45,"Biaya Bahan Baku",MUTASI!$H$6:$H$45)) -> 50730535 | G14: =IF(G$5>BLN,"",SUMIF(MUTASI!$B$6:$B$45,"Biaya Bahan Baku",MUTASI!$I$6:$I$45)) -> 31404673 | H14: =IF(H$5>BLN,"",SUMIF(MUTASI!$B$6:$B$45,"Biaya Bahan Baku",MUTASI!$J$6:$J$45)) -> 38670406 | I14: =IF(I$5>BLN,"",SUMIF(MUTASI!$B$6:$B$45,"Biaya Bahan Baku",MUTASI!$K$6:$K$45)) -> 31812694 | J14: =IF(J$5>BLN,"",SUMIF(MUTASI!$B$6:$B$45,"Biaya Bahan Baku",MUTASI!$L$6:$L$45)) -> 20123020 | K14: =IF(K$5>BLN,"",SUMIF(MUTASI!$B$6:$B$45,"Biaya Bahan Baku",MUTASI!$M$6:$M$45)) -> 49298099 | L14: =IF(L$5>BLN,"",SUMIF(MUTASI!$B$6:$B$45,"Biaya Bahan Baku",MUTASI!$N$6:$N$45)) | M14: =IF(M$5>BLN,"",SUMIF(MUTASI!$B$6:$B$45,"Biaya Bahan Baku",MUTASI!$O$6:$O$45)) | N14: =IF(N$5>BLN,"",SUMIF(MUTASI!$B$6:$B$45,"Biaya Bahan Baku",MUTASI!$P$6:$P$45)) | O14: =SUMIF(MUTASI!$B$6:$B$45,"Biaya Bahan Baku",MUTASI!$R$6:$R$45) -> 302587714 | P14: =IFERROR(O14/O11,"") -> 0.38037143
B15: Penyajian & kemasan | C15: =IF(C$5>BLN,"",SUMIF(MUTASI!$B$6:$B$45,"Biaya Penyajian",MUTASI!$E$6:$E$45)) -> 2858100 | D15: =IF(D$5>BLN,"",SUMIF(MUTASI!$B$6:$B$45,"Biaya Penyajian",MUTASI!$F$6:$F$45)) -> 4280010 | E15: =IF(E$5>BLN,"",SUMIF(MUTASI!$B$6:$B$45,"Biaya Penyajian",MUTASI!$G$6:$G$45)) -> 4752800 | F15: =IF(F$5>BLN,"",SUMIF(MUTASI!$B$6:$B$45,"Biaya Penyajian",MUTASI!$H$6:$H$45)) -> 5438259 | G15: =IF(G$5>BLN,"",SUMIF(MUTASI!$B$6:$B$45,"Biaya Penyajian",MUTASI!$I$6:$I$45)) -> 3320500 | H15: =IF(H$5>BLN,"",SUMIF(MUTASI!$B$6:$B$45,"Biaya Penyajian",MUTASI!$J$6:$J$45)) -> 6466101 | I15: =IF(I$5>BLN,"",SUMIF(MUTASI!$B$6:$B$45,"Biaya Penyajian",MUTASI!$K$6:$K$45)) -> 2105350 | J15: =IF(J$5>BLN,"",SUMIF(MUTASI!$B$6:$B$45,"Biaya Penyajian",MUTASI!$L$6:$L$45)) -> 2970000 | K15: =IF(K$5>BLN,"",SUMIF(MUTASI!$B$6:$B$45,"Biaya Penyajian",MUTASI!$M$6:$M$45)) -> 3800700 | L15: =IF(L$5>BLN,"",SUMIF(MUTASI!$B$6:$B$45,"Biaya Penyajian",MUTASI!$N$6:$N$45)) | M15: =IF(M$5>BLN,"",SUMIF(MUTASI!$B$6:$B$45,"Biaya Penyajian",MUTASI!$O$6:$O$45)) | N15: =IF(N$5>BLN,"",SUMIF(MUTASI!$B$6:$B$45,"Biaya Penyajian",MUTASI!$P$6:$P$45)) | O15: =SUMIF(MUTASI!$B$6:$B$45,"Biaya Penyajian",MUTASI!$R$6:$R$45) -> 35991820 | P15: =IFERROR(O15/O11,"") -> 0.045243938
B16: Total beban pokok penjualan | C16: =IF(C$5>BLN,"",N(C14)+N(C15)) -> 28168300 | D16: =IF(D$5>BLN,"",N(D14)+N(D15)) -> 31233710 | E16: =IF(E$5>BLN,"",N(E14)+N(E15)) -> 33037187 | F16: =IF(F$5>BLN,"",N(F14)+N(F15)) -> 56168794 | G16: =IF(G$5>BLN,"",N(G14)+N(G15)) -> 34725173 | H16: =IF(H$5>BLN,"",N(H14)+N(H15)) -> 45136507 | I16: =IF(I$5>BLN,"",N(I14)+N(I15)) -> 33918044 | J16: =IF(J$5>BLN,"",N(J14)+N(J15)) -> 23093020 | ... N16: =IF(N$5>BLN,"",N(N14)+N(N15)) | O16: =N(O14)+N(O15) -> 338579534 | P16: =IFERROR(O16/O11,"") -> 0.42561536
B18: LABA KOTOR | C18: =IF(C$5>BLN,"",N(C11)-N(C16)) -> 62112682 | D18: =IF(D$5>BLN,"",N(D11)-N(D16)) -> 37077633 | E18: =IF(E$5>BLN,"",N(E11)-N(E16)) -> 60166834 | F18: =IF(F$5>BLN,"",N(F11)-N(F16)) -> 29785930 | G18: =IF(G$5>BLN,"",N(G11)-N(G16)) -> 67769696 | H18: =IF(H$5>BLN,"",N(H11)-N(H16)) -> 50680584 | I18: =IF(I$5>BLN,"",N(I11)-N(I16)) -> 51463451 | J18: =IF(J$5>BLN,"",N(J11)-N(J16)) -> 64748737 | ... N18: =IF(N$5>BLN,"",N(N11)-N(N16)) | O18: =N(O11)-N(O16) -> 456926368 | P18: =IFERROR(O18/O11,"") -> 0.57438464
B19: Margin laba kotor | C19: =IF(C$5>BLN,"",IFERROR((N(C18))/C11,"")) -> 0.68799298 | D19: =IF(D$5>BLN,"",IFERROR((N(D18))/D11,"")) -> 0.54277418 | E19: =IF(E$5>BLN,"",IFERROR((N(E18))/E11,"")) -> 0.64553904 | F19: =IF(F$5>BLN,"",IFERROR((N(F18))/F11,"")) -> 0.34653046 | G19: =IF(G$5>BLN,"",IFERROR((N(G18))/G11,"")) -> 0.66120086 | H19: =IF(H$5>BLN,"",IFERROR((N(H18))/H11,"")) -> 0.52893052 | I19: =IF(I$5>BLN,"",IFERROR((N(I18))/I11,"")) -> 0.60274713 | J19: =IF(J$5>BLN,"",IFERROR((N(J18))/J11,"")) -> 0.73710658 | ... N19: =IF(N$5>BLN,"",IFERROR((N(N18))/N11,"")) | O19: =IFERROR((N(O18))/O11,"") -> 0.57438464
B21: BEBAN USAHA
B22: Gaji karyawan | C22: =IF(C$5>BLN,"",SUMIF(MUTASI!$B$6:$B$45,"Beban Gaji",MUTASI!$E$6:$E$45)) -> 25630000 | D22: =IF(D$5>BLN,"",SUMIF(MUTASI!$B$6:$B$45,"Beban Gaji",MUTASI!$F$6:$F$45)) -> 26694500 | E22: =IF(E$5>BLN,"",SUMIF(MUTASI!$B$6:$B$45,"Beban Gaji",MUTASI!$G$6:$G$45)) -> 42902000 | F22: =IF(F$5>BLN,"",SUMIF(MUTASI!$B$6:$B$45,"Beban Gaji",MUTASI!$H$6:$H$45)) -> 27266000 | G22: =IF(G$5>BLN,"",SUMIF(MUTASI!$B$6:$B$45,"Beban Gaji",MUTASI!$I$6:$I$45)) -> 29405333 | H22: =IF(H$5>BLN,"",SUMIF(MUTASI!$B$6:$B$45,"Beban Gaji",MUTASI!$J$6:$J$45)) -> 30293333 | I22: =IF(I$5>BLN,"",SUMIF(MUTASI!$B$6:$B$45,"Beban Gaji",MUTASI!$K$6:$K$45)) -> 22761333 | J22: =IF(J$5>BLN,"",SUMIF(MUTASI!$B$6:$B$45,"Beban Gaji",MUTASI!$L$6:$L$45)) -> 24169333 | K22: =IF(K$5>BLN,"",SUMIF(MUTASI!$B$6:$B$45,"Beban Gaji",MUTASI!$M$6:$M$45)) -> 24792333 | L22: =IF(L$5>BLN,"",SUMIF(MUTASI!$B$6:$B$45,"Beban Gaji",MUTASI!$N$6:$N$45)) | M22: =IF(M$5>BLN,"",SUMIF(MUTASI!$B$6:$B$45,"Beban Gaji",MUTASI!$O$6:$O$45)) | N22: =IF(N$5>BLN,"",SUMIF(MUTASI!$B$6:$B$45,"Beban Gaji",MUTASI!$P$6:$P$45)) | O22: =SUMIF(MUTASI!$B$6:$B$45,"Beban Gaji",MUTASI!$R$6:$R$45) -> 253914165 | P22: =IFERROR(O22/O11,"") -> 0.31918577
B23: Sewa tempat | C23: =IF(C$5>BLN,"",SUMIF(MUTASI!$B$6:$B$45,"Biaya Sewa Tempat",MUTASI!$E$6:$E$45)) -> 10000000 | D23: =IF(D$5>BLN,"",SUMIF(MUTASI!$B$6:$B$45,"Biaya Sewa Tempat",MUTASI!$F$6:$F$45)) -> 10000000 | E23: =IF(E$5>BLN,"",SUMIF(MUTASI!$B$6:$B$45,"Biaya Sewa Tempat",MUTASI!$G$6:$G$45)) -> 10000000 | F23: =IF(F$5>BLN,"",SUMIF(MUTASI!$B$6:$B$45,"Biaya Sewa Tempat",MUTASI!$H$6:$H$45)) -> 10000000 | G23: =IF(G$5>BLN,"",SUMIF(MUTASI!$B$6:$B$45,"Biaya Sewa Tempat",MUTASI!$I$6:$I$45)) -> 10000000 | H23: =IF(H$5>BLN,"",SUMIF(MUTASI!$B$6:$B$45,"Biaya Sewa Tempat",MUTASI!$J$6:$J$45)) -> 0 | I23: =IF(I$5>BLN,"",SUMIF(MUTASI!$B$6:$B$45,"Biaya Sewa Tempat",MUTASI!$K$6:$K$45)) -> 10000000 | J23: =IF(J$5>BLN,"",SUMIF(MUTASI!$B$6:$B$45,"Biaya Sewa Tempat",MUTASI!$L$6:$L$45)) -> 10000000 | K23: =IF(K$5>BLN,"",SUMIF(MUTASI!$B$6:$B$45,"Biaya Sewa Tempat",MUTASI!$M$6:$M$45)) -> 10000000 | L23: =IF(L$5>BLN,"",SUMIF(MUTASI!$B$6:$B$45,"Biaya Sewa Tempat",MUTASI!$N$6:$N$45)) | M23: =IF(M$5>BLN,"",SUMIF(MUTASI!$B$6:$B$45,"Biaya Sewa Tempat",MUTASI!$O$6:$O$45)) | N23: =IF(N$5>BLN,"",SUMIF(MUTASI!$B$6:$B$45,"Biaya Sewa Tempat",MUTASI!$P$6:$P$45)) | O23: =SUMIF(MUTASI!$B$6:$B$45,"Biaya Sewa Tempat",MUTASI!$R$6:$R$45) -> 80000000 | P23: =IFERROR(O23/O11,"") -> 0.10056494
B24: Listrik, air, internet & langganan | C24: =IF(C$5>BLN,"",SUMIF(MUTASI!$B$6:$B$45,"Biaya Tagihan Bulanan",MUTASI!$E$6:$E$45)) -> 4619448 | D24: =IF(D$5>BLN,"",SUMIF(MUTASI!$B$6:$B$45,"Biaya Tagihan Bulanan",MUTASI!$F$6:$F$45)) -> 4511384 | E24: =IF(E$5>BLN,"",SUMIF(MUTASI!$B$6:$B$45,"Biaya Tagihan Bulanan",MUTASI!$G$6:$G$45)) -> 4663782 | F24: =IF(F$5>BLN,"",SUMIF(MUTASI!$B$6:$B$45,"Biaya Tagihan Bulanan",MUTASI!$H$6:$H$45)) -> 4957412 | G24: =IF(G$5>BLN,"",SUMIF(MUTASI!$B$6:$B$45,"Biaya Tagihan Bulanan",MUTASI!$I$6:$I$45)) -> 5262141 | H24: =IF(H$5>BLN,"",SUMIF(MUTASI!$B$6:$B$45,"Biaya Tagihan Bulanan",MUTASI!$J$6:$J$45)) -> 5146765 | I24: =IF(I$5>BLN,"",SUMIF(MUTASI!$B$6:$B$45,"Biaya Tagihan Bulanan",MUTASI!$K$6:$K$45)) -> 5525230 | J24: =IF(J$5>BLN,"",SUMIF(MUTASI!$B$6:$B$45,"Biaya Tagihan Bulanan",MUTASI!$L$6:$L$45)) -> 5414662 | K24: =IF(K$5>BLN,"",SUMIF(MUTASI!$B$6:$B$45,"Biaya Tagihan Bulanan",MUTASI!$M$6:$M$45)) -> 5336097 | L24: =IF(L$5>BLN,"",SUMIF(MUTASI!$B$6:$B$45,"Biaya Tagihan Bulanan",MUTASI!$N$6:$N$45)) | M24: =IF(M$5>BLN,"",SUMIF(MUTASI!$B$6:$B$45,"Biaya Tagihan Bulanan",MUTASI!$O$6:$O$45)) | N24: =IF(N$5>BLN,"",SUMIF(MUTASI!$B$6:$B$45,"Biaya Tagihan Bulanan",MUTASI!$P$6:$P$45)) | O24: =SUMIF(MUTASI!$B$6:$B$45,"Biaya Tagihan Bulanan",MUTASI!$R$6:$R$45) -> 45436921 | P24: =IFERROR(O24/O11,"") -> 0.057117013
B25: Marketing, promosi & event | C25: =IF(C$5>BLN,"",SUMIF(MUTASI!$B$6:$B$45,"Biaya Marketing & Promosi",MUTASI!$E$6:$E$45)) -> 64039154 | D25: =IF(D$5>BLN,"",SUMIF(MUTASI!$B$6:$B$45,"Biaya Marketing & Promosi",MUTASI!$F$6:$F$45)) -> 41301 | E25: =IF(E$5>BLN,"",SUMIF(MUTASI!$B$6:$B$45,"Biaya Marketing & Promosi",MUTASI!$G$6:$G$45)) -> 0 | F25: =IF(F$5>BLN,"",SUMIF(MUTASI!$B$6:$B$45,"Biaya Marketing & Promosi",MUTASI!$H$6:$H$45)) -> 2369540 | G25: =IF(G$5>BLN,"",SUMIF(MUTASI!$B$6:$B$45,"Biaya Marketing & Promosi",MUTASI!$I$6:$I$45)) -> 1047000 | H25: =IF(H$5>BLN,"",SUMIF(MUTASI!$B$6:$B$45,"Biaya Marketing & Promosi",MUTASI!$J$6:$J$45)) -> 2470003 | I25: =IF(I$5>BLN,"",SUMIF(MUTASI!$B$6:$B$45,"Biaya Marketing & Promosi",MUTASI!$K$6:$K$45)) -> 2546500 | J25: =IF(J$5>BLN,"",SUMIF(MUTASI!$B$6:$B$45,"Biaya Marketing & Promosi",MUTASI!$L$6:$L$45)) -> 1705000 | K25: =IF(K$5>BLN,"",SUMIF(MUTASI!$B$6:$B$45,"Biaya Marketing & Promosi",MUTASI!$M$6:$M$45)) -> 4974800 | L25: =IF(L$5>BLN,"",SUMIF(MUTASI!$B$6:$B$45,"Biaya Marketing & Promosi",MUTASI!$N$6:$N$45)) | M25: =IF(M$5>BLN,"",SUMIF(MUTASI!$B$6:$B$45,"Biaya Marketing & Promosi",MUTASI!$O$6:$O$45)) | N25: =IF(N$5>BLN,"",SUMIF(MUTASI!$B$6:$B$45,"Biaya Marketing & Promosi",MUTASI!$P$6:$P$45)) | O25: =SUMIF(MUTASI!$B$6:$B$45,"Biaya Marketing & Promosi",MUTASI!$R$6:$R$45) -> 79193298 | P25: =IFERROR(O25/O11,"") -> 0.099550862
B26: Perlengkapan | C26: =IF(C$5>BLN,"",SUMIF(MUTASI!$B$6:$B$45,"Beban Perlengkapan",MUTASI!$E$6:$E$45)) -> 755900 | D26: =IF(D$5>BLN,"",SUMIF(MUTASI!$B$6:$B$45,"Beban Perlengkapan",MUTASI!$F$6:$F$45)) -> 328832 | E26: =IF(E$5>BLN,"",SUMIF(MUTASI!$B$6:$B$45,"Beban Perlengkapan",MUTASI!$G$6:$G$45)) -> 1468366 | F26: =IF(F$5>BLN,"",SUMIF(MUTASI!$B$6:$B$45,"Beban Perlengkapan",MUTASI!$H$6:$H$45)) -> 2041399 | G26: =IF(G$5>BLN,"",SUMIF(MUTASI!$B$6:$B$45,"Beban Perlengkapan",MUTASI!$I$6:$I$45)) -> 369584 | H26: =IF(H$5>BLN,"",SUMIF(MUTASI!$B$6:$B$45,"Beban Perlengkapan",MUTASI!$J$6:$J$45)) -> 1179010 | I26: =IF(I$5>BLN,"",SUMIF(MUTASI!$B$6:$B$45,"Beban Perlengkapan",MUTASI!$K$6:$K$45)) -> 1465476 | J26: =IF(J$5>BLN,"",SUMIF(MUTASI!$B$6:$B$45,"Beban Perlengkapan",MUTASI!$L$6:$L$45)) -> 2645674 | K26: =IF(K$5>BLN,"",SUMIF(MUTASI!$B$6:$B$45,"Beban Perlengkapan",MUTASI!$M$6:$M$45)) -> 3178772 | L26: =IF(L$5>BLN,"",SUMIF(MUTASI!$B$6:$B$45,"Beban Perlengkapan",MUTASI!$N$6:$N$45)) | M26: =IF(M$5>BLN,"",SUMIF(MUTASI!$B$6:$B$45,"Beban Perlengkapan",MUTASI!$O$6:$O$45)) | N26: =IF(N$5>BLN,"",SUMIF(MUTASI!$B$6:$B$45,"Beban Perlengkapan",MUTASI!$P$6:$P$45)) | O26: =SUMIF(MUTASI!$B$6:$B$45,"Beban Perlengkapan",MUTASI!$R$6:$R$45) -> 13433013 | P26: =IFERROR(O26/O11,"") -> 0.016886126
B27: Operasional harian | C27: =IF(C$5>BLN,"",SUMIF(MUTASI!$B$6:$B$45,"Biaya Operasional Harian",MUTASI!$E$6:$E$45)) -> 549900 | D27: =IF(D$5>BLN,"",SUMIF(MUTASI!$B$6:$B$45,"Biaya Operasional Harian",MUTASI!$F$6:$F$45)) -> 75000 | E27: =IF(E$5>BLN,"",SUMIF(MUTASI!$B$6:$B$45,"Biaya Operasional Harian",MUTASI!$G$6:$G$45)) -> 1282180 | F27: =IF(F$5>BLN,"",SUMIF(MUTASI!$B$6:$B$45,"Biaya Operasional Harian",MUTASI!$H$6:$H$45)) -> 452500 | G27: =IF(G$5>BLN,"",SUMIF(MUTASI!$B$6:$B$45,"Biaya Operasional Harian",MUTASI!$I$6:$I$45)) -> 634500 | H27: =IF(H$5>BLN,"",SUMIF(MUTASI!$B$6:$B$45,"Biaya Operasional Harian",MUTASI!$J$6:$J$45)) -> 521500 | I27: =IF(I$5>BLN,"",SUMIF(MUTASI!$B$6:$B$45,"Biaya Operasional Harian",MUTASI!$K$6:$K$45)) -> 450000 | J27: =IF(J$5>BLN,"",SUMIF(MUTASI!$B$6:$B$45,"Biaya Operasional Harian",MUTASI!$L$6:$L$45)) -> 310000 | K27: =IF(K$5>BLN,"",SUMIF(MUTASI!$B$6:$B$45,"Biaya Operasional Harian",MUTASI!$M$6:$M$45)) -> 620500 | L27: =IF(L$5>BLN,"",SUMIF(MUTASI!$B$6:$B$45,"Biaya Operasional Harian",MUTASI!$N$6:$N$45)) | M27: =IF(M$5>BLN,"",SUMIF(MUTASI!$B$6:$B$45,"Biaya Operasional Harian",MUTASI!$O$6:$O$45)) | N27: =IF(N$5>BLN,"",SUMIF(MUTASI!$B$6:$B$45,"Biaya Operasional Harian",MUTASI!$P$6:$P$45)) | O27: =SUMIF(MUTASI!$B$6:$B$45,"Biaya Operasional Harian",MUTASI!$R$6:$R$45) -> 4896080 | P27: =IFERROR(O27/O11,"") -> 0.0061546746
B28: Pemeliharaan | C28: =IF(C$5>BLN,"",SUMIF(MUTASI!$B$6:$B$45,"Biaya Pemeliharaan",MUTASI!$E$6:$E$45)) -> 3059350 | D28: =IF(D$5>BLN,"",SUMIF(MUTASI!$B$6:$B$45,"Biaya Pemeliharaan",MUTASI!$F$6:$F$45)) -> 78500 | E28: =IF(E$5>BLN,"",SUMIF(MUTASI!$B$6:$B$45,"Biaya Pemeliharaan",MUTASI!$G$6:$G$45)) -> 446000 | F28: =IF(F$5>BLN,"",SUMIF(MUTASI!$B$6:$B$45,"Biaya Pemeliharaan",MUTASI!$H$6:$H$45)) -> 536010 | G28: =IF(G$5>BLN,"",SUMIF(MUTASI!$B$6:$B$45,"Biaya Pemeliharaan",MUTASI!$I$6:$I$45)) -> 3680848 | H28: =IF(H$5>BLN,"",SUMIF(MUTASI!$B$6:$B$45,"Biaya Pemeliharaan",MUTASI!$J$6:$J$45)) -> 4333387 | I28: =IF(I$5>BLN,"",SUMIF(MUTASI!$B$6:$B$45,"Biaya Pemeliharaan",MUTASI!$K$6:$K$45)) -> 1214000 | J28: =IF(J$5>BLN,"",SUMIF(MUTASI!$B$6:$B$45,"Biaya Pemeliharaan",MUTASI!$L$6:$L$45)) -> 0 | K28: =IF(K$5>BLN,"",SUMIF(MUTASI!$B$6:$B$45,"Biaya Pemeliharaan",MUTASI!$M$6:$M$45)) -> 210000 | L28: =IF(L$5>BLN,"",SUMIF(MUTASI!$B$6:$B$45,"Biaya Pemeliharaan",MUTASI!$N$6:$N$45)) | M28: =IF(M$5>BLN,"",SUMIF(MUTASI!$B$6:$B$45,"Biaya Pemeliharaan",MUTASI!$O$6:$O$45)) | N28: =IF(N$5>BLN,"",SUMIF(MUTASI!$B$6:$B$45,"Biaya Pemeliharaan",MUTASI!$P$6:$P$45)) | O28: =SUMIF(MUTASI!$B$6:$B$45,"Biaya Pemeliharaan",MUTASI!$R$6:$R$45) -> 13558095 | P28: =IFERROR(O28/O11,"") -> 0.017043362
B29: Compliment | C29: =IF(C$5>BLN,"",SUMIF(MUTASI!$B$6:$B$45,"Biaya Compliment",MUTASI!$E$6:$E$45)) -> 1220000 | D29: =IF(D$5>BLN,"",SUMIF(MUTASI!$B$6:$B$45,"Biaya Compliment",MUTASI!$F$6:$F$45)) -> 339300 | E29: =IF(E$5>BLN,"",SUMIF(MUTASI!$B$6:$B$45,"Biaya Compliment",MUTASI!$G$6:$G$45)) -> 282300 | F29: =IF(F$5>BLN,"",SUMIF(MUTASI!$B$6:$B$45,"Biaya Compliment",MUTASI!$H$6:$H$45)) -> 986000 | G29: =IF(G$5>BLN,"",SUMIF(MUTASI!$B$6:$B$45,"Biaya Compliment",MUTASI!$I$6:$I$45)) -> 96000 | H29: =IF(H$5>BLN,"",SUMIF(MUTASI!$B$6:$B$45,"Biaya Compliment",MUTASI!$J$6:$J$45)) -> 166300 | I29: =IF(I$5>BLN,"",SUMIF(MUTASI!$B$6:$B$45,"Biaya Compliment",MUTASI!$K$6:$K$45)) -> 432900 | J29: =IF(J$5>BLN,"",SUMIF(MUTASI!$B$6:$B$45,"Biaya Compliment",MUTASI!$L$6:$L$45)) -> 642600 | K29: =IF(K$5>BLN,"",SUMIF(MUTASI!$B$6:$B$45,"Biaya Compliment",MUTASI!$M$6:$M$45)) -> 314600 | L29: =IF(L$5>BLN,"",SUMIF(MUTASI!$B$6:$B$45,"Biaya Compliment",MUTASI!$N$6:$N$45)) | M29: =IF(M$5>BLN,"",SUMIF(MUTASI!$B$6:$B$45,"Biaya Compliment",MUTASI!$O$6:$O$45)) | N29: =IF(N$5>BLN,"",SUMIF(MUTASI!$B$6:$B$45,"Biaya Compliment",MUTASI!$P$6:$P$45)) | O29: =SUMIF(MUTASI!$B$6:$B$45,"Biaya Compliment",MUTASI!$R$6:$R$45) -> 4480000 | P29: =IFERROR(O29/O11,"") -> 0.0056316364
B30: Riset & pengembangan menu | C30: =IF(C$5>BLN,"",SUMIF(MUTASI!$B$6:$B$45,"Biaya R&D",MUTASI!$E$6:$E$45)) -> 0 | D30: =IF(D$5>BLN,"",SUMIF(MUTASI!$B$6:$B$45,"Biaya R&D",MUTASI!$F$6:$F$45)) -> 0 | E30: =IF(E$5>BLN,"",SUMIF(MUTASI!$B$6:$B$45,"Biaya R&D",MUTASI!$G$6:$G$45)) -> 0 | F30: =IF(F$5>BLN,"",SUMIF(MUTASI!$B$6:$B$45,"Biaya R&D",MUTASI!$H$6:$H$45)) -> 0 | G30: =IF(G$5>BLN,"",SUMIF(MUTASI!$B$6:$B$45,"Biaya R&D",MUTASI!$I$6:$I$45)) -> 0 | H30: =IF(H$5>BLN,"",SUMIF(MUTASI!$B$6:$B$45,"Biaya R&D",MUTASI!$J$6:$J$45)) -> 0 | I30: =IF(I$5>BLN,"",SUMIF(MUTASI!$B$6:$B$45,"Biaya R&D",MUTASI!$K$6:$K$45)) -> 0 | J30: =IF(J$5>BLN,"",SUMIF(MUTASI!$B$6:$B$45,"Biaya R&D",MUTASI!$L$6:$L$45)) -> 0 | K30: =IF(K$5>BLN,"",SUMIF(MUTASI!$B$6:$B$45,"Biaya R&D",MUTASI!$M$6:$M$45)) -> 0 | L30: =IF(L$5>BLN,"",SUMIF(MUTASI!$B$6:$B$45,"Biaya R&D",MUTASI!$N$6:$N$45)) | M30: =IF(M$5>BLN,"",SUMIF(MUTASI!$B$6:$B$45,"Biaya R&D",MUTASI!$O$6:$O$45)) | N30: =IF(N$5>BLN,"",SUMIF(MUTASI!$B$6:$B$45,"Biaya R&D",MUTASI!$P$6:$P$45)) | O30: =SUMIF(MUTASI!$B$6:$B$45,"Biaya R&D",MUTASI!$R$6:$R$45) -> 0 | P30: =IFERROR(O30/O11,"") -> 0
B31: Dana sosial & CSR | C31: =IF(C$5>BLN,"",SUMIF(MUTASI!$B$6:$B$45,"Dana Sosial & CSR",MUTASI!$E$6:$E$45)) -> 2800000 | D31: =IF(D$5>BLN,"",SUMIF(MUTASI!$B$6:$B$45,"Dana Sosial & CSR",MUTASI!$F$6:$F$45)) -> 980000 | E31: =IF(E$5>BLN,"",SUMIF(MUTASI!$B$6:$B$45,"Dana Sosial & CSR",MUTASI!$G$6:$G$45)) -> 1440000 | F31: =IF(F$5>BLN,"",SUMIF(MUTASI!$B$6:$B$45,"Dana Sosial & CSR",MUTASI!$H$6:$H$45)) -> 800000 | G31: =IF(G$5>BLN,"",SUMIF(MUTASI!$B$6:$B$45,"Dana Sosial & CSR",MUTASI!$I$6:$I$45)) -> 1030000 | H31: =IF(H$5>BLN,"",SUMIF(MUTASI!$B$6:$B$45,"Dana Sosial & CSR",MUTASI!$J$6:$J$45)) -> 850000 | I31: =IF(I$5>BLN,"",SUMIF(MUTASI!$B$6:$B$45,"Dana Sosial & CSR",MUTASI!$K$6:$K$45)) -> 1860000 | J31: =IF(J$5>BLN,"",SUMIF(MUTASI!$B$6:$B$45,"Dana Sosial & CSR",MUTASI!$L$6:$L$45)) -> 1235000 | K31: =IF(K$5>BLN,"",SUMIF(MUTASI!$B$6:$B$45,"Dana Sosial & CSR",MUTASI!$M$6:$M$45)) -> 839000 | L31: =IF(L$5>BLN,"",SUMIF(MUTASI!$B$6:$B$45,"Dana Sosial & CSR",MUTASI!$N$6:$N$45)) | M31: =IF(M$5>BLN,"",SUMIF(MUTASI!$B$6:$B$45,"Dana Sosial & CSR",MUTASI!$O$6:$O$45)) | N31: =IF(N$5>BLN,"",SUMIF(MUTASI!$B$6:$B$45,"Dana Sosial & CSR",MUTASI!$P$6:$P$45)) | O31: =SUMIF(MUTASI!$B$6:$B$45,"Dana Sosial & CSR",MUTASI!$R$6:$R$45) -> 11834000 | P31: =IFERROR(O31/O11,"") -> 0.014876068
B32: Penyusutan peralatan | C32: =IF(C$5>BLN,"",SUMIF(MUTASI!$B$6:$B$45,"Beban Penyusutan Peralatan",MUTASI!$E$6:$E$45)) -> 0 | D32: =IF(D$5>BLN,"",SUMIF(MUTASI!$B$6:$B$45,"Beban Penyusutan Peralatan",MUTASI!$F$6:$F$45)) -> 216667 | E32: =IF(E$5>BLN,"",SUMIF(MUTASI!$B$6:$B$45,"Beban Penyusutan Peralatan",MUTASI!$G$6:$G$45)) -> 216667 | F32: =IF(F$5>BLN,"",SUMIF(MUTASI!$B$6:$B$45,"Beban Penyusutan Peralatan",MUTASI!$H$6:$H$45)) -> 252964 | G32: =IF(G$5>BLN,"",SUMIF(MUTASI!$B$6:$B$45,"Beban Penyusutan Peralatan",MUTASI!$I$6:$I$45)) -> 260452 | H32: =IF(H$5>BLN,"",SUMIF(MUTASI!$B$6:$B$45,"Beban Penyusutan Peralatan",MUTASI!$J$6:$J$45)) -> 297787 | I32: =IF(I$5>BLN,"",SUMIF(MUTASI!$B$6:$B$45,"Beban Penyusutan Peralatan",MUTASI!$K$6:$K$45)) -> 399853 | J32: =IF(J$5>BLN,"",SUMIF(MUTASI!$B$6:$B$45,"Beban Penyusutan Peralatan",MUTASI!$L$6:$L$45)) -> 426400 | K32: =IF(K$5>BLN,"",SUMIF(MUTASI!$B$6:$B$45,"Beban Penyusutan Peralatan",MUTASI!$M$6:$M$45)) -> 493329 | L32: =IF(L$5>BLN,"",SUMIF(MUTASI!$B$6:$B$45,"Beban Penyusutan Peralatan",MUTASI!$N$6:$N$45)) | M32: =IF(M$5>BLN,"",SUMIF(MUTASI!$B$6:$B$45,"Beban Penyusutan Peralatan",MUTASI!$O$6:$O$45)) | N32: =IF(N$5>BLN,"",SUMIF(MUTASI!$B$6:$B$45,"Beban Penyusutan Peralatan",MUTASI!$P$6:$P$45)) | O32: =SUMIF(MUTASI!$B$6:$B$45,"Beban Penyusutan Peralatan",MUTASI!$R$6:$R$45) -> 2564119 | P32: =IFERROR(O32/O11,"") -> 0.0032232558
B33: Total beban usaha | C33: =IF(C$5>BLN,"",N(C22)+N(C23)+N(C24)+N(C25)+N(C26)+N(C27)+N(C28)+N(C29)+N(C30)+N(C31)+N(C32)) -> 112673752 | D33: =IF(D$5>BLN,"",N(D22)+N(D23)+N(D24)+N(D25)+N(D26)+N(D27)+N(D28)+N(D29)+N(D30)+N(D31)+N(D32)) -> 43265484 | E33: =IF(E$5>BLN,"",N(E22)+N(E23)+N(E24)+N(E25)+N(E26)+N(E27)+N(E28)+N(E29)+N(E30)+N(E31)+N(E32)) -> 62701295 | F33: =IF(F$5>BLN,"",N(F22)+N(F23)+N(F24)+N(F25)+N(F26)+N(F27)+N(F28)+N(F29)+N(F30)+N(F31)+N(F32)) -> 49661825 | G33: =IF(G$5>BLN,"",N(G22)+N(G23)+N(G24)+N(G25)+N(G26)+N(G27)+N(G28)+N(G29)+N(G30)+N(G31)+N(G32)) -> 51785858 | H33: =IF(H$5>BLN,"",N(H22)+N(H23)+N(H24)+N(H25)+N(H26)+N(H27)+N(H28)+N(H29)+N(H30)+N(H31)+N(H32)) -> 45258085 | I33: =IF(I$5>BLN,"",N(I22)+N(I23)+N(I24)+N(I25)+N(I26)+N(I27)+N(I28)+N(I29)+N(I30)+N(I31)+N(I32)) -> 46655292 | J33: =IF(J$5>BLN,"",N(J22)+N(J23)+N(J24)+N(J25)+N(J26)+N(J27)+N(J28)+N(J29)+N(J30)+N(J31)+N(J32)) -> 46548669 | ... N33: =IF(N$5>BLN,"",N(N22)+N(N23)+N(N24)+N(N25)+N(N26)+N(N27)+N(N28)+N(N29)+N(N30)+N(N31)+N(N32)) | O33: =N(O22)+N(O23)+N(O24)+N(O25)+N(O26)+N(O27)+N(O28)+N(O29)+N(O30)+N(O31)+N(O32) -> 509309691 | P33: =IFERROR(O33/O11,"") -> 0.64023371
B35: LABA (RUGI) USAHA | C35: =IF(C$5>BLN,"",N(C18)-N(C33)) -> -50561070 | D35: =IF(D$5>BLN,"",N(D18)-N(D33)) -> -6187851 | E35: =IF(E$5>BLN,"",N(E18)-N(E33)) -> -2534461 | F35: =IF(F$5>BLN,"",N(F18)-N(F33)) -> -19875895 | G35: =IF(G$5>BLN,"",N(G18)-N(G33)) -> 15983838 | H35: =IF(H$5>BLN,"",N(H18)-N(H33)) -> 5422499 | I35: =IF(I$5>BLN,"",N(I18)-N(I33)) -> 4808159 | J35: =IF(J$5>BLN,"",N(J18)-N(J33)) -> 18200068 | ... N35: =IF(N$5>BLN,"",N(N18)-N(N33)) | O35: =N(O18)-N(O33) -> -52383323 | P35: =IFERROR(O35/O11,"") -> -0.065849069
B36: EBITDA (laba usaha + penyusutan) | C36: =IF(C$5>BLN,"",N(C35)+N(C32)) -> -50561070 | D36: =IF(D$5>BLN,"",N(D35)+N(D32)) -> -5971184 | E36: =IF(E$5>BLN,"",N(E35)+N(E32)) -> -2317794 | F36: =IF(F$5>BLN,"",N(F35)+N(F32)) -> -19622931 | G36: =IF(G$5>BLN,"",N(G35)+N(G32)) -> 16244290 | H36: =IF(H$5>BLN,"",N(H35)+N(H32)) -> 5720286 | I36: =IF(I$5>BLN,"",N(I35)+N(I32)) -> 5208012 | J36: =IF(J$5>BLN,"",N(J35)+N(J32)) -> 18626468 | ... N36: =IF(N$5>BLN,"",N(N35)+N(N32)) | O36: =N(O35)+N(O32) -> -49819204 | P36: =IFERROR(O36/O11,"") -> -0.062625813
B38: PENDAPATAN (BEBAN) LAIN-LAIN
B39: Pendapatan lain-lain | C39: =IF(C$5>BLN,"",-SUMIF(MUTASI!$B$6:$B$45,"Pendapatan Lainnya",MUTASI!$E$6:$E$45)) -> 104748 | D39: =IF(D$5>BLN,"",-SUMIF(MUTASI!$B$6:$B$45,"Pendapatan Lainnya",MUTASI!$F$6:$F$45)) -> 165632 | E39: =IF(E$5>BLN,"",-SUMIF(MUTASI!$B$6:$B$45,"Pendapatan Lainnya",MUTASI!$G$6:$G$45)) -> 219302 | F39: =IF(F$5>BLN,"",-SUMIF(MUTASI!$B$6:$B$45,"Pendapatan Lainnya",MUTASI!$H$6:$H$45)) -> 447496 | G39: =IF(G$5>BLN,"",-SUMIF(MUTASI!$B$6:$B$45,"Pendapatan Lainnya",MUTASI!$I$6:$I$45)) -> 133847 | H39: =IF(H$5>BLN,"",-SUMIF(MUTASI!$B$6:$B$45,"Pendapatan Lainnya",MUTASI!$J$6:$J$45)) -> 1016 | I39: =IF(I$5>BLN,"",-SUMIF(MUTASI!$B$6:$B$45,"Pendapatan Lainnya",MUTASI!$K$6:$K$45)) -> 26330 | J39: =IF(J$5>BLN,"",-SUMIF(MUTASI!$B$6:$B$45,"Pendapatan Lainnya",MUTASI!$L$6:$L$45)) -> 104920 | K39: =IF(K$5>BLN,"",-SUMIF(MUTASI!$B$6:$B$45,"Pendapatan Lainnya",MUTASI!$M$6:$M$45)) -> 13449 | L39: =IF(L$5>BLN,"",-SUMIF(MUTASI!$B$6:$B$45,"Pendapatan Lainnya",MUTASI!$N$6:$N$45)) | M39: =IF(M$5>BLN,"",-SUMIF(MUTASI!$B$6:$B$45,"Pendapatan Lainnya",MUTASI!$O$6:$O$45)) | N39: =IF(N$5>BLN,"",-SUMIF(MUTASI!$B$6:$B$45,"Pendapatan Lainnya",MUTASI!$P$6:$P$45)) | O39: =-SUMIF(MUTASI!$B$6:$B$45,"Pendapatan Lainnya",MUTASI!$R$6:$R$45) -> 1216740 | P39: =IFERROR(O39/O11,"") -> 0.0015295173
B40: Beban lain-lain (admin bank, denda) | C40: =IF(C$5>BLN,"",SUMIF(MUTASI!$B$6:$B$45,"Biaya Lainnya",MUTASI!$E$6:$E$45)) -> 691719 | D40: =IF(D$5>BLN,"",SUMIF(MUTASI!$B$6:$B$45,"Biaya Lainnya",MUTASI!$F$6:$F$45)) -> 189899 | E40: =IF(E$5>BLN,"",SUMIF(MUTASI!$B$6:$B$45,"Biaya Lainnya",MUTASI!$G$6:$G$45)) -> 1088138 | F40: =IF(F$5>BLN,"",SUMIF(MUTASI!$B$6:$B$45,"Biaya Lainnya",MUTASI!$H$6:$H$45)) -> 979111 | G40: =IF(G$5>BLN,"",SUMIF(MUTASI!$B$6:$B$45,"Biaya Lainnya",MUTASI!$I$6:$I$45)) -> 37309 | H40: =IF(H$5>BLN,"",SUMIF(MUTASI!$B$6:$B$45,"Biaya Lainnya",MUTASI!$J$6:$J$45)) -> 41481 | I40: =IF(I$5>BLN,"",SUMIF(MUTASI!$B$6:$B$45,"Biaya Lainnya",MUTASI!$K$6:$K$45)) -> 38480 | J40: =IF(J$5>BLN,"",SUMIF(MUTASI!$B$6:$B$45,"Biaya Lainnya",MUTASI!$L$6:$L$45)) -> 579041 | K40: =IF(K$5>BLN,"",SUMIF(MUTASI!$B$6:$B$45,"Biaya Lainnya",MUTASI!$M$6:$M$45)) -> 184941 | L40: =IF(L$5>BLN,"",SUMIF(MUTASI!$B$6:$B$45,"Biaya Lainnya",MUTASI!$N$6:$N$45)) | M40: =IF(M$5>BLN,"",SUMIF(MUTASI!$B$6:$B$45,"Biaya Lainnya",MUTASI!$O$6:$O$45)) | N40: =IF(N$5>BLN,"",SUMIF(MUTASI!$B$6:$B$45,"Biaya Lainnya",MUTASI!$P$6:$P$45)) | O40: =SUMIF(MUTASI!$B$6:$B$45,"Biaya Lainnya",MUTASI!$R$6:$R$45) -> 3830119 | P40: =IFERROR(O40/O11,"") -> 0.0048146959
B41: Total lain-lain bersih | C41: =IF(C$5>BLN,"",N(C39)-N(C40)) -> -586971 | D41: =IF(D$5>BLN,"",N(D39)-N(D40)) -> -24267 | E41: =IF(E$5>BLN,"",N(E39)-N(E40)) -> -868836 | F41: =IF(F$5>BLN,"",N(F39)-N(F40)) -> -531615 | G41: =IF(G$5>BLN,"",N(G39)-N(G40)) -> 96538 | H41: =IF(H$5>BLN,"",N(H39)-N(H40)) -> -40465 | I41: =IF(I$5>BLN,"",N(I39)-N(I40)) -> -12150 | J41: =IF(J$5>BLN,"",N(J39)-N(J40)) -> -474121 | ... N41: =IF(N$5>BLN,"",N(N39)-N(N40)) | O41: =N(O39)-N(O40) -> -2613379 | P41: =IFERROR(O41/O11,"") -> -0.0032851786
B43: LABA (RUGI) BERSIH | C43: =IF(C$5>BLN,"",N(C35)+N(C41)) -> -51148041 | D43: =IF(D$5>BLN,"",N(D35)+N(D41)) -> -6212118 | E43: =IF(E$5>BLN,"",N(E35)+N(E41)) -> -3403297 | F43: =IF(F$5>BLN,"",N(F35)+N(F41)) -> -20407510 | G43: =IF(G$5>BLN,"",N(G35)+N(G41)) -> 16080376 | H43: =IF(H$5>BLN,"",N(H35)+N(H41)) -> 5382034 | I43: =IF(I$5>BLN,"",N(I35)+N(I41)) -> 4796009 | J43: =IF(J$5>BLN,"",N(J35)+N(J41)) -> 17725947 | ... N43: =IF(N$5>BLN,"",N(N35)+N(N41)) | O43: =N(O35)+N(O41) -> -54996702 | P43: =IFERROR(O43/O11,"") -> -0.069134248
B44: Margin laba bersih | C44: =IF(C$5>BLN,"",IFERROR((N(C43))/C11,"")) -> -0.56654281 | D44: =IF(D$5>BLN,"",IFERROR((N(D43))/D11,"")) -> -0.090938309 | E44: =IF(E$5>BLN,"",IFERROR((N(E43))/E11,"")) -> -0.036514487 | F44: =IF(F$5>BLN,"",IFERROR((N(F43))/F11,"")) -> -0.23742162 | G44: =IF(G$5>BLN,"",IFERROR((N(G43))/G11,"")) -> 0.15688957 | H44: =IF(H$5>BLN,"",IFERROR((N(H43))/H11,"")) -> 0.056169875 | I44: =IF(I$5>BLN,"",IFERROR((N(I43))/I11,"")) -> 0.056171528 | J44: =IF(J$5>BLN,"",IFERROR((N(J43))/J11,"")) -> 0.20179409 | ... N44: =IF(N$5>BLN,"",IFERROR((N(N43))/N11,"")) | O44: =IFERROR((N(O43))/O11,"") -> -0.069134248
B46: INDIKATOR BIAYA (terhadap pendapatan bersih)
B47: Food cost (HPP) | C47: =IF(C$5>BLN,"",IFERROR((N(C16))/C11,"")) -> 0.31200702 | D47: =IF(D$5>BLN,"",IFERROR((N(D16))/D11,"")) -> 0.45722582 | E47: =IF(E$5>BLN,"",IFERROR((N(E16))/E11,"")) -> 0.35446096 | F47: =IF(F$5>BLN,"",IFERROR((N(F16))/F11,"")) -> 0.65346954 | G47: =IF(G$5>BLN,"",IFERROR((N(G16))/G11,"")) -> 0.33879914 | H47: =IF(H$5>BLN,"",IFERROR((N(H16))/H11,"")) -> 0.47106948 | I47: =IF(I$5>BLN,"",IFERROR((N(I16))/I11,"")) -> 0.39725287 | J47: =IF(J$5>BLN,"",IFERROR((N(J16))/J11,"")) -> 0.26289342 | ... N47: =IF(N$5>BLN,"",IFERROR((N(N16))/N11,"")) | O47: =IFERROR((N(O16))/O11,"") -> 0.42561536
B48: Payroll (gaji) | C48: =IF(C$5>BLN,"",IFERROR((N(C22))/C11,"")) -> 0.28389146 | D48: =IF(D$5>BLN,"",IFERROR((N(D22))/D11,"")) -> 0.39077698 | E48: =IF(E$5>BLN,"",IFERROR((N(E22))/E11,"")) -> 0.46030203 | F48: =IF(F$5>BLN,"",IFERROR((N(F22))/F11,"")) -> 0.31721351 | G48: =IF(G$5>BLN,"",IFERROR((N(G22))/G11,"")) -> 0.28689566 | H48: =IF(H$5>BLN,"",IFERROR((N(H22))/H11,"")) -> 0.31615793 | I48: =IF(I$5>BLN,"",IFERROR((N(I22))/I11,"")) -> 0.26658391 | J48: =IF(J$5>BLN,"",IFERROR((N(J22))/J11,"")) -> 0.27514628 | ... N48: =IF(N$5>BLN,"",IFERROR((N(N22))/N11,"")) | O48: =IFERROR((N(O22))/O11,"") -> 0.31918577
B49: Occupancy (sewa) | C49: =IF(C$5>BLN,"",IFERROR((N(C23))/C11,"")) -> 0.1107653 | D49: =IF(D$5>BLN,"",IFERROR((N(D23))/D11,"")) -> 0.14638857 | E49: =IF(E$5>BLN,"",IFERROR((N(E23))/E11,"")) -> 0.10729151 | F49: =IF(F$5>BLN,"",IFERROR((N(F23))/F11,"")) -> 0.11634032 | G49: =IF(G$5>BLN,"",IFERROR((N(G23))/G11,"")) -> 0.09756586 | H49: =IF(H$5>BLN,"",IFERROR((N(H23))/H11,"")) -> 0 | I49: =IF(I$5>BLN,"",IFERROR((N(I23))/I11,"")) -> 0.1171214 | J49: =IF(J$5>BLN,"",IFERROR((N(J23))/J11,"")) -> 0.11384107 | ... N49: =IF(N$5>BLN,"",IFERROR((N(N23))/N11,"")) | O49: =IFERROR((N(O23))/O11,"") -> 0.10056494
B50: Prime cost (HPP + gaji) | C50: =IF(C$5>BLN,"",IFERROR((N(C16)+N(C22))/C11,"")) -> 0.59589848 | D50: =IF(D$5>BLN,"",IFERROR((N(D16)+N(D22))/D11,"")) -> 0.8480028 | E50: =IF(E$5>BLN,"",IFERROR((N(E16)+N(E22))/E11,"")) -> 0.81476299 | F50: =IF(F$5>BLN,"",IFERROR((N(F16)+N(F22))/F11,"")) -> 0.97068305 | G50: =IF(G$5>BLN,"",IFERROR((N(G16)+N(G22))/G11,"")) -> 0.62569479 | H50: =IF(H$5>BLN,"",IFERROR((N(H16)+N(H22))/H11,"")) -> 0.78722741 | I50: =IF(I$5>BLN,"",IFERROR((N(I16)+N(I22))/I11,"")) -> 0.66383678 | J50: =IF(J$5>BLN,"",IFERROR((N(J16)+N(J22))/J11,"")) -> 0.5380397 | ... N50: =IF(N$5>BLN,"",IFERROR((N(N16)+N(N22))/N11,"")) | O50: =IFERROR((N(O16)+N(O22))/O11,"") -> 0.74480114
B51: Marketing & event | C51: =IF(C$5>BLN,"",IFERROR((N(C25))/C11,"")) -> 0.70933161 | D51: =IF(D$5>BLN,"",IFERROR((N(D25))/D11,"")) -> 0.00060459944 | E51: =IF(E$5>BLN,"",IFERROR((N(E25))/E11,"")) -> 0 | F51: =IF(F$5>BLN,"",IFERROR((N(F25))/F11,"")) -> 0.027567304 | G51: =IF(G$5>BLN,"",IFERROR((N(G25))/G11,"")) -> 0.010215146 | H51: =IF(H$5>BLN,"",IFERROR((N(H25))/H11,"")) -> 0.025778313 | I51: =IF(I$5>BLN,"",IFERROR((N(I25))/I11,"")) -> 0.029824964 | J51: =IF(J$5>BLN,"",IFERROR((N(J25))/J11,"")) -> 0.019409903 | ... N51: =IF(N$5>BLN,"",IFERROR((N(N25))/N11,"")) | O51: =IFERROR((N(O25))/O11,"") -> 0.099550862
B53: Catatan: belum termasuk PPh atas usaha (lihat CALK & PAJAK). Bulan setelah tutup buku dikosongkan.

Sheet NERACA
A1: LAPORAN POSISI KEUANGAN (NERACA)
A2: ="KOPI PARANG • dalam Rupiah" -> KOPI PARANG • dalam Rupiah
B4: Keterangan | C4: ="1 Jan "&TAHUN -> 1 Jan 2026 | D4: =TEXT(DATE(TAHUN,BLN+1,0),"d")&" "&LEFT(NAMA_BLN,3)&" "&TAHUN -> 30 Sep 2026
B5: ASET
B6: Aset lancar
B7: Kas tunai | C7: =SUMIF(MUTASI!$B$6:$B$45,"Kas Tunai",MUTASI!$Q$6:$Q$45) -> 26605500 | D7: =SUMIF(MUTASI!$B$6:$B$45,"Kas Tunai",MUTASI!$S$6:$S$45) -> 51913400
B8: Kas di bank | C8: =SUMIF(MUTASI!$B$6:$B$45,"Kas Bank",MUTASI!$Q$6:$Q$45) -> 81982785 | D8: =SUMIF(MUTASI!$B$6:$B$45,"Kas Bank",MUTASI!$S$6:$S$45) -> -2739792
B9: Kas kecil (warung) | C9: =SUMIF(MUTASI!$B$6:$B$45,"Kas Warung",MUTASI!$Q$6:$Q$45) -> 3000000 | D9: =SUMIF(MUTASI!$B$6:$B$45,"Kas Warung",MUTASI!$S$6:$S$45) -> 4108000
B10: Piutang usaha | C10: =SUMIF(MUTASI!$B$6:$B$45,"Piutang Usaha Cafe",MUTASI!$Q$6:$Q$45)+SUMIF(MUTASI!$B$6:$B$45,"Piutang Usaha non Cafe",MUTASI!$Q$6:$Q$45) -> 4500000 | D10: =SUMIF(MUTASI!$B$6:$B$45,"Piutang Usaha Cafe",MUTASI!$S$6:$S$45)+SUMIF(MUTASI!$B$6:$B$45,"Piutang Usaha non Cafe",MUTASI!$S$6:$S$45) -> 0
B11: Piutang lain-lain | C11: =SUMIF(MUTASI!$B$6:$B$45,"Piutang Lainnya",MUTASI!$Q$6:$Q$45) -> 3000000 | D11: =SUMIF(MUTASI!$B$6:$B$45,"Piutang Lainnya",MUTASI!$S$6:$S$45) -> 8133335
B12: Persediaan bahan baku | C12: =SUMIF(MUTASI!$B$6:$B$45,"Inventori",MUTASI!$Q$6:$Q$45) -> 0 | D12: =SUMIF(MUTASI!$B$6:$B$45,"Inventori",MUTASI!$S$6:$S$45) -> 0
B13: Perlengkapan | C13: =SUMIF(MUTASI!$B$6:$B$45,"Perlengkapan",MUTASI!$Q$6:$Q$45) -> 0 | D13: =SUMIF(MUTASI!$B$6:$B$45,"Perlengkapan",MUTASI!$S$6:$S$45) -> 864780
B14: Beban dibayar di muka | C14: =SUMIF(MUTASI!$B$6:$B$45,"Beban Dibayar di Muka",MUTASI!$Q$6:$Q$45) -> 0 | D14: =SUMIF(MUTASI!$B$6:$B$45,"Beban Dibayar di Muka",MUTASI!$S$6:$S$45) -> 0
B15: Total aset lancar | C15: =C7+C8+C9+C10+C11+C12+C13+C14 -> 119088285 | D15: =D7+D8+D9+D10+D11+D12+D13+D14 -> 62279723
B16: Aset tidak lancar
B17: Peralatan (harga perolehan) | C17: =SUMIF(MUTASI!$B$6:$B$45,"Peralatan",MUTASI!$Q$6:$Q$45) -> 0 | D17: =SUMIF(MUTASI!$B$6:$B$45,"Peralatan",MUTASI!$S$6:$S$45) -> 42023410
B18: Akumulasi penyusutan | C18: =SUMIF(MUTASI!$B$6:$B$45,"Akumulasi Penyusutan Peralatan",MUTASI!$Q$6:$Q$45) -> 0 | D18: =SUMIF(MUTASI!$B$6:$B$45,"Akumulasi Penyusutan Peralatan",MUTASI!$S$6:$S$45) -> -2564119
B19: Total aset tidak lancar | C19: =C17+C18 -> 0 | D19: =D17+D18 -> 39459291
B20: TOTAL ASET | C20: =C15+C19 -> 119088285 | D20: =D15+D19 -> 101739014
B22: LIABILITAS DAN EKUITAS
B23: Liabilitas jangka pendek
B24: Utang usaha | C24: =-SUMIF(MUTASI!$B$6:$B$45,"Utang Usaha Lancar",MUTASI!$Q$6:$Q$45) -> 0 | D24: =-SUMIF(MUTASI!$B$6:$B$45,"Utang Usaha Lancar",MUTASI!$S$6:$S$45) -> 0
B25: Utang pajak daerah (PBJT) | C25: =-SUMIF(MUTASI!$B$6:$B$45,"Utang Pajak Daerah (PBJT)",MUTASI!$Q$6:$Q$45) -> 0 | D25: =-SUMIF(MUTASI!$B$6:$B$45,"Utang Pajak Daerah (PBJT)",MUTASI!$S$6:$S$45) -> 59326181
B26: Utang lain-lain | C26: =-SUMIF(MUTASI!$B$6:$B$45,"Utang Lainnya",MUTASI!$Q$6:$Q$45) -> 3567600 | D26: =-SUMIF(MUTASI!$B$6:$B$45,"Utang Lainnya",MUTASI!$S$6:$S$45) -> 3567600
B27: Total liabilitas jangka pendek | C27: =C24+C25+C26 -> 3567600 | D27: =D24+D25+D26 -> 62893781
B28: Liabilitas jangka panjang
B29: Utang usaha jangka panjang | C29: =-SUMIF(MUTASI!$B$6:$B$45,"Utang Usaha Jangka Panjang",MUTASI!$Q$6:$Q$45) -> 2420000 | D29: =-SUMIF(MUTASI!$B$6:$B$45,"Utang Usaha Jangka Panjang",MUTASI!$S$6:$S$45) -> 11726000
B30: TOTAL LIABILITAS | C30: =C27+C29 -> 5987600 | D30: =D27+D29 -> 74619781
B31: Ekuitas
B32: Modal pemilik | C32: =-SUMIF(MUTASI!$B$6:$B$45,"Ekuitas Kopi Parang",MUTASI!$Q$6:$Q$45) -> 113100685 | D32: =-SUMIF(MUTASI!$B$6:$B$45,"Ekuitas Kopi Parang",MUTASI!$S$6:$S$45) -> 113100685
B33: Prive (pengambilan pemilik) | C33: =-SUMIF(MUTASI!$B$6:$B$45,"Prive",MUTASI!$Q$6:$Q$45) -> 0 | D33: =-SUMIF(MUTASI!$B$6:$B$45,"Prive",MUTASI!$S$6:$S$45) -> -30984750
B34: Laba (rugi) tahun berjalan | C34: =0 -> 0 | D34: =-(SUMIF(MUTASI!$C$6:$C$45,"PENDAPATAN",MUTASI!$R$6:$R$45)+SUMIF(MUTASI!$C$6:$C$45,"BEBAN",MUTASI!$R$6:$R$45)) -> -54996702
B35: TOTAL EKUITAS | C35: =C32+C33+C34 -> 113100685 | D35: =D32+D33+D34 -> 27119233
B36: TOTAL LIABILITAS DAN EKUITAS | C36: =C30+C35 -> 119088285 | D36: =D30+D35 -> 101739014
B38: Cek keseimbangan (harus 0) | C38: =ROUND(C20-C36,0) -> 0 | D38: =ROUND(D20-D36,0) -> 0
B40: Lihat CALK untuk penjelasan pos-pos penting (saldo awal aset tetap, kewajiban pajak).

Sheet ARUS KAS
A1: LAPORAN ARUS KAS (METODE LANGSUNG)
A2: ="KOPI PARANG • "&"Periode 1 Januari – "&TEXT(DATE(TAHUN,BLN+1,0),"d")&" "&NAMA_BLN&" "&TAHUN&" • pindah dana antar-kas tidak dihitung" -> KOPI PARANG • Periode 1 Januari – 30 September 2026 • pindah dana antar-kas tidak dihitung
B4: Keterangan | C4: Jan | D4: Feb | E4: Mar | F4: Apr | G4: Mei | H4: Jun | I4: Jul | J4: Agu | K4: Sep | L4: Okt | M4: Nov | N4: Des | O4: ="s.d. "&LEFT(NAMA_BLN,3)&" "&TAHUN -> s.d. Sep 2026
C5: 1 | D5: 2 | E5: 3 | F5: 4 | G5: 5 | H5: 6 | I5: 7 | J5: 8 | K5: 9 | L5: 10 | M5: 11 | N5: 12
B6: ARUS KAS DARI AKTIVITAS OPERASI
B7: Penerimaan dari pelanggan | C7: =IF(C$5>BLN,"",SUMIFS(J_KAS,J_BARIS,"OP1",J_BLN,C$5,J_THN,TAHUN)) -> 97109977 | D7: =IF(D$5>BLN,"",SUMIFS(J_KAS,J_BARIS,"OP1",J_BLN,D$5,J_THN,TAHUN)) -> 74780788 | E7: =IF(E$5>BLN,"",SUMIFS(J_KAS,J_BARIS,"OP1",J_BLN,E$5,J_THN,TAHUN)) -> 101366744 | F7: =IF(F$5>BLN,"",SUMIFS(J_KAS,J_BARIS,"OP1",J_BLN,F$5,J_THN,TAHUN)) -> 93542488 | G7: =IF(G$5>BLN,"",SUMIFS(J_KAS,J_BARIS,"OP1",J_BLN,G$5,J_THN,TAHUN)) -> 110628974 | H7: =IF(H$5>BLN,"",SUMIFS(J_KAS,J_BARIS,"OP1",J_BLN,H$5,J_THN,TAHUN)) -> 103966227 | I7: =IF(I$5>BLN,"",SUMIFS(J_KAS,J_BARIS,"OP1",J_BLN,I$5,J_THN,TAHUN)) -> 91223181 | J7: =IF(J$5>BLN,"",SUMIFS(J_KAS,J_BARIS,"OP1",J_BLN,J$5,J_THN,TAHUN)) -> 93754284 | ... N7: =IF(N$5>BLN,"",SUMIFS(J_KAS,J_BARIS,"OP1",J_BLN,N$5,J_THN,TAHUN)) | O7: =SUMIFS(J_KAS,J_BARIS,"OP1",J_THN,TAHUN,J_BLN,"<="&BLN) -> 858725533
B8: Penerimaan (pembayaran) lain-lain bersih | C8: =IF(C$5>BLN,"",SUMIFS(J_KAS,J_BARIS,"OP2",J_BLN,C$5,J_THN,TAHUN)) -> -4274771 | D8: =IF(D$5>BLN,"",SUMIFS(J_KAS,J_BARIS,"OP2",J_BLN,D$5,J_THN,TAHUN)) -> 246033 | E8: =IF(E$5>BLN,"",SUMIFS(J_KAS,J_BARIS,"OP2",J_BLN,E$5,J_THN,TAHUN)) -> -595336 | F8: =IF(F$5>BLN,"",SUMIFS(J_KAS,J_BARIS,"OP2",J_BLN,F$5,J_THN,TAHUN)) -> -1399315 | G8: =IF(G$5>BLN,"",SUMIFS(J_KAS,J_BARIS,"OP2",J_BLN,G$5,J_THN,TAHUN)) -> -1021829 | H8: =IF(H$5>BLN,"",SUMIFS(J_KAS,J_BARIS,"OP2",J_BLN,H$5,J_THN,TAHUN)) -> 647768 | I8: =IF(I$5>BLN,"",SUMIFS(J_KAS,J_BARIS,"OP2",J_BLN,I$5,J_THN,TAHUN)) -> -595017 | J8: =IF(J$5>BLN,"",SUMIFS(J_KAS,J_BARIS,"OP2",J_BLN,J$5,J_THN,TAHUN)) -> -1288 | ... N8: =IF(N$5>BLN,"",SUMIFS(J_KAS,J_BARIS,"OP2",J_BLN,N$5,J_THN,TAHUN)) | O8: =SUMIFS(J_KAS,J_BARIS,"OP2",J_THN,TAHUN,J_BLN,"<="&BLN) -> -4842614
B9: Pembayaran bahan baku & penyajian | C9: =IF(C$5>BLN,"",SUMIFS(J_KAS,J_BARIS,"OP3",J_BLN,C$5,J_THN,TAHUN)) -> -28168300 | D9: =IF(D$5>BLN,"",SUMIFS(J_KAS,J_BARIS,"OP3",J_BLN,D$5,J_THN,TAHUN)) -> -31233710 | E9: =IF(E$5>BLN,"",SUMIFS(J_KAS,J_BARIS,"OP3",J_BLN,E$5,J_THN,TAHUN)) -> -33037187 | F9: =IF(F$5>BLN,"",SUMIFS(J_KAS,J_BARIS,"OP3",J_BLN,F$5,J_THN,TAHUN)) -> -56168794 | G9: =IF(G$5>BLN,"",SUMIFS(J_KAS,J_BARIS,"OP3",J_BLN,G$5,J_THN,TAHUN)) -> -34725173 | H9: =IF(H$5>BLN,"",SUMIFS(J_KAS,J_BARIS,"OP3",J_BLN,H$5,J_THN,TAHUN)) -> -45136507 | I9: =IF(I$5>BLN,"",SUMIFS(J_KAS,J_BARIS,"OP3",J_BLN,I$5,J_THN,TAHUN)) -> -33918044 | J9: =IF(J$5>BLN,"",SUMIFS(J_KAS,J_BARIS,"OP3",J_BLN,J$5,J_THN,TAHUN)) -> -23093020 | ... N9: =IF(N$5>BLN,"",SUMIFS(J_KAS,J_BARIS,"OP3",J_BLN,N$5,J_THN,TAHUN)) | O9: =SUMIFS(J_KAS,J_BARIS,"OP3",J_THN,TAHUN,J_BLN,"<="&BLN) -> -338579534
B10: Pembayaran gaji | C10: =IF(C$5>BLN,"",SUMIFS(J_KAS,J_BARIS,"OP4",J_BLN,C$5,J_THN,TAHUN)) -> -24630000 | D10: =IF(D$5>BLN,"",SUMIFS(J_KAS,J_BARIS,"OP4",J_BLN,D$5,J_THN,TAHUN)) -> -25694500 | E10: =IF(E$5>BLN,"",SUMIFS(J_KAS,J_BARIS,"OP4",J_BLN,E$5,J_THN,TAHUN)) -> -41902000 | F10: =IF(F$5>BLN,"",SUMIFS(J_KAS,J_BARIS,"OP4",J_BLN,F$5,J_THN,TAHUN)) -> -26266000 | G10: =IF(G$5>BLN,"",SUMIFS(J_KAS,J_BARIS,"OP4",J_BLN,G$5,J_THN,TAHUN)) -> -28405333 | H10: =IF(H$5>BLN,"",SUMIFS(J_KAS,J_BARIS,"OP4",J_BLN,H$5,J_THN,TAHUN)) -> -29293333 | I10: =IF(I$5>BLN,"",SUMIFS(J_KAS,J_BARIS,"OP4",J_BLN,I$5,J_THN,TAHUN)) -> -22761333 | J10: =IF(J$5>BLN,"",SUMIFS(J_KAS,J_BARIS,"OP4",J_BLN,J$5,J_THN,TAHUN)) -> -24169333 | ... N10: =IF(N$5>BLN,"",SUMIFS(J_KAS,J_BARIS,"OP4",J_BLN,N$5,J_THN,TAHUN)) | O10: =SUMIFS(J_KAS,J_BARIS,"OP4",J_THN,TAHUN,J_BLN,"<="&BLN) -> -247914165
B11: Pembayaran sewa | C11: =IF(C$5>BLN,"",SUMIFS(J_KAS,J_BARIS,"OP5",J_BLN,C$5,J_THN,TAHUN)) -> -10000000 | D11: =IF(D$5>BLN,"",SUMIFS(J_KAS,J_BARIS,"OP5",J_BLN,D$5,J_THN,TAHUN)) -> -10000000 | E11: =IF(E$5>BLN,"",SUMIFS(J_KAS,J_BARIS,"OP5",J_BLN,E$5,J_THN,TAHUN)) -> -10000000 | F11: =IF(F$5>BLN,"",SUMIFS(J_KAS,J_BARIS,"OP5",J_BLN,F$5,J_THN,TAHUN)) -> -10000000 | G11: =IF(G$5>BLN,"",SUMIFS(J_KAS,J_BARIS,"OP5",J_BLN,G$5,J_THN,TAHUN)) -> -10000000 | H11: =IF(H$5>BLN,"",SUMIFS(J_KAS,J_BARIS,"OP5",J_BLN,H$5,J_THN,TAHUN)) -> 0 | I11: =IF(I$5>BLN,"",SUMIFS(J_KAS,J_BARIS,"OP5",J_BLN,I$5,J_THN,TAHUN)) -> -10000000 | J11: =IF(J$5>BLN,"",SUMIFS(J_KAS,J_BARIS,"OP5",J_BLN,J$5,J_THN,TAHUN)) -> -10000000 | ... N11: =IF(N$5>BLN,"",SUMIFS(J_KAS,J_BARIS,"OP5",J_BLN,N$5,J_THN,TAHUN)) | O11: =SUMIFS(J_KAS,J_BARIS,"OP5",J_THN,TAHUN,J_BLN,"<="&BLN) -> -80000000
B12: Pembayaran beban operasional lainnya | C12: =IF(C$5>BLN,"",SUMIFS(J_KAS,J_BARIS,"OP6",J_BLN,C$5,J_THN,TAHUN)) -> -71813952 | D12: =IF(D$5>BLN,"",SUMIFS(J_KAS,J_BARIS,"OP6",J_BLN,D$5,J_THN,TAHUN)) -> -8624317 | E12: =IF(E$5>BLN,"",SUMIFS(J_KAS,J_BARIS,"OP6",J_BLN,E$5,J_THN,TAHUN)) -> -9300328 | F12: =IF(F$5>BLN,"",SUMIFS(J_KAS,J_BARIS,"OP6",J_BLN,F$5,J_THN,TAHUN)) -> -11156861 | G12: =IF(G$5>BLN,"",SUMIFS(J_KAS,J_BARIS,"OP6",J_BLN,G$5,J_THN,TAHUN)) -> -12024073 | H12: =IF(H$5>BLN,"",SUMIFS(J_KAS,J_BARIS,"OP6",J_BLN,H$5,J_THN,TAHUN)) -> -14500665 | I12: =IF(I$5>BLN,"",SUMIFS(J_KAS,J_BARIS,"OP6",J_BLN,I$5,J_THN,TAHUN)) -> -19061206 | J12: =IF(J$5>BLN,"",SUMIFS(J_KAS,J_BARIS,"OP6",J_BLN,J$5,J_THN,TAHUN)) -> -11310336 | ... N12: =IF(N$5>BLN,"",SUMIFS(J_KAS,J_BARIS,"OP6",J_BLN,N$5,J_THN,TAHUN)) | O12: =SUMIFS(J_KAS,J_BARIS,"OP6",J_THN,TAHUN,J_BLN,"<="&BLN) -> -173815687
B13: Pembayaran pajak restoran (PBJT) | C13: =IF(C$5>BLN,"",SUMIFS(J_KAS,J_BARIS,"OP7",J_BLN,C$5,J_THN,TAHUN)) -> -2056200 | D13: =IF(D$5>BLN,"",SUMIFS(J_KAS,J_BARIS,"OP7",J_BLN,D$5,J_THN,TAHUN)) -> -1664000 | E13: =IF(E$5>BLN,"",SUMIFS(J_KAS,J_BARIS,"OP7",J_BLN,E$5,J_THN,TAHUN)) -> -2310000 | F13: =IF(F$5>BLN,"",SUMIFS(J_KAS,J_BARIS,"OP7",J_BLN,F$5,J_THN,TAHUN)) -> -2058000 | G13: =IF(G$5>BLN,"",SUMIFS(J_KAS,J_BARIS,"OP7",J_BLN,G$5,J_THN,TAHUN)) -> -2257000 | H13: =IF(H$5>BLN,"",SUMIFS(J_KAS,J_BARIS,"OP7",J_BLN,H$5,J_THN,TAHUN)) -> -2232000 | I13: =IF(I$5>BLN,"",SUMIFS(J_KAS,J_BARIS,"OP7",J_BLN,I$5,J_THN,TAHUN)) -> -2094000 | J13: =IF(J$5>BLN,"",SUMIFS(J_KAS,J_BARIS,"OP7",J_BLN,J$5,J_THN,TAHUN)) -> -1995100 | ... N13: =IF(N$5>BLN,"",SUMIFS(J_KAS,J_BARIS,"OP7",J_BLN,N$5,J_THN,TAHUN)) | O13: =SUMIFS(J_KAS,J_BARIS,"OP7",J_THN,TAHUN,J_BLN,"<="&BLN) -> -18762300
B14: Kas bersih dari aktivitas operasi | C14: =IF(C$5>BLN,"",N(C7)+N(C8)+N(C9)+N(C10)+N(C11)+N(C12)+N(C13)) -> -43833246 | D14: =IF(D$5>BLN,"",N(D7)+N(D8)+N(D9)+N(D10)+N(D11)+N(D12)+N(D13)) -> -2189706 | E14: =IF(E$5>BLN,"",N(E7)+N(E8)+N(E9)+N(E10)+N(E11)+N(E12)+N(E13)) -> 4221893 | F14: =IF(F$5>BLN,"",N(F7)+N(F8)+N(F9)+N(F10)+N(F11)+N(F12)+N(F13)) -> -13506482 | G14: =IF(G$5>BLN,"",N(G7)+N(G8)+N(G9)+N(G10)+N(G11)+N(G12)+N(G13)) -> 22195566 | H14: =IF(H$5>BLN,"",N(H7)+N(H8)+N(H9)+N(H10)+N(H11)+N(H12)+N(H13)) -> 13451490 | I14: =IF(I$5>BLN,"",N(I7)+N(I8)+N(I9)+N(I10)+N(I11)+N(I12)+N(I13)) -> 2793581 | J14: =IF(J$5>BLN,"",N(J7)+N(J8)+N(J9)+N(J10)+N(J11)+N(J12)+N(J13)) -> 23185207 | ... N14: =IF(N$5>BLN,"",N(N7)+N(N8)+N(N9)+N(N10)+N(N11)+N(N12)+N(N13)) | O14: =N(O7)+N(O8)+N(O9)+N(O10)+N(O11)+N(O12)+N(O13) -> -5188767
B16: ARUS KAS DARI AKTIVITAS INVESTASI
B17: Pembelian peralatan | C17: =IF(C$5>BLN,"",SUMIFS(J_KAS,J_BARIS,"IN1",J_BLN,C$5,J_THN,TAHUN)) -> -13000000 | D17: =IF(D$5>BLN,"",SUMIFS(J_KAS,J_BARIS,"IN1",J_BLN,D$5,J_THN,TAHUN)) -> 0 | E17: =IF(E$5>BLN,"",SUMIFS(J_KAS,J_BARIS,"IN1",J_BLN,E$5,J_THN,TAHUN)) -> -1742240 | F17: =IF(F$5>BLN,"",SUMIFS(J_KAS,J_BARIS,"IN1",J_BLN,F$5,J_THN,TAHUN)) -> -359448 | G17: =IF(G$5>BLN,"",SUMIFS(J_KAS,J_BARIS,"IN1",J_BLN,G$5,J_THN,TAHUN)) -> -1792100 | H17: =IF(H$5>BLN,"",SUMIFS(J_KAS,J_BARIS,"IN1",J_BLN,H$5,J_THN,TAHUN)) -> -5650980 | I17: =IF(I$5>BLN,"",SUMIFS(J_KAS,J_BARIS,"IN1",J_BLN,I$5,J_THN,TAHUN)) -> -1274220 | J17: =IF(J$5>BLN,"",SUMIFS(J_KAS,J_BARIS,"IN1",J_BLN,J$5,J_THN,TAHUN)) -> -3212587 | ... N17: =IF(N$5>BLN,"",SUMIFS(J_KAS,J_BARIS,"IN1",J_BLN,N$5,J_THN,TAHUN)) | O17: =SUMIFS(J_KAS,J_BARIS,"IN1",J_THN,TAHUN,J_BLN,"<="&BLN) -> -29231410
B18: Kas bersih dari aktivitas investasi | C18: =IF(C$5>BLN,"",N(C17)) -> -13000000 | D18: =IF(D$5>BLN,"",N(D17)) -> 0 | E18: =IF(E$5>BLN,"",N(E17)) -> -1742240 | F18: =IF(F$5>BLN,"",N(F17)) -> -359448 | G18: =IF(G$5>BLN,"",N(G17)) -> -1792100 | H18: =IF(H$5>BLN,"",N(H17)) -> -5650980 | I18: =IF(I$5>BLN,"",N(I17)) -> -1274220 | J18: =IF(J$5>BLN,"",N(J17)) -> -3212587 | ... N18: =IF(N$5>BLN,"",N(N17)) | O18: =N(O17) -> -29231410
B20: ARUS KAS DARI AKTIVITAS PENDANAAN
B21: Pengambilan pemilik (prive) | C21: =IF(C$5>BLN,"",SUMIFS(J_KAS,J_BARIS,"FN1",J_BLN,C$5,J_THN,TAHUN)) -> -2500000 | D21: =IF(D$5>BLN,"",SUMIFS(J_KAS,J_BARIS,"FN1",J_BLN,D$5,J_THN,TAHUN)) -> -2500000 | E21: =IF(E$5>BLN,"",SUMIFS(J_KAS,J_BARIS,"FN1",J_BLN,E$5,J_THN,TAHUN)) -> -2500000 | F21: =IF(F$5>BLN,"",SUMIFS(J_KAS,J_BARIS,"FN1",J_BLN,F$5,J_THN,TAHUN)) -> -2500000 | G21: =IF(G$5>BLN,"",SUMIFS(J_KAS,J_BARIS,"FN1",J_BLN,G$5,J_THN,TAHUN)) -> -2500000 | H21: =IF(H$5>BLN,"",SUMIFS(J_KAS,J_BARIS,"FN1",J_BLN,H$5,J_THN,TAHUN)) -> -2500000 | I21: =IF(I$5>BLN,"",SUMIFS(J_KAS,J_BARIS,"FN1",J_BLN,I$5,J_THN,TAHUN)) -> -4000000 | J21: =IF(J$5>BLN,"",SUMIFS(J_KAS,J_BARIS,"FN1",J_BLN,J$5,J_THN,TAHUN)) -> 0 | ... N21: =IF(N$5>BLN,"",SUMIFS(J_KAS,J_BARIS,"FN1",J_BLN,N$5,J_THN,TAHUN)) | O21: =SUMIFS(J_KAS,J_BARIS,"FN1",J_THN,TAHUN,J_BLN,"<="&BLN) -> -19000000
B22: Setoran modal pemilik | C22: =IF(C$5>BLN,"",SUMIFS(J_KAS,J_BARIS,"FN2",J_BLN,C$5,J_THN,TAHUN)) -> 0 | D22: =IF(D$5>BLN,"",SUMIFS(J_KAS,J_BARIS,"FN2",J_BLN,D$5,J_THN,TAHUN)) -> 0 | E22: =IF(E$5>BLN,"",SUMIFS(J_KAS,J_BARIS,"FN2",J_BLN,E$5,J_THN,TAHUN)) -> 0 | F22: =IF(F$5>BLN,"",SUMIFS(J_KAS,J_BARIS,"FN2",J_BLN,F$5,J_THN,TAHUN)) -> 0 | G22: =IF(G$5>BLN,"",SUMIFS(J_KAS,J_BARIS,"FN2",J_BLN,G$5,J_THN,TAHUN)) -> 0 | H22: =IF(H$5>BLN,"",SUMIFS(J_KAS,J_BARIS,"FN2",J_BLN,H$5,J_THN,TAHUN)) -> 0 | I22: =IF(I$5>BLN,"",SUMIFS(J_KAS,J_BARIS,"FN2",J_BLN,I$5,J_THN,TAHUN)) -> 0 | J22: =IF(J$5>BLN,"",SUMIFS(J_KAS,J_BARIS,"FN2",J_BLN,J$5,J_THN,TAHUN)) -> 0 | ... N22: =IF(N$5>BLN,"",SUMIFS(J_KAS,J_BARIS,"FN2",J_BLN,N$5,J_THN,TAHUN)) | O22: =SUMIFS(J_KAS,J_BARIS,"FN2",J_THN,TAHUN,J_BLN,"<="&BLN) -> 0
B23: Penerimaan (pembayaran) utang | C23: =IF(C$5>BLN,"",SUMIFS(J_KAS,J_BARIS,"FN3",J_BLN,C$5,J_THN,TAHUN)) -> -1920000 | D23: =IF(D$5>BLN,"",SUMIFS(J_KAS,J_BARIS,"FN3",J_BLN,D$5,J_THN,TAHUN)) -> -522000 | E23: =IF(E$5>BLN,"",SUMIFS(J_KAS,J_BARIS,"FN3",J_BLN,E$5,J_THN,TAHUN)) -> -1378500 | F23: =IF(F$5>BLN,"",SUMIFS(J_KAS,J_BARIS,"FN3",J_BLN,F$5,J_THN,TAHUN)) -> 0 | G23: =IF(G$5>BLN,"",SUMIFS(J_KAS,J_BARIS,"FN3",J_BLN,G$5,J_THN,TAHUN)) -> 0 | H23: =IF(H$5>BLN,"",SUMIFS(J_KAS,J_BARIS,"FN3",J_BLN,H$5,J_THN,TAHUN)) -> 0 | I23: =IF(I$5>BLN,"",SUMIFS(J_KAS,J_BARIS,"FN3",J_BLN,I$5,J_THN,TAHUN)) -> 0 | J23: =IF(J$5>BLN,"",SUMIFS(J_KAS,J_BARIS,"FN3",J_BLN,J$5,J_THN,TAHUN)) -> 0 | ... N23: =IF(N$5>BLN,"",SUMIFS(J_KAS,J_BARIS,"FN3",J_BLN,N$5,J_THN,TAHUN)) | O23: =SUMIFS(J_KAS,J_BARIS,"FN3",J_THN,TAHUN,J_BLN,"<="&BLN) -> -4886500
B24: Kas bersih dari aktivitas pendanaan | C24: =IF(C$5>BLN,"",N(C21)+N(C22)+N(C23)) -> -4420000 | D24: =IF(D$5>BLN,"",N(D21)+N(D22)+N(D23)) -> -3022000 | E24: =IF(E$5>BLN,"",N(E21)+N(E22)+N(E23)) -> -3878500 | F24: =IF(F$5>BLN,"",N(F21)+N(F22)+N(F23)) -> -2500000 | G24: =IF(G$5>BLN,"",N(G21)+N(G22)+N(G23)) -> -2500000 | H24: =IF(H$5>BLN,"",N(H21)+N(H22)+N(H23)) -> -2500000 | I24: =IF(I$5>BLN,"",N(I21)+N(I22)+N(I23)) -> -4000000 | J24: =IF(J$5>BLN,"",N(J21)+N(J22)+N(J23)) -> 0 | ... N24: =IF(N$5>BLN,"",N(N21)+N(N22)+N(N23)) | O24: =N(O21)+N(O22)+N(O23) -> -23886500
B26: KENAIKAN (PENURUNAN) KAS BERSIH | C26: =IF(C$5>BLN,"",N(C14)+N(C18)+N(C24)) -> -61253246 | D26: =IF(D$5>BLN,"",N(D14)+N(D18)+N(D24)) -> -5211706 | E26: =IF(E$5>BLN,"",N(E14)+N(E18)+N(E24)) -> -1398847 | F26: =IF(F$5>BLN,"",N(F14)+N(F18)+N(F24)) -> -16365930 | G26: =IF(G$5>BLN,"",N(G14)+N(G18)+N(G24)) -> 17903466 | H26: =IF(H$5>BLN,"",N(H14)+N(H18)+N(H24)) -> 5300510 | I26: =IF(I$5>BLN,"",N(I14)+N(I18)+N(I24)) -> -2480639 | J26: =IF(J$5>BLN,"",N(J14)+N(J18)+N(J24)) -> 19972620 | ... N26: =IF(N$5>BLN,"",N(N14)+N(N18)+N(N24)) | O26: =N(O14)+N(O18)+N(O24) -> -58306677
B27: Kas awal periode | C27: =IF(C$5>BLN,"",SUMIF(MUTASI!$T$6:$T$45,"KAS",MUTASI!$Q$6:$Q$45)) -> 111588285 | D27: =IF(D$5>BLN,"",N(C28)) -> 50335039 | E27: =IF(E$5>BLN,"",N(D28)) -> 45123333 | F27: =IF(F$5>BLN,"",N(E28)) -> 43724486 | G27: =IF(G$5>BLN,"",N(F28)) -> 27358556 | H27: =IF(H$5>BLN,"",N(G28)) -> 45262022 | I27: =IF(I$5>BLN,"",N(H28)) -> 50562532 | J27: =IF(J$5>BLN,"",N(I28)) -> 48081893 | K27: =IF(K$5>BLN,"",N(J28)) -> 68054513 | ... N27: =IF(N$5>BLN,"",N(M28)) | O27: =SUMIF(MUTASI!$T$6:$T$45,"KAS",MUTASI!$Q$6:$Q$45) -> 111588285
B28: KAS AKHIR PERIODE | C28: =IF(C$5>BLN,"",N(C27)+N(C26)) -> 50335039 | D28: =IF(D$5>BLN,"",N(D27)+N(D26)) -> 45123333 | E28: =IF(E$5>BLN,"",N(E27)+N(E26)) -> 43724486 | F28: =IF(F$5>BLN,"",N(F27)+N(F26)) -> 27358556 | G28: =IF(G$5>BLN,"",N(G27)+N(G26)) -> 45262022 | H28: =IF(H$5>BLN,"",N(H27)+N(H26)) -> 50562532 | I28: =IF(I$5>BLN,"",N(I27)+N(I26)) -> 48081893 | J28: =IF(J$5>BLN,"",N(J27)+N(J26)) -> 68054513 | ... N28: =IF(N$5>BLN,"",N(N27)+N(N26)) | O28: =N(O27)+N(O26) -> 53281608
B29: Cek vs saldo kas di buku besar (harus 0) | C29: =IF(C$5>BLN,"",ROUND(N(C28)-SUMIF(MUTASI!$T$6:$T$45,"KAS",MUTASI!$Q$6:$Q$45)-SUMPRODUCT((MUTASI!$T$6:$T$45="KAS")*MUTASI!$E$6:$E$45),0)) -> 0 | D29: =IF(D$5>BLN,"",ROUND(N(D28)-SUMIF(MUTASI!$T$6:$T$45,"KAS",MUTASI!$Q$6:$Q$45)-SUMPRODUCT((MUTASI!$T$6:$T$45="KAS")*MUTASI!$E$6:$F$45),0)) -> 0 | E29: =IF(E$5>BLN,"",ROUND(N(E28)-SUMIF(MUTASI!$T$6:$T$45,"KAS",MUTASI!$Q$6:$Q$45)-SUMPRODUCT((MUTASI!$T$6:$T$45="KAS")*MUTASI!$E$6:$G$45),0)) -> 0 | F29: =IF(F$5>BLN,"",ROUND(N(F28)-SUMIF(MUTASI!$T$6:$T$45,"KAS",MUTASI!$Q$6:$Q$45)-SUMPRODUCT((MUTASI!$T$6:$T$45="KAS")*MUTASI!$E$6:$H$45),0)) -> 0 | G29: =IF(G$5>BLN,"",ROUND(N(G28)-SUMIF(MUTASI!$T$6:$T$45,"KAS",MUTASI!$Q$6:$Q$45)-SUMPRODUCT((MUTASI!$T$6:$T$45="KAS")*MUTASI!$E$6:$I$45),0)) -> 0 | H29: =IF(H$5>BLN,"",ROUND(N(H28)-SUMIF(MUTASI!$T$6:$T$45,"KAS",MUTASI!$Q$6:$Q$45)-SUMPRODUCT((MUTASI!$T$6:$T$45="KAS")*MUTASI!$E$6:$J$45),0)) -> 0 | I29: =IF(I$5>BLN,"",ROUND(N(I28)-SUMIF(MUTASI!$T$6:$T$45,"KAS",MUTASI!$Q$6:$Q$45)-SUMPRODUCT((MUTASI!$T$6:$T$45="KAS")*MUTASI!$E$6:$K$45),0)) -> 0 | J29: =IF(J$5>BLN,"",ROUND(N(J28)-SUMIF(MUTASI!$T$6:$T$45,"KAS",MUTASI!$Q$6:$Q$45)-SUMPRODUCT((MUTASI!$T$6:$T$45="KAS")*MUTASI!$E$6:$L$45),0)) -> 0 | K29: =IF(K$5>BLN,"",ROUND(N(K28)-SUMIF(MUTASI!$T$6:$T$45,"KAS",MUTASI!$Q$6:$Q$45)-SUMPRODUCT((MUTASI!$T$6:$T$45="KAS")*MUTASI!$E$6:$M$45),0)) -> 0 | L29: =IF(L$5>BLN,"",ROUND(N(L28)-SUMIF(MUTASI!$T$6:$T$45,"KAS",MUTASI!$Q$6:$Q$45)-SUMPRODUCT((MUTASI!$T$6:$T$45="KAS")*MUTASI!$E$6:$N$45),0)) | M29: =IF(M$5>BLN,"",ROUND(N(M28)-SUMIF(MUTASI!$T$6:$T$45,"KAS",MUTASI!$Q$6:$Q$45)-SUMPRODUCT((MUTASI!$T$6:$T$45="KAS")*MUTASI!$E$6:$O$45),0)) | N29: =IF(N$5>BLN,"",ROUND(N(N28)-SUMIF(MUTASI!$T$6:$T$45,"KAS",MUTASI!$Q$6:$Q$45)-SUMPRODUCT((MUTASI!$T$6:$T$45="KAS")*MUTASI!$E$6:$P$45),0)) | O29: =ROUND(N(O28)-SUMIF(MUTASI!$T$6:$T$45,"KAS",MUTASI!$S$6:$S$45),0) -> 0
B31: Disusun dari setiap transaksi yang melibatkan akun kas (Kas Tunai, Kas Bank, Kas Warung) dan dikelompokkan menurut akun lawannya (kolom "Baris AK" di AKUN).

Sheet PERUBAHAN EKUITAS
A1: LAPORAN PERUBAHAN EKUITAS
A2: ="KOPI PARANG • "&"Periode 1 Januari – "&TEXT(DATE(TAHUN,BLN+1,0),"d")&" "&NAMA_BLN&" "&TAHUN -> KOPI PARANG • Periode 1 Januari – 30 September 2026
B4: Keterangan | C4: Jan | D4: Feb | E4: Mar | F4: Apr | G4: Mei | H4: Jun | I4: Jul | J4: Agu | K4: Sep | L4: Okt | M4: Nov | N4: Des | O4: ="s.d. "&LEFT(NAMA_BLN,3)&" "&TAHUN -> s.d. Sep 2026
C5: 1 | D5: 2 | E5: 3 | F5: 4 | G5: 5 | H5: 6 | I5: 7 | J5: 8 | K5: 9 | L5: 10 | M5: 11 | N5: 12
B6: Ekuitas awal | C6: =IF(C$5>BLN,"",-SUMIF(MUTASI!$B$6:$B$45,"Ekuitas Kopi Parang",MUTASI!$Q$6:$Q$45)-SUMIF(MUTASI!$B$6:$B$45,"Prive",MUTASI!$Q$6:$Q$45)) -> 113100685 | D6: =IF(D$5>BLN,"",N(C10)) -> 58541644 | E6: =IF(E$5>BLN,"",N(D10)) -> 48753526 | F6: =IF(F$5>BLN,"",N(E10)) -> 41262929 | G6: =IF(G$5>BLN,"",N(F10)) -> 17584319 | H6: =IF(H$5>BLN,"",N(G10)) -> 29505195 | I6: =IF(I$5>BLN,"",N(H10)) -> 31476429 | J6: =IF(J$5>BLN,"",N(I10)) -> 30616038 | K6: =IF(K$5>BLN,"",N(J10)) -> 46561335 | ... N6: =IF(N$5>BLN,"",N(M10)) | O6: =-SUMIF(MUTASI!$B$6:$B$45,"Ekuitas Kopi Parang",MUTASI!$Q$6:$Q$45)-SUMIF(MUTASI!$B$6:$B$45,"Prive",MUTASI!$Q$6:$Q$45) -> 113100685
B7: Setoran modal | C7: =IF(C$5>BLN,"",-SUMIF(MUTASI!$B$6:$B$45,"Ekuitas Kopi Parang",MUTASI!$E$6:$E$45)) -> 0 | D7: =IF(D$5>BLN,"",-SUMIF(MUTASI!$B$6:$B$45,"Ekuitas Kopi Parang",MUTASI!$F$6:$F$45)) -> 0 | E7: =IF(E$5>BLN,"",-SUMIF(MUTASI!$B$6:$B$45,"Ekuitas Kopi Parang",MUTASI!$G$6:$G$45)) -> 0 | F7: =IF(F$5>BLN,"",-SUMIF(MUTASI!$B$6:$B$45,"Ekuitas Kopi Parang",MUTASI!$H$6:$H$45)) -> 0 | G7: =IF(G$5>BLN,"",-SUMIF(MUTASI!$B$6:$B$45,"Ekuitas Kopi Parang",MUTASI!$I$6:$I$45)) -> 0 | H7: =IF(H$5>BLN,"",-SUMIF(MUTASI!$B$6:$B$45,"Ekuitas Kopi Parang",MUTASI!$J$6:$J$45)) -> 0 | I7: =IF(I$5>BLN,"",-SUMIF(MUTASI!$B$6:$B$45,"Ekuitas Kopi Parang",MUTASI!$K$6:$K$45)) -> 0 | J7: =IF(J$5>BLN,"",-SUMIF(MUTASI!$B$6:$B$45,"Ekuitas Kopi Parang",MUTASI!$L$6:$L$45)) -> 0 | K7: =IF(K$5>BLN,"",-SUMIF(MUTASI!$B$6:$B$45,"Ekuitas Kopi Parang",MUTASI!$M$6:$M$45)) -> 0 | L7: =IF(L$5>BLN,"",-SUMIF(MUTASI!$B$6:$B$45,"Ekuitas Kopi Parang",MUTASI!$N$6:$N$45)) | M7: =IF(M$5>BLN,"",-SUMIF(MUTASI!$B$6:$B$45,"Ekuitas Kopi Parang",MUTASI!$O$6:$O$45)) | N7: =IF(N$5>BLN,"",-SUMIF(MUTASI!$B$6:$B$45,"Ekuitas Kopi Parang",MUTASI!$P$6:$P$45)) | O7: =-SUMIF(MUTASI!$B$6:$B$45,"Ekuitas Kopi Parang",MUTASI!$R$6:$R$45) -> 0
B8: Laba (rugi) bersih | C8: =IF(C$5>BLN,"",N('LABA RUGI'!C43)) -> -51148041 | D8: =IF(D$5>BLN,"",N('LABA RUGI'!D43)) -> -6212118 | E8: =IF(E$5>BLN,"",N('LABA RUGI'!E43)) -> -3403297 | F8: =IF(F$5>BLN,"",N('LABA RUGI'!F43)) -> -20407510 | G8: =IF(G$5>BLN,"",N('LABA RUGI'!G43)) -> 16080376 | H8: =IF(H$5>BLN,"",N('LABA RUGI'!H43)) -> 5382034 | I8: =IF(I$5>BLN,"",N('LABA RUGI'!I43)) -> 4796009 | J8: =IF(J$5>BLN,"",N('LABA RUGI'!J43)) -> 17725947 | ... N8: =IF(N$5>BLN,"",N('LABA RUGI'!N43)) | O8: =N('LABA RUGI'!O43) -> -54996702
B9: Prive (pengambilan pemilik) | C9: =IF(C$5>BLN,"",-SUMIF(MUTASI!$B$6:$B$45,"Prive",MUTASI!$E$6:$E$45)) -> -3411000 | D9: =IF(D$5>BLN,"",-SUMIF(MUTASI!$B$6:$B$45,"Prive",MUTASI!$F$6:$F$45)) -> -3576000 | E9: =IF(E$5>BLN,"",-SUMIF(MUTASI!$B$6:$B$45,"Prive",MUTASI!$G$6:$G$45)) -> -4087300 | F9: =IF(F$5>BLN,"",-SUMIF(MUTASI!$B$6:$B$45,"Prive",MUTASI!$H$6:$H$45)) -> -3271100 | G9: =IF(G$5>BLN,"",-SUMIF(MUTASI!$B$6:$B$45,"Prive",MUTASI!$I$6:$I$45)) -> -4159500 | H9: =IF(H$5>BLN,"",-SUMIF(MUTASI!$B$6:$B$45,"Prive",MUTASI!$J$6:$J$45)) -> -3410800 | I9: =IF(I$5>BLN,"",-SUMIF(MUTASI!$B$6:$B$45,"Prive",MUTASI!$K$6:$K$45)) -> -5656400 | J9: =IF(J$5>BLN,"",-SUMIF(MUTASI!$B$6:$B$45,"Prive",MUTASI!$L$6:$L$45)) -> -1780650 | K9: =IF(K$5>BLN,"",-SUMIF(MUTASI!$B$6:$B$45,"Prive",MUTASI!$M$6:$M$45)) -> -1632000 | L9: =IF(L$5>BLN,"",-SUMIF(MUTASI!$B$6:$B$45,"Prive",MUTASI!$N$6:$N$45)) | M9: =IF(M$5>BLN,"",-SUMIF(MUTASI!$B$6:$B$45,"Prive",MUTASI!$O$6:$O$45)) | N9: =IF(N$5>BLN,"",-SUMIF(MUTASI!$B$6:$B$45,"Prive",MUTASI!$P$6:$P$45)) | O9: =-SUMIF(MUTASI!$B$6:$B$45,"Prive",MUTASI!$R$6:$R$45) -> -30984750
B10: EKUITAS AKHIR | C10: =IF(C$5>BLN,"",N(C6)+N(C7)+N(C8)+N(C9)) -> 58541644 | D10: =IF(D$5>BLN,"",N(D6)+N(D7)+N(D8)+N(D9)) -> 48753526 | E10: =IF(E$5>BLN,"",N(E6)+N(E7)+N(E8)+N(E9)) -> 41262929 | F10: =IF(F$5>BLN,"",N(F6)+N(F7)+N(F8)+N(F9)) -> 17584319 | G10: =IF(G$5>BLN,"",N(G6)+N(G7)+N(G8)+N(G9)) -> 29505195 | H10: =IF(H$5>BLN,"",N(H6)+N(H7)+N(H8)+N(H9)) -> 31476429 | I10: =IF(I$5>BLN,"",N(I6)+N(I7)+N(I8)+N(I9)) -> 30616038 | J10: =IF(J$5>BLN,"",N(J6)+N(J7)+N(J8)+N(J9)) -> 46561335 | ... N10: =IF(N$5>BLN,"",N(N6)+N(N7)+N(N8)+N(N9)) | O10: =N(O6)+N(O7)+N(O8)+N(O9) -> 27119233
B12: Cek vs total ekuitas di NERACA (harus 0) | O12: =ROUND(O10-NERACA!D35,0) -> 0

Sheet CALK
A1: CATATAN ATAS LAPORAN KEUANGAN (CALK)
A2: ="KOPI PARANG • "&"Periode 1 Januari – "&TEXT(DATE(TAHUN,BLN+1,0),"d")&" "&NAMA_BLN&" "&TAHUN -> KOPI PARANG • Periode 1 Januari – 30 September 2026
B4: 1 | C4: UMUM
C5: Kopi Parang adalah usaha cafe & kedai kopi yang juga menyelenggarakan event. Laporan ini disajikan dalam Rupiah penuh.
B6: 2 | C6: DASAR PENYUSUNAN
C7: Laporan disusun dengan basis akrual dan biaya historis, mengacu pada SAK EMKM (Standar Akuntansi Keuangan Entitas Mikro, Kecil, dan Menengah). Laporan arus kas dan perubahan ekuitas disajikan sebagai informasi tambahan.
C8: Periode yang dilaporkan dibatasi s.d. bulan tutup buku di PENGATURAN; bulan sesudahnya belum lengkap dan tidak disajikan.
B9: 3 | C9: KEBIJAKAN AKUNTANSI PENTING
C10: a. Pendapatan cafe diakui sebesar omzet bersih harian (omzet POS dikurangi selisih tunai yang tak terjelaskan dan selisih EDC). Konsumsi pemilik (bill owner) diperlakukan sebagai prive.
C11: b. Pajak restoran (PBJT) disajikan sebagai pengurang pendapatan. Estimasi kurang bayar diakui sebagai Utang Pajak Daerah bila diaktifkan di PENGATURAN.
C12: c. Persediaan: saat ini pembelian bahan baku langsung dibebankan. Mulai bulan berikutnya disarankan stok opname akhir bulan sehingga HPP = persediaan awal + pembelian − persediaan akhir.
C13: d. Aset tetap dicatat sebesar harga perolehan dan disusutkan garis lurus mulai bulan setelah perolehan. Masa manfaat: 4 tahun (peralatan & perabot), 5 tahun (kulkas).
B14: 4 | C14: KAS DAN SETARA KAS
C15: ="Saldo per tanggal laporan: Rp "&TEXT(NERACA!D7+NERACA!D8+NERACA!D9,"#,##0")&" (tunai Rp "&TEXT(NERACA!D7,"#,##0")&", bank Rp "&TEXT(NERACA!D8,"#,##0")&", kas kecil Rp "&TEXT(NERACA!D9,"#,##0")&"). Saldo kas tunai perlu didukung berita acara kas opname."&IF(NERACA!D8<0," Saldo bank menurut catatan negatif, sehingga wajib direkonsiliasi dengan rekening koran.","") -> Saldo per tanggal laporan: Rp 53,281,608 (tunai Rp 51,913,400, bank Rp -2,739,792, kas kecil Rp 4,108,000). Saldo kas tunai perlu didukung berita acara kas opname. Saldo bank menurut catatan negatif, sehingga wajib direkonsiliasi dengan rekening koran.
B16: 5 | C16: PIUTANG
C17: ="Piutang usaha Rp "&TEXT(NERACA!D10,"#,##0")&" merupakan omzet yang belum diterima (setoran tunai H+1 / settlement EDC). Piutang lain-lain Rp "&TEXT(NERACA!D11,"#,##0")&" terdiri dari bon karyawan dan pinjaman pihak lain, termasuk pinjaman pemilik." -> Piutang usaha Rp 0 merupakan omzet yang belum diterima (setoran tunai H+1 / settlement EDC). Piutang lain-lain Rp 8,133,335 terdiri dari bon karyawan dan pinjaman pihak lain, termasuk pinjaman pemilik.
B18: 6 | C18: ASET TETAP
C19: ="Harga perolehan Rp "&TEXT(NERACA!D17,"#,##0")&", akumulasi penyusutan Rp "&TEXT(-NERACA!D18,"#,##0")&". Aset yang dimiliki sebelum 2026 belum diinventarisasi sehingga belum tercermin di laporan ini." -> Harga perolehan Rp 42,023,410, akumulasi penyusutan Rp 2,564,119. Aset yang dimiliki sebelum 2026 belum diinventarisasi sehingga belum tercermin di laporan ini.
B20: 7 | C20: KEWAJIBAN PAJAK
C21: ="Omzet yang dilaporkan untuk PBJT lebih rendah dari omzet tercatat. Estimasi PBJT kurang bayar s.d. tanggal laporan Rp "&TEXT(PAJAK!J18,"#,##0")&" (belum termasuk sanksi). Kewajiban PPh atas usaha belum dicatat dan sedang ditelaah." -> Omzet yang dilaporkan untuk PBJT lebih rendah dari omzet tercatat. Estimasi PBJT kurang bayar s.d. tanggal laporan Rp 59,326,181 (belum termasuk sanksi). Kewajiban PPh atas usaha belum dicatat dan sedang ditelaah.
B22: 8 | C22: EKUITAS
C23: ="Modal pemilik awal tahun ditetapkan sebagai selisih aset dan liabilitas per 1 Januari. Prive s.d. tanggal laporan Rp "&TEXT(-NERACA!D33,"#,##0")&"." -> Modal pemilik awal tahun ditetapkan sebagai selisih aset dan liabilitas per 1 Januari. Prive s.d. tanggal laporan Rp 30,984,750.
B24: 9 | C24: KEJADIAN PENTING
C25: ="Event Maharia (Januari) menghasilkan rugi Rp "&TEXT(-SUMIFS('ANALISIS EVENT'!F:F,'ANALISIS EVENT'!B:B,"Event Maharia"),"#,##0")&", yang menjadi penyebab utama rugi kuartal I." -> Event Maharia (Januari) menghasilkan rugi Rp 46,680,054, yang menjadi penyebab utama rugi kuartal I.

Sheet REVIEW
A1: HASIL REVIEW FILE LAMA & TINDAKAN
A2: Prioritas: 🔴 kritis, 🟠 penting, 🟡 perbaikan. Kolom "Status" untuk dicentang tim keuangan.
A4: No | B4: Prioritas | C4: Area | D4: Temuan di file lama | E4: Dampak | F4: Yang sudah dikerjakan di v2 / rekomendasi | G4: Status
A5: 1 | B5: 🔴 | C5: Pajak | D5: Omzet yang dilaporkan ke Bapenda Jan–Sep Rp187,6 jt, padahal omzet tercatat di kasir Rp859 jt (±22%). Sheet27 berisi rumus pembagi omzet laporan ke harian. | E5: Potensi kurang bayar PBJT ±Rp59–67 jt + sanksi. Risiko hukum & reputasi, apalagi kalau laporan ditunjukkan ke bank/investor. | F5: Sheet27 tidak dibawa. Sheet PAJAK menghitung PBJT dari omzet asli dan kurang bayarnya diakui sebagai utang (bisa diatur di PENGATURAN). Rekomendasi: konsultan pajak & pembetulan SPTPD.
A6: 2 | B6: 🔴 | C6: Pajak | D6: Tidak ada pencatatan PPh atas usaha. | E6: Omzet 2026 > Rp1 M → ada kewajiban PPh yang belum dicadangkan. | F6: Dicatat di CALK. Tentukan skema PPh bersama konsultan pajak lalu tambahkan akun Beban/Utang PPh.
A7: 3 | B7: 🔴 | C7: Profitabilitas | D7: Laba bersih Jan–Sep hanya ±Rp5,6 jt (0,6%) sebelum koreksi pajak. Event Maharia rugi ±Rp47 jt. | E7: Usaha praktis impas; satu event besar bisa menghapus laba 1 kuartal. | F7: Sheet ANALISIS EVENT untuk evaluasi per event; indikator biaya di LABA RUGI & DASHBOARD.
A8: 4 | B8: 🔴 | C8: HPP / Persediaan | D8: Belanja bahan baku langsung dibebankan, tanpa stok opname. Sheet INVENTORI belum jalan (rumusnya hanya membaca baris 2–1001). | E8: Food cost loncat 24%–59% per bulan → laba bulanan tidak bisa dipercaya. | F8: Akun Inventori disiapkan. Rekomendasi: stok opname tiap akhir bulan, jurnal penyesuaian Inventori ↔ Biaya Bahan Baku.
A9: 5 | B9: 🔴 | C9: Aset Tetap | D9: Penyusutan hanya kulkas (Feb–Jul) karena bergantung centang "V" manual; ±Rp29 jt peralatan lain (termasuk grinder Rp12,8 jt) tidak disusutkan sama sekali. Saldo awal peralatan 0. | E9: Beban kurang saji, aset & ekuitas tidak mencerminkan kondisi nyata. | F9: Sheet ASET TETAP: penyusutan garis lurus otomatis → jurnal otomatis. Baris khusus aset pra-2026 untuk diinventarisasi.
A10: 6 | B10: 🔴 | C10: Uang Pemilik | D10: Bill Owner Rp12,4 jt dicatat sebagai piutang; "Owner pinjam" Rp4 jt di Piutang Lainnya; sewa "diubah jadi prive"; "gaji direktur". | E10: Piutang fiktif menggelembungkan aset; batas uang usaha vs pribadi kabur. | F10: Bill Owner kini dicatat sebagai Prive. Rekomendasi: kebijakan tertulis — gaji owner (beban) atau prive, jangan dicampur; tagih/selesaikan pinjaman owner.
A11: 7 | B11: 🟠 | C11: Arus Kas | D11: CASHFLOW hanya masuk/keluar per akun kas, termasuk pindah dana antar-kas (Rp205 jt Tunai→Bank dihitung dua kali). | E11: "Kas masuk" Rp1,25 M padahal pendapatan ±Rp0,9 M — menyesatkan. | F11: ARUS KAS metode langsung, 3 aktivitas (operasi/investasi/pendanaan), transfer antar-kas dikeluarkan, dicek ke neraca.
A12: 8 | B12: 🟠 | C12: Neraca | D12: Bentuk masih neraca saldo (debet/kredit), tidak dikelompokkan lancar/tidak lancar. Akumulasi penyusutan di sisi kredit. | E12: Tidak sesuai format laporan posisi keuangan standar. | F12: NERACA berklasifikasi dengan pembanding 1 Jan, akumulasi penyusutan sebagai pengurang aset, cek keseimbangan.
A13: 9 | B13: 🟠 | C13: Klasifikasi | D13: Pajak restoran & pendapatan event di "Tambahan Laba (Rugi)", sementara biaya event di marketing. Utang FM Wood/grinder di jangka panjang. | E13: Margin usaha & hasil event terdistorsi; utang jangka pendek tersembunyi. | F13: LABA RUGI multi-step: PBJT sebagai pengurang pendapatan, event di pendapatan usaha. Cek jatuh tempo utang FM Wood/grinder.
A14: 10 | B14: 🟠 | C14: Dashboard | D14: CEO: bulan berjalan (Okt) tampil untung 36% karena gaji/sewa belum dicatat; target kosong (error bagi nol); bulan "September" diketik manual. | E14: Keputusan bisa diambil dari angka yang salah. | F14: PENGATURAN "bulan tutup buku" mengunci semua laporan; DASHBOARD hanya menampilkan bulan yang sudah ditutup + cek kesehatan data.
A15: 11 | B15: 🟠 | C15: Omzet | D15: Realisasi tunai 9–11 Okt belum diisi sehingga dianggap "biaya selisih" Rp2,4 jt. | E15: Omzet bersih Okt kurang saji. | F15: OMZET HARIAN: bila realisasi belum diisi, selisih ditunda & status "Belum direalisasi"; piutang tetap tercatat.
A16: 12 | B16: 🟠 | C16: Rumus | D16: Banyak fungsi khusus Google Sheets (LET, LAMBDA, BYCOL, FILTER, QUERY) dan range terkunci (1000, 1003, 1007, 979). | E16: Rusak/nilai mati bila dibuka di Excel; data baru di luar range tidak terbaca. | F16: Semua rumus v2 memakai fungsi standar (SUMIFS, INDEX/MATCH) yang jalan di Excel & Google Sheets, dengan kapasitas 3.000 transaksi.
... A22: 18 | B22: 🟡 | C22: Struktur | D22: 24 sheet, banyak duplikat (JURNAL UMUM, 5 buku besar serupa, R-OMZET, Sheet27, BELANJA, ribuan baris kosong). | E22: Berat, membingungkan, mudah rusak. | F22: v2: alur jelas INPUT (OMZET HARIAN, JURNAL) → PROSES (MUTASI, BUKU BESAR, NERACA SALDO) → LAPORAN.
D24: Transaksi yang diberi tag event otomatis di v2:
D25: 12/01/2026 — Pemasukan penjualan tiket 12/01 event Maharia tgl 16/01 → Event Maharia
D26: 13/01/2026 — Pemasukan penjualan tiket 13/01 event Maharia tgl 16/01 → Event Maharia
D27: 14/01/2026 — Pembayaran transportasi tiket travel bus kru Iksan Skuter acara Maharia → Event Maharia
D28: 25/04/2026 — Sponsor Artefac UNS → Event Artefac
D29: 12/06/2026 — kupon & golden tiket Artefact UNS → Event Artefac
D30: 13/06/2026 — Biaya jalan/makan event artefack → Event Artefac

Sheet PAJAK
A1: REKONSILIASI PAJAK RESTORAN (PBJT)
A2: Membandingkan omzet asli (OMZET HARIAN) dengan omzet yang dilaporkan ke Bapenda. Angka dilaporkan diambil dari sheet TAX file lama.
A5: No | B5: Bulan | C5: Omzet Tercatat (asli) | D5: Omzet Dilaporkan | E5: % Dilaporkan | F5: DPP Seharusnya | G5: PBJT Terutang | H5: PBJT Dibayar (SSPD) | I5: Selisih Omzet Tak Dilaporkan | J5: PBJT Kurang Bayar | K5: Dibayar menurut JURNAL | L5: Cocok?
A6: 1 | B6: Januari | C6: =IF(A6>BLN,"",SUMIFS(OZ_TOTAL,OZ_BLN,A6)) -> 90994150 | D6: 20562000 | E6: =IF(OR(A6>BLN,N(C6)=0),"",N(D6)/C6) -> 0.22597057 | F6: =IF(A6>BLN,"",IF(INKL="YA",C6/(1+TARIF),C6)) -> 82721955 | G6: =IF(A6>BLN,"",ROUND(F6*TARIF,0)) -> 8272195 | H6: 2056200 | I6: =IF(A6>BLN,"",C6-N(D6)) -> 70432150 | J6: =IF(A6>BLN,0,G6-H6) -> 6215995 | K6: =IF(A6>BLN,"",-SUMIFS(J_KAS,J_LAWAN,"Pajak Restoran",J_BLN,A6,J_THN,TAHUN)) -> 2056200 | L6: =IF(A6>BLN,"",IF(ROUND(N(H6)-N(K6),0)=0,"✔","✘ beda")) -> ✔
A7: 2 | B7: Februari | C7: =IF(A7>BLN,"",SUMIFS(OZ_TOTAL,OZ_BLN,A7)) -> 73205500 | D7: 16640000 | E7: =IF(OR(A7>BLN,N(C7)=0),"",N(D7)/C7) -> 0.22730533 | F7: =IF(A7>BLN,"",IF(INKL="YA",C7/(1+TARIF),C7)) -> 66550455 | G7: =IF(A7>BLN,"",ROUND(F7*TARIF,0)) -> 6655045 | H7: 1664000 | I7: =IF(A7>BLN,"",C7-N(D7)) -> 56565500 | J7: =IF(A7>BLN,0,G7-H7) -> 4991045 | K7: =IF(A7>BLN,"",-SUMIFS(J_KAS,J_LAWAN,"Pajak Restoran",J_BLN,A7,J_THN,TAHUN)) -> 1664000 | L7: =IF(A7>BLN,"",IF(ROUND(N(H7)-N(K7),0)=0,"✔","✘ beda")) -> ✔
A8: 3 | B8: Maret | C8: =IF(A8>BLN,"",SUMIFS(OZ_TOTAL,OZ_BLN,A8)) -> 102364050 | D8: 23100000 | E8: =IF(OR(A8>BLN,N(C8)=0),"",N(D8)/C8) -> 0.22566516 | F8: =IF(A8>BLN,"",IF(INKL="YA",C8/(1+TARIF),C8)) -> 93058227 | G8: =IF(A8>BLN,"",ROUND(F8*TARIF,0)) -> 9305823 | H8: 2310000 | I8: =IF(A8>BLN,"",C8-N(D8)) -> 79264050 | J8: =IF(A8>BLN,0,G8-H8) -> 6995823 | K8: =IF(A8>BLN,"",-SUMIFS(J_KAS,J_LAWAN,"Pajak Restoran",J_BLN,A8,J_THN,TAHUN)) -> 2310000 | L8: =IF(A8>BLN,"",IF(ROUND(N(H8)-N(K8),0)=0,"✔","✘ beda")) -> ✔
A9: 4 | B9: April | C9: =IF(A9>BLN,"",SUMIFS(OZ_TOTAL,OZ_BLN,A9)) -> 94568800 | D9: 20580000 | E9: =IF(OR(A9>BLN,N(C9)=0),"",N(D9)/C9) -> 0.21761934 | F9: =IF(A9>BLN,"",IF(INKL="YA",C9/(1+TARIF),C9)) -> 85971636 | G9: =IF(A9>BLN,"",ROUND(F9*TARIF,0)) -> 8597164 | H9: 2058000 | I9: =IF(A9>BLN,"",C9-N(D9)) -> 73988800 | J9: =IF(A9>BLN,0,G9-H9) -> 6539164 | K9: =IF(A9>BLN,"",-SUMIFS(J_KAS,J_LAWAN,"Pajak Restoran",J_BLN,A9,J_THN,TAHUN)) -> 2058000 | L9: =IF(A9>BLN,"",IF(ROUND(N(H9)-N(K9),0)=0,"✔","✘ beda")) -> ✔
A10: 5 | B10: Mei | C10: =IF(A10>BLN,"",SUMIFS(OZ_TOTAL,OZ_BLN,A10)) -> 111296950 | D10: 22570000 | E10: =IF(OR(A10>BLN,N(C10)=0),"",N(D10)/C10) -> 0.20279082 | F10: =IF(A10>BLN,"",IF(INKL="YA",C10/(1+TARIF),C10)) -> 1.0117905e+08 | G10: =IF(A10>BLN,"",ROUND(F10*TARIF,0)) -> 10117905 | H10: 2257000 | I10: =IF(A10>BLN,"",C10-N(D10)) -> 88726950 | J10: =IF(A10>BLN,0,G10-H10) -> 7860905 | K10: =IF(A10>BLN,"",-SUMIFS(J_KAS,J_LAWAN,"Pajak Restoran",J_BLN,A10,J_THN,TAHUN)) -> 2257000 | L10: =IF(A10>BLN,"",IF(ROUND(N(H10)-N(K10),0)=0,"✔","✘ beda")) -> ✔
A11: 6 | B11: Juni | C11: =IF(A11>BLN,"",SUMIFS(OZ_TOTAL,OZ_BLN,A11)) -> 105392500 | D11: 22320000 | E11: =IF(OR(A11>BLN,N(C11)=0),"",N(D11)/C11) -> 0.21177978 | F11: =IF(A11>BLN,"",IF(INKL="YA",C11/(1+TARIF),C11)) -> 95811364 | G11: =IF(A11>BLN,"",ROUND(F11*TARIF,0)) -> 9581136 | H11: 2232000 | I11: =IF(A11>BLN,"",C11-N(D11)) -> 83072500 | J11: =IF(A11>BLN,0,G11-H11) -> 7349136 | K11: =IF(A11>BLN,"",-SUMIFS(J_KAS,J_LAWAN,"Pajak Restoran",J_BLN,A11,J_THN,TAHUN)) -> 2232000 | L11: =IF(A11>BLN,"",IF(ROUND(N(H11)-N(K11),0)=0,"✔","✘ beda")) -> ✔
A12: 7 | B12: Juli | C12: =IF(A12>BLN,"",SUMIFS(OZ_TOTAL,OZ_BLN,A12)) -> 93959650 | D12: 20940000 | E12: =IF(OR(A12>BLN,N(C12)=0),"",N(D12)/C12) -> 0.22286162 | F12: =IF(A12>BLN,"",IF(INKL="YA",C12/(1+TARIF),C12)) -> 85417864 | G12: =IF(A12>BLN,"",ROUND(F12*TARIF,0)) -> 8541786 | H12: 2094000 | I12: =IF(A12>BLN,"",C12-N(D12)) -> 73019650 | J12: =IF(A12>BLN,0,G12-H12) -> 6447786 | K12: =IF(A12>BLN,"",-SUMIFS(J_KAS,J_LAWAN,"Pajak Restoran",J_BLN,A12,J_THN,TAHUN)) -> 2094000 | L12: =IF(A12>BLN,"",IF(ROUND(N(H12)-N(K12),0)=0,"✔","✘ beda")) -> ✔
A13: 8 | B13: Agustus | C13: =IF(A13>BLN,"",SUMIFS(OZ_TOTAL,OZ_BLN,A13)) -> 94907750 | D13: 19951000 | E13: =IF(OR(A13>BLN,N(C13)=0),"",N(D13)/C13) -> 0.21021466 | F13: =IF(A13>BLN,"",IF(INKL="YA",C13/(1+TARIF),C13)) -> 86279773 | G13: =IF(A13>BLN,"",ROUND(F13*TARIF,0)) -> 8627977 | H13: 1995100 | I13: =IF(A13>BLN,"",C13-N(D13)) -> 74956750 | J13: =IF(A13>BLN,0,G13-H13) -> 6632877 | K13: =IF(A13>BLN,"",-SUMIFS(J_KAS,J_LAWAN,"Pajak Restoran",J_BLN,A13,J_THN,TAHUN)) -> 1995100 | L13: =IF(A13>BLN,"",IF(ROUND(N(H13)-N(K13),0)=0,"✔","✘ beda")) -> ✔
A14: 9 | B14: September | C14: =IF(A14>BLN,"",SUMIFS(OZ_TOTAL,OZ_BLN,A14)) -> 92283950 | D14: 20960000 | E14: =IF(OR(A14>BLN,N(C14)=0),"",N(D14)/C14) -> 0.22712509 | F14: =IF(A14>BLN,"",IF(INKL="YA",C14/(1+TARIF),C14)) -> 83894500 | G14: =IF(A14>BLN,"",ROUND(F14*TARIF,0)) -> 8389450 | H14: 2096000 | I14: =IF(A14>BLN,"",C14-N(D14)) -> 71323950 | J14: =IF(A14>BLN,0,G14-H14) -> 6293450 | K14: =IF(A14>BLN,"",-SUMIFS(J_KAS,J_LAWAN,"Pajak Restoran",J_BLN,A14,J_THN,TAHUN)) -> 2096000 | L14: =IF(A14>BLN,"",IF(ROUND(N(H14)-N(K14),0)=0,"✔","✘ beda")) -> ✔
A15: 10 | B15: Oktober | C15: =IF(A15>BLN,"",SUMIFS(OZ_TOTAL,OZ_BLN,A15)) | E15: =IF(OR(A15>BLN,N(C15)=0),"",N(D15)/C15) | F15: =IF(A15>BLN,"",IF(INKL="YA",C15/(1+TARIF),C15)) | G15: =IF(A15>BLN,"",ROUND(F15*TARIF,0)) | I15: =IF(A15>BLN,"",C15-N(D15)) | J15: =IF(A15>BLN,0,G15-H15) -> 0 | K15: =IF(A15>BLN,"",-SUMIFS(J_KAS,J_LAWAN,"Pajak Restoran",J_BLN,A15,J_THN,TAHUN)) | L15: =IF(A15>BLN,"",IF(ROUND(N(H15)-N(K15),0)=0,"✔","✘ beda"))
A16: 11 | B16: November | C16: =IF(A16>BLN,"",SUMIFS(OZ_TOTAL,OZ_BLN,A16)) | E16: =IF(OR(A16>BLN,N(C16)=0),"",N(D16)/C16) | F16: =IF(A16>BLN,"",IF(INKL="YA",C16/(1+TARIF),C16)) | G16: =IF(A16>BLN,"",ROUND(F16*TARIF,0)) | I16: =IF(A16>BLN,"",C16-N(D16)) | J16: =IF(A16>BLN,0,G16-H16) -> 0 | K16: =IF(A16>BLN,"",-SUMIFS(J_KAS,J_LAWAN,"Pajak Restoran",J_BLN,A16,J_THN,TAHUN)) | L16: =IF(A16>BLN,"",IF(ROUND(N(H16)-N(K16),0)=0,"✔","✘ beda"))
A17: 12 | B17: Desember | C17: =IF(A17>BLN,"",SUMIFS(OZ_TOTAL,OZ_BLN,A17)) | E17: =IF(OR(A17>BLN,N(C17)=0),"",N(D17)/C17) | F17: =IF(A17>BLN,"",IF(INKL="YA",C17/(1+TARIF),C17)) | G17: =IF(A17>BLN,"",ROUND(F17*TARIF,0)) | I17: =IF(A17>BLN,"",C17-N(D17)) | J17: =IF(A17>BLN,0,G17-H17) -> 0 | K17: =IF(A17>BLN,"",-SUMIFS(J_KAS,J_LAWAN,"Pajak Restoran",J_BLN,A17,J_THN,TAHUN)) | L17: =IF(A17>BLN,"",IF(ROUND(N(H17)-N(K17),0)=0,"✔","✘ beda"))
B18: TOTAL | C18: =SUMIFS(C6:C17,$A$6:$A$17,"<="&BLN) -> 858973300 | D18: =SUMIFS(D6:D17,$A$6:$A$17,"<="&BLN) -> 187623000 | E18: =IF(C18=0,"",D18/C18) -> 0.21842705 | F18: =SUMIFS(F6:F17,$A$6:$A$17,"<="&BLN) -> 7.8088482e+08 | G18: =SUMIFS(G6:G17,$A$6:$A$17,"<="&BLN) -> 78088481 | H18: =SUMIFS(H6:H17,$A$6:$A$17,"<="&BLN) -> 18762300 | I18: =SUMIFS(I6:I17,$A$6:$A$17,"<="&BLN) -> 671350300 | J18: =SUMIFS(J6:J17,$A$6:$A$17,"<="&BLN) -> 59326181 | K18: =SUMIFS(K6:K17,$A$6:$A$17,"<="&BLN) -> 18762300
B21: Catatan:
B22: 1. PBJT terutang dihitung dari omzet ASLI dengan tarif & asumsi di PENGATURAN (harga termasuk pajak atau tidak).
B23: 2. Kurang bayar BELUM termasuk sanksi administratif (bunga/denda) dari Bapenda.
B24: 3. Bila PENGATURAN "Akui estimasi PBJT kurang bayar" = YA, kolom J otomatis dijurnal: Pajak Restoran (D) / Utang Pajak Daerah (K).
B25: 4. Langkah yang disarankan: konsultasikan dengan konsultan pajak soal pembetulan SPTPD, lalu laporkan omzet sesuai data kasir mulai bulan berjalan.
B26: 5. PPh atas usaha BELUM dicatat sama sekali. Omzet 2026 diperkirakan > Rp1 miliar. Pastikan skema PPh (mis. PPh Final UMKM atau tarif umum) bersama konsultan pajak.

Sheet ANALISIS EVENT
A1: ANALISIS LABA RUGI PER EVENT
A2: Berdasarkan kolom "Tag Event" di JURNAL (seluruh data). Biaya yang tidak diberi tag tidak ikut terhitung — biasakan selalu isi tag.
B4: Event | C4: Tanggal Pertama | D4: Pendapatan | E4: Biaya | F4: Laba (Rugi) | G4: Biaya per Rp1 Pendapatan | H4: Keterangan
B5: Event Ragaria | C5: =_xlfn.MINIFS(J_TGL,J_TAG,B5) -> 46024 | D5: =SUMIFS(J_NOM,J_TAG,B5,J_KELK,"PENDAPATAN") -> 0 | E5: =SUMIFS(J_NOM,J_TAG,B5,J_KELD,"BEBAN") -> 5630000 | F5: =D5-E5 -> -5630000 | G5: =IF(D5=0,"",E5/D5)
B6: Event Maharia | C6: =_xlfn.MINIFS(J_TGL,J_TAG,B6) -> 46027 | D6: =SUMIFS(J_NOM,J_TAG,B6,J_KELK,"PENDAPATAN") -> 7870000 | E6: =SUMIFS(J_NOM,J_TAG,B6,J_KELD,"BEBAN") -> 54550054 | F6: =D6-E6 -> -46680054 | G6: =IF(D6=0,"",E6/D6) -> 6.9313919 | H6: Biaya talent, orkestra & sound besar; pemasukan tiket jauh di bawah biaya
B7: Event Artefac | C7: =_xlfn.MINIFS(J_TGL,J_TAG,B7) -> 46137 | D7: =SUMIFS(J_NOM,J_TAG,B7,J_KELK,"PENDAPATAN") -> 1000000 | E7: =SUMIFS(J_NOM,J_TAG,B7,J_KELD,"BEBAN") -> 1727601 | F7: =D7-E7 -> -727601 | G7: =IF(D7=0,"",E7/D7) -> 1.727601
B8: Event Yoga | C8: =_xlfn.MINIFS(J_TGL,J_TAG,B8) -> 46233 | D8: =SUMIFS(J_NOM,J_TAG,B8,J_KELK,"PENDAPATAN") -> 1610000 | E8: =SUMIFS(J_NOM,J_TAG,B8,J_KELD,"BEBAN") -> 373000 | F8: =D8-E8 -> 1237000 | G8: =IF(D8=0,"",E8/D8) -> 0.23167702
B9: Event Solo Coffee Party | C9: =_xlfn.MINIFS(J_TGL,J_TAG,B9) -> 46263 | D9: =SUMIFS(J_NOM,J_TAG,B9,J_KELK,"PENDAPATAN") -> 1994000 | E9: =SUMIFS(J_NOM,J_TAG,B9,J_KELD,"BEBAN") -> 8872000 | F9: =D9-E9 -> -6878000 | G9: =IF(D9=0,"",E9/D9) -> 4.449348
B10: Event Lokananta | C10: =_xlfn.MINIFS(J_TGL,J_TAG,B10) -> 46278 | D10: =SUMIFS(J_NOM,J_TAG,B10,J_KELK,"PENDAPATAN") -> 1394250 | E10: =SUMIFS(J_NOM,J_TAG,B10,J_KELD,"BEBAN") -> 0 | F10: =D10-E10 -> 1394250 | G10: =IF(D10=0,"",E10/D10) -> 0
B11: TOTAL EVENT | D11: =SUM(D5:D10) -> 13868250 | E11: =SUM(E5:E10) -> 71152655 | F11: =SUM(F5:F10) -> -57284405
B13: Saran: buat anggaran per event sebelum jalan (target tiket/sponsor ≥ biaya), dan evaluasi dampak event ke omzet cafe di hari-hari setelahnya.
B14: 6 transaksi yang keterangannya menyebut nama event tapi belum diberi tag, sudah diberi tag otomatis di versi ini.

Sheet REKAP OMZET
A1: REKAP OMZET BULANAN
A2: Data operasional dari OMZET HARIAN (termasuk bulan berjalan).
B4: Keterangan | C4: Jan | D4: Feb | E4: Mar | F4: Apr | G4: Mei | H4: Jun | I4: Jul | J4: Agu | K4: Sep | L4: Okt | M4: Nov | N4: Des | O4: Total
C5: 1 | D5: 2 | E5: 3 | F5: 4 | G5: 5 | H5: 6 | I5: 7 | J5: 8 | K5: 9 | L5: 10 | M5: 11 | N5: 12
B6: Omzet tercatat (POS) | C6: =SUMIFS('OMZET HARIAN'!$E$5:$E$369,OZ_BLN,C$5) -> 90994150 | D6: =SUMIFS('OMZET HARIAN'!$E$5:$E$369,OZ_BLN,D$5) -> 73205500 | E6: =SUMIFS('OMZET HARIAN'!$E$5:$E$369,OZ_BLN,E$5) -> 102364050 | F6: =SUMIFS('OMZET HARIAN'!$E$5:$E$369,OZ_BLN,F$5) -> 94568800 | G6: =SUMIFS('OMZET HARIAN'!$E$5:$E$369,OZ_BLN,G$5) -> 111296950 | H6: =SUMIFS('OMZET HARIAN'!$E$5:$E$369,OZ_BLN,H$5) -> 105392500 | I6: =SUMIFS('OMZET HARIAN'!$E$5:$E$369,OZ_BLN,I$5) -> 93959650 | J6: =SUMIFS('OMZET HARIAN'!$E$5:$E$369,OZ_BLN,J$5) -> 94907750 | ... N6: =SUMIFS('OMZET HARIAN'!$E$5:$E$369,OZ_BLN,N$5) -> 0 | O6: =SUM(C6:N6) -> 892143200
B7: Tunai | C7: =SUMIFS('OMZET HARIAN'!$C$5:$C$369,OZ_BLN,C$5) -> 25237450 | D7: =SUMIFS('OMZET HARIAN'!$C$5:$C$369,OZ_BLN,D$5) -> 21958400 | E7: =SUMIFS('OMZET HARIAN'!$C$5:$C$369,OZ_BLN,E$5) -> 32347300 | F7: =SUMIFS('OMZET HARIAN'!$C$5:$C$369,OZ_BLN,F$5) -> 29245650 | G7: =SUMIFS('OMZET HARIAN'!$C$5:$C$369,OZ_BLN,G$5) -> 32636000 | H7: =SUMIFS('OMZET HARIAN'!$C$5:$C$369,OZ_BLN,H$5) -> 25968500 | I7: =SUMIFS('OMZET HARIAN'!$C$5:$C$369,OZ_BLN,I$5) -> 24974000 | J7: =SUMIFS('OMZET HARIAN'!$C$5:$C$369,OZ_BLN,J$5) -> 22426900 | ... N7: =SUMIFS('OMZET HARIAN'!$C$5:$C$369,OZ_BLN,N$5) -> 0 | O7: =SUM(C7:N7) -> 244028750
B8: EDC / QRIS | C8: =SUMIFS('OMZET HARIAN'!$D$5:$D$369,OZ_BLN,C$5) -> 65756700 | D8: =SUMIFS('OMZET HARIAN'!$D$5:$D$369,OZ_BLN,D$5) -> 51247100 | E8: =SUMIFS('OMZET HARIAN'!$D$5:$D$369,OZ_BLN,E$5) -> 70016750 | F8: =SUMIFS('OMZET HARIAN'!$D$5:$D$369,OZ_BLN,F$5) -> 65323150 | G8: =SUMIFS('OMZET HARIAN'!$D$5:$D$369,OZ_BLN,G$5) -> 78660950 | H8: =SUMIFS('OMZET HARIAN'!$D$5:$D$369,OZ_BLN,H$5) -> 79424000 | I8: =SUMIFS('OMZET HARIAN'!$D$5:$D$369,OZ_BLN,I$5) -> 68985650 | J8: =SUMIFS('OMZET HARIAN'!$D$5:$D$369,OZ_BLN,J$5) -> 72480850 | ... N8: =SUMIFS('OMZET HARIAN'!$D$5:$D$369,OZ_BLN,N$5) -> 0 | O8: =SUM(C8:N8) -> 648114450
B9: Realisasi masuk kas | C9: =SUMIFS('OMZET HARIAN'!$I$5:$I$369,OZ_BLN,C$5) -> 88239977 | D9: =SUMIFS('OMZET HARIAN'!$I$5:$I$369,OZ_BLN,D$5) -> 71420788 | E9: =SUMIFS('OMZET HARIAN'!$I$5:$I$369,OZ_BLN,E$5) -> 100366744 | F9: =SUMIFS('OMZET HARIAN'!$I$5:$I$369,OZ_BLN,F$5) -> 92542488 | G9: =SUMIFS('OMZET HARIAN'!$I$5:$I$369,OZ_BLN,G$5) -> 109328974 | H9: =SUMIFS('OMZET HARIAN'!$I$5:$I$369,OZ_BLN,H$5) -> 103966227 | I9: =SUMIFS('OMZET HARIAN'!$I$5:$I$369,OZ_BLN,I$5) -> 91223181 | J9: =SUMIFS('OMZET HARIAN'!$I$5:$I$369,OZ_BLN,J$5) -> 91999684 | ... N9: =SUMIFS('OMZET HARIAN'!$I$5:$I$369,OZ_BLN,N$5) -> 0 | O9: =SUM(C9:N9) -> 869227739
B10: Selisih tunai | C10: =SUMIFS('OMZET HARIAN'!$J$5:$J$369,OZ_BLN,C$5) -> 2443450 | D10: =SUMIFS('OMZET HARIAN'!$J$5:$J$369,OZ_BLN,D$5) -> 1624900 | E10: =SUMIFS('OMZET HARIAN'!$J$5:$J$369,OZ_BLN,E$5) -> 2112800 | F10: =SUMIFS('OMZET HARIAN'!$J$5:$J$369,OZ_BLN,F$5) -> 2054650 | G10: =SUMIFS('OMZET HARIAN'!$J$5:$J$369,OZ_BLN,G$5) -> 2008900 | H10: =SUMIFS('OMZET HARIAN'!$J$5:$J$369,OZ_BLN,H$5) -> 1448500 | I10: =SUMIFS('OMZET HARIAN'!$J$5:$J$369,OZ_BLN,I$5) -> 2789000 | J10: =SUMIFS('OMZET HARIAN'!$J$5:$J$369,OZ_BLN,J$5) -> 2911400 | ... N10: =SUMIFS('OMZET HARIAN'!$J$5:$J$369,OZ_BLN,N$5) -> 0 | O10: =SUM(C10:N10) -> 20689150
B11: dijelaskan: bon karyawan | C11: =SUMIFS('OMZET HARIAN'!$L$5:$L$369,OZ_BLN,C$5) -> 312200 | D11: =SUMIFS('OMZET HARIAN'!$L$5:$L$369,OZ_BLN,D$5) -> 270300 | E11: =SUMIFS('OMZET HARIAN'!$L$5:$L$369,OZ_BLN,E$5) -> 273500 | F11: =SUMIFS('OMZET HARIAN'!$L$5:$L$369,OZ_BLN,F$5) -> 252300 | G11: =SUMIFS('OMZET HARIAN'!$L$5:$L$369,OZ_BLN,G$5) -> 228300 | H11: =SUMIFS('OMZET HARIAN'!$L$5:$L$369,OZ_BLN,H$5) -> 354900 | I11: =SUMIFS('OMZET HARIAN'!$L$5:$L$369,OZ_BLN,I$5) -> 610800 | J11: =SUMIFS('OMZET HARIAN'!$L$5:$L$369,OZ_BLN,J$5) -> 292200 | ... N11: =SUMIFS('OMZET HARIAN'!$L$5:$L$369,OZ_BLN,N$5) -> 0 | O11: =SUM(C11:N11) -> 3037600
B12: dijelaskan: compliment | C12: =SUMIFS('OMZET HARIAN'!$M$5:$M$369,OZ_BLN,C$5) -> 1220000 | D12: =SUMIFS('OMZET HARIAN'!$M$5:$M$369,OZ_BLN,D$5) -> 339300 | E12: =SUMIFS('OMZET HARIAN'!$M$5:$M$369,OZ_BLN,E$5) -> 282300 | F12: =SUMIFS('OMZET HARIAN'!$M$5:$M$369,OZ_BLN,F$5) -> 986000 | G12: =SUMIFS('OMZET HARIAN'!$M$5:$M$369,OZ_BLN,G$5) -> 96000 | H12: =SUMIFS('OMZET HARIAN'!$M$5:$M$369,OZ_BLN,H$5) -> 166300 | I12: =SUMIFS('OMZET HARIAN'!$M$5:$M$369,OZ_BLN,I$5) -> 432900 | J12: =SUMIFS('OMZET HARIAN'!$M$5:$M$369,OZ_BLN,J$5) -> 642600 | ... N12: =SUMIFS('OMZET HARIAN'!$M$5:$M$369,OZ_BLN,N$5) -> 0 | O12: =SUM(C12:N12) -> 4480000
B13: dijelaskan: bill owner | C13: =SUMIFS('OMZET HARIAN'!$N$5:$N$369,OZ_BLN,C$5) -> 911000 | D13: =SUMIFS('OMZET HARIAN'!$N$5:$N$369,OZ_BLN,D$5) -> 1076000 | E13: =SUMIFS('OMZET HARIAN'!$N$5:$N$369,OZ_BLN,E$5) -> 1587300 | F13: =SUMIFS('OMZET HARIAN'!$N$5:$N$369,OZ_BLN,F$5) -> 771100 | G13: =SUMIFS('OMZET HARIAN'!$N$5:$N$369,OZ_BLN,G$5) -> 1659500 | H13: =SUMIFS('OMZET HARIAN'!$N$5:$N$369,OZ_BLN,H$5) -> 910800 | I13: =SUMIFS('OMZET HARIAN'!$N$5:$N$369,OZ_BLN,I$5) -> 1656400 | J13: =SUMIFS('OMZET HARIAN'!$N$5:$N$369,OZ_BLN,J$5) -> 1780650 | ... N13: =SUMIFS('OMZET HARIAN'!$N$5:$N$369,OZ_BLN,N$5) -> 0 | O13: =SUM(C13:N13) -> 12408950
B14: Selisih tunai tak terjelaskan | C14: =SUMIFS('OMZET HARIAN'!$O$5:$O$369,OZ_BLN,C$5) -> 250 | D14: =SUMIFS('OMZET HARIAN'!$O$5:$O$369,OZ_BLN,D$5) -> -60700 | E14: =SUMIFS('OMZET HARIAN'!$O$5:$O$369,OZ_BLN,E$5) -> -30300 | F14: =SUMIFS('OMZET HARIAN'!$O$5:$O$369,OZ_BLN,F$5) -> 45250 | G14: =SUMIFS('OMZET HARIAN'!$O$5:$O$369,OZ_BLN,G$5) -> 25100 | H14: =SUMIFS('OMZET HARIAN'!$O$5:$O$369,OZ_BLN,H$5) -> 16500 | I14: =SUMIFS('OMZET HARIAN'!$O$5:$O$369,OZ_BLN,I$5) -> 88900 | J14: =SUMIFS('OMZET HARIAN'!$O$5:$O$369,OZ_BLN,J$5) -> 195950 | ... N14: =SUMIFS('OMZET HARIAN'!$O$5:$O$369,OZ_BLN,N$5) -> 0 | O14: =SUM(C14:N14) -> 762600
B15: Selisih EDC (MDR / settlement) | C15: =SUMIFS('OMZET HARIAN'!$K$5:$K$369,OZ_BLN,C$5) -> 310723 | D15: =SUMIFS('OMZET HARIAN'!$K$5:$K$369,OZ_BLN,D$5) -> 159812 | E15: =SUMIFS('OMZET HARIAN'!$K$5:$K$369,OZ_BLN,E$5) -> -115494 | F15: =SUMIFS('OMZET HARIAN'!$K$5:$K$369,OZ_BLN,F$5) -> -28338 | G15: =SUMIFS('OMZET HARIAN'!$K$5:$K$369,OZ_BLN,G$5) -> -40924 | H15: =SUMIFS('OMZET HARIAN'!$K$5:$K$369,OZ_BLN,H$5) -> -22227 | I15: =SUMIFS('OMZET HARIAN'!$K$5:$K$369,OZ_BLN,I$5) -> -52531 | J15: =SUMIFS('OMZET HARIAN'!$K$5:$K$369,OZ_BLN,J$5) -> -3334 | ... N15: =SUMIFS('OMZET HARIAN'!$K$5:$K$369,OZ_BLN,N$5) -> 0 | O15: =SUM(C15:N15) -> 129611
B16: OMZET BERSIH | C16: =SUMIFS('OMZET HARIAN'!$Q$5:$Q$369,OZ_BLN,C$5) -> 90683177 | D16: =SUMIFS('OMZET HARIAN'!$Q$5:$Q$369,OZ_BLN,D$5) -> 73106388 | E16: =SUMIFS('OMZET HARIAN'!$Q$5:$Q$369,OZ_BLN,E$5) -> 102509844 | F16: =SUMIFS('OMZET HARIAN'!$Q$5:$Q$369,OZ_BLN,F$5) -> 94551888 | G16: =SUMIFS('OMZET HARIAN'!$Q$5:$Q$369,OZ_BLN,G$5) -> 111312774 | H16: =SUMIFS('OMZET HARIAN'!$Q$5:$Q$369,OZ_BLN,H$5) -> 105398227 | I16: =SUMIFS('OMZET HARIAN'!$Q$5:$Q$369,OZ_BLN,I$5) -> 93923281 | J16: =SUMIFS('OMZET HARIAN'!$Q$5:$Q$369,OZ_BLN,J$5) -> 94715134 | ... N16: =SUMIFS('OMZET HARIAN'!$Q$5:$Q$369,OZ_BLN,N$5) -> 0 | O16: =SUM(C16:N16) -> 891250989
B18: Hari buka | C18: =COUNTIFS(OZ_BLN,C$5,OZ_TOTAL,">0") -> 31 | D18: =COUNTIFS(OZ_BLN,D$5,OZ_TOTAL,">0") -> 28 | E18: =COUNTIFS(OZ_BLN,E$5,OZ_TOTAL,">0") -> 29 | F18: =COUNTIFS(OZ_BLN,F$5,OZ_TOTAL,">0") -> 30 | G18: =COUNTIFS(OZ_BLN,G$5,OZ_TOTAL,">0") -> 31 | H18: =COUNTIFS(OZ_BLN,H$5,OZ_TOTAL,">0") -> 30 | I18: =COUNTIFS(OZ_BLN,I$5,OZ_TOTAL,">0") -> 31 | J18: =COUNTIFS(OZ_BLN,J$5,OZ_TOTAL,">0") -> 30 | ... N18: =COUNTIFS(OZ_BLN,N$5,OZ_TOTAL,">0") -> 0 | O18: =SUM(C18:N18) -> 281
B19: Rata-rata omzet bersih / hari | C19: =IFERROR(C16/C18,0) -> 2925263.8 | D19: =IFERROR(D16/D18,0) -> 2610942.4 | E19: =IFERROR(E16/E18,0) -> 3534822.2 | F19: =IFERROR(F16/F18,0) -> 3151729.6 | G19: =IFERROR(G16/G18,0) -> 3590734.6 | H19: =IFERROR(H16/H18,0) -> 3513274.2 | I19: =IFERROR(I16/I18,0) -> 3029783.3 | J19: =IFERROR(J16/J18,0) -> 3157171.1 | ... O19: =IFERROR(O16/O18,0) -> 3171711.7
B20: Jumlah transaksi | C20: =SUMIFS('OMZET HARIAN'!$S$5:$S$369,OZ_BLN,C$5) -> 1948 | D20: =SUMIFS('OMZET HARIAN'!$S$5:$S$369,OZ_BLN,D$5) -> 1533 | E20: =SUMIFS('OMZET HARIAN'!$S$5:$S$369,OZ_BLN,E$5) -> 2077 | F20: =SUMIFS('OMZET HARIAN'!$S$5:$S$369,OZ_BLN,F$5) -> 1968 | G20: =SUMIFS('OMZET HARIAN'!$S$5:$S$369,OZ_BLN,G$5) -> 2278 | H20: =SUMIFS('OMZET HARIAN'!$S$5:$S$369,OZ_BLN,H$5) -> 2189 | I20: =SUMIFS('OMZET HARIAN'!$S$5:$S$369,OZ_BLN,I$5) -> 1934 | J20: =SUMIFS('OMZET HARIAN'!$S$5:$S$369,OZ_BLN,J$5) -> 1878 | ... N20: =SUMIFS('OMZET HARIAN'!$S$5:$S$369,OZ_BLN,N$5) -> 0 | O20: =SUM(C20:N20) -> 18047
B21: Rata-rata nilai / transaksi (avg ticket) | C21: =IFERROR(C16/C20,0) -> 46551.939 | D21: =IFERROR(D16/D20,0) -> 47688.446 | E21: =IFERROR(E16/E20,0) -> 49354.764 | F21: =IFERROR(F16/F20,0) -> 48044.659 | G21: =IFERROR(G16/G20,0) -> 48864.255 | H21: =IFERROR(H16/H20,0) -> 48149.03 | I21: =IFERROR(I16/I20,0) -> 48564.261 | J21: =IFERROR(J16/J20,0) -> 50434.044 | ... O21: =IFERROR(O16/O20,0) -> 49384.994
B22: Produk terjual | C22: =SUMIFS('OMZET HARIAN'!$R$5:$R$369,OZ_BLN,C$5) -> 3579 | D22: =SUMIFS('OMZET HARIAN'!$R$5:$R$369,OZ_BLN,D$5) -> 2855 | E22: =SUMIFS('OMZET HARIAN'!$R$5:$R$369,OZ_BLN,E$5) -> 3931 | F22: =SUMIFS('OMZET HARIAN'!$R$5:$R$369,OZ_BLN,F$5) -> 3656 | G22: =SUMIFS('OMZET HARIAN'!$R$5:$R$369,OZ_BLN,G$5) -> 4232 | H22: =SUMIFS('OMZET HARIAN'!$R$5:$R$369,OZ_BLN,H$5) -> 3870 | I22: =SUMIFS('OMZET HARIAN'!$R$5:$R$369,OZ_BLN,I$5) -> 3370 | J22: =SUMIFS('OMZET HARIAN'!$R$5:$R$369,OZ_BLN,J$5) -> 3376 | ... N22: =SUMIFS('OMZET HARIAN'!$R$5:$R$369,OZ_BLN,N$5) -> 0 | O22: =SUM(C22:N22) -> 32739
B23: Target omzet | C23: =TARGET -> 100000000 | D23: =TARGET -> 100000000 | E23: =TARGET -> 100000000 | F23: =TARGET -> 100000000 | G23: =TARGET -> 100000000 | H23: =TARGET -> 100000000 | I23: =TARGET -> 100000000 | J23: =TARGET -> 100000000 | ... N23: =TARGET -> 100000000 | O23: =SUMPRODUCT((C16:N16>0)*C23:N23) -> 1000000000
B24: Pencapaian target | C24: =IF(C16=0,"",IFERROR(C16/C23,"")) -> 0.90683177 | D24: =IF(D16=0,"",IFERROR(D16/D23,"")) -> 0.73106388 | E24: =IF(E16=0,"",IFERROR(E16/E23,"")) -> 1.0250984 | F24: =IF(F16=0,"",IFERROR(F16/F23,"")) -> 0.94551888 | G24: =IF(G16=0,"",IFERROR(G16/G23,"")) -> 1.1131277 | H24: =IF(H16=0,"",IFERROR(H16/H23,"")) -> 1.0539823 | I24: =IF(I16=0,"",IFERROR(I16/I23,"")) -> 0.93923281 | J24: =IF(J16=0,"",IFERROR(J16/J23,"")) -> 0.94715134 | ... N24: =IF(N16=0,"",IFERROR(N16/N23,"")) | O24: =IFERROR(O16/O23,"") -> 0.89125099
B25: Pertumbuhan vs bulan lalu | C25: ="" | D25: =IF(OR(D16=0,C16=0),"",D16/C16-1) -> -0.19382635 | E25: =IF(OR(E16=0,D16=0),"",E16/D16-1) -> 0.40220091 | F25: =IF(OR(F16=0,E16=0),"",F16/E16-1) -> -0.07763114 | G25: =IF(OR(G16=0,F16=0),"",G16/F16-1) -> 0.17726654 | H25: =IF(OR(H16=0,G16=0),"",H16/G16-1) -> -0.053134486 | I25: =IF(OR(I16=0,H16=0),"",I16/H16-1) -> -0.10887229 | J25: =IF(OR(J16=0,I16=0),"",J16/I16-1) -> 0.008430849 | K25: =IF(OR(K16=0,J16=0),"",K16/J16-1) -> -0.026398252 | ... N25: =IF(OR(N16=0,M16=0),"",N16/M16-1) | O25: =""
B26: Hari belum direalisasi / perlu dicek | C26: =COUNTIFS(OZ_BLN,C$5,'OMZET HARIAN'!$U$5:$U$369,"<>OK",OZ_TOTAL,">0") -> 0 | D26: =COUNTIFS(OZ_BLN,D$5,'OMZET HARIAN'!$U$5:$U$369,"<>OK",OZ_TOTAL,">0") -> 1 | E26: =COUNTIFS(OZ_BLN,E$5,'OMZET HARIAN'!$U$5:$U$369,"<>OK",OZ_TOTAL,">0") -> 0 | F26: =COUNTIFS(OZ_BLN,F$5,'OMZET HARIAN'!$U$5:$U$369,"<>OK",OZ_TOTAL,">0") -> 0 | G26: =COUNTIFS(OZ_BLN,G$5,'OMZET HARIAN'!$U$5:$U$369,"<>OK",OZ_TOTAL,">0") -> 0 | H26: =COUNTIFS(OZ_BLN,H$5,'OMZET HARIAN'!$U$5:$U$369,"<>OK",OZ_TOTAL,">0") -> 3 | I26: =COUNTIFS(OZ_BLN,I$5,'OMZET HARIAN'!$U$5:$U$369,"<>OK",OZ_TOTAL,">0") -> 0 | J26: =COUNTIFS(OZ_BLN,J$5,'OMZET HARIAN'!$U$5:$U$369,"<>OK",OZ_TOTAL,">0") -> 2 | ... N26: =COUNTIFS(OZ_BLN,N$5,'OMZET HARIAN'!$U$5:$U$369,"<>OK",OZ_TOTAL,">0") -> 0 | O26: =SUM(C26:N26) -> 12

Sheet OMZET HARIAN
A1: OMZET HARIAN
A2: Input harian dari kasir. Biru = isi manual, hitam = rumus. Realisasi tunai diisi saat setor H+1; kalau belum diisi, status "Belum direalisasi" dan selisih tidak dihitung dulu.
A4: Tanggal | B4: Bln | C4: Tunai (POS) | D4: EDC/QRIS (POS) | E4: Total Tercatat | F4: Real Tunai Shift 1 | G4: Real Tunai Shift 2 | H4: Real EDC (settle) | I4: Total Realisasi | J4: Selisih Tunai | K4: Selisih EDC | L4: Bon Karyawan | M4: Compliment | N4: Bill Owner | O4: Selisih Tunai Tak Terjelaskan | P4: Biaya Selisih | Q4: OMZET BERSIH | R4: Produk Terjual | S4: Jml Transaksi | T4: Rata-rata / Transaksi | U4: Status
A5: 46023 | B5: =MONTH(A5) -> 1 | C5: 629200 | D5: 2447700 | E5: =N(C5)+N(D5) -> 3076900 | F5: 125000 | G5: 385000 | H5: 2452908 | I5: =N(F5)+N(G5)+N(H5) -> 2962908 | J5: =IF(AND(F5="",G5=""),0,N(C5)-N(F5)-N(G5)) -> 119200 | K5: =IF(H5="",0,N(D5)-N(H5)) -> -5208 | L5: 0 | M5: 0 | N5: 119200 | O5: =IF(AND(F5="",G5=""),0,J5-N(L5)-N(M5)-N(N5)) -> 0 | P5: =K5+O5 -> -5208 | Q5: =E5-P5 -> 3082108 | R5: 121 | S5: 70 | T5: =IF(N(S5)=0,"",Q5/S5) -> 44030.114 | U5: =IF(E5=0,"",IF(AND(N(C5)>0,F5="",G5=""),"Belum direalisasi",IF(AND(N(D5)>0,H5=""),"EDC belum settle",IF(ABS(O5)>50000,"Cek selisih tunai","OK")))) -> OK
A6: 46024 | B6: =MONTH(A6) -> 1 | C6: 1148750 | D6: 3663100 | E6: =N(C6)+N(D6) -> 4811850 | F6: 205000 | G6: 921000 | H6: 3637458 | I6: =N(F6)+N(G6)+N(H6) -> 4763458 | J6: =IF(AND(F6="",G6=""),0,N(C6)-N(F6)-N(G6)) -> 22750 | K6: =IF(H6="",0,N(D6)-N(H6)) -> 25642 | L6: 22500 | M6: 0 | N6: 0 | O6: =IF(AND(F6="",G6=""),0,J6-N(L6)-N(M6)-N(N6)) -> 250 | P6: =K6+O6 -> 25892 | Q6: =E6-P6 -> 4785958 | R6: 189 | S6: 103 | T6: =IF(N(S6)=0,"",Q6/S6) -> 46465.612 | U6: =IF(E6=0,"",IF(AND(N(C6)>0,F6="",G6=""),"Belum direalisasi",IF(AND(N(D6)>0,H6=""),"EDC belum settle",IF(ABS(O6)>50000,"Cek selisih tunai","OK")))) -> OK
A7: 46025 | B7: =MONTH(A7) -> 1 | C7: 1730900 | D7: 2510900 | E7: =N(C7)+N(D7) -> 4241800 | F7: 666000 | G7: 973000 | H7: 2438708 | I7: =N(F7)+N(G7)+N(H7) -> 4077708 | J7: =IF(AND(F7="",G7=""),0,N(C7)-N(F7)-N(G7)) -> 91900 | K7: =IF(H7="",0,N(D7)-N(H7)) -> 72192 | L7: 0 | M7: 0 | N7: 91300 | O7: =IF(AND(F7="",G7=""),0,J7-N(L7)-N(M7)-N(N7)) -> 600 | P7: =K7+O7 -> 72792 | Q7: =E7-P7 -> 4169008 | R7: 171 | S7: 93 | T7: =IF(N(S7)=0,"",Q7/S7) -> 44828.043 | U7: =IF(E7=0,"",IF(AND(N(C7)>0,F7="",G7=""),"Belum direalisasi",IF(AND(N(D7)>0,H7=""),"EDC belum settle",IF(ABS(O7)>50000,"Cek selisih tunai","OK")))) -> OK
A8: 46026 | B8: =MONTH(A8) -> 1 | C8: 781200 | D8: 2342600 | E8: =N(C8)+N(D8) -> 3123800 | F8: 202000 | G8: 455000 | H8: 2354307 | I8: =N(F8)+N(G8)+N(H8) -> 3011307 | J8: =IF(AND(F8="",G8=""),0,N(C8)-N(F8)-N(G8)) -> 124200 | K8: =IF(H8="",0,N(D8)-N(H8)) -> -11707 | L8: 74700 | M8: 0 | N8: 49300 | O8: =IF(AND(F8="",G8=""),0,J8-N(L8)-N(M8)-N(N8)) -> 200 | P8: =K8+O8 -> -11507 | Q8: =E8-P8 -> 3135307 | R8: 125 | S8: 71 | T8: =IF(N(S8)=0,"",Q8/S8) -> 44159.254 | U8: =IF(E8=0,"",IF(AND(N(C8)>0,F8="",G8=""),"Belum direalisasi",IF(AND(N(D8)>0,H8=""),"EDC belum settle",IF(ABS(O8)>50000,"Cek selisih tunai","OK")))) -> OK
A9: 46027 | B9: =MONTH(A9) -> 1 | C9: 1104500 | D9: 1648100 | E9: =N(C9)+N(D9) -> 2752600 | F9: 390000 | G9: 715000 | H9: 1663293 | I9: =N(F9)+N(G9)+N(H9) -> 2768293 | J9: =IF(AND(F9="",G9=""),0,N(C9)-N(F9)-N(G9)) -> -500 | K9: =IF(H9="",0,N(D9)-N(H9)) -> -15193 | L9: 0 | M9: 0 | N9: 0 | O9: =IF(AND(F9="",G9=""),0,J9-N(L9)-N(M9)-N(N9)) -> -500 | P9: =K9+O9 -> -15693 | Q9: =E9-P9 -> 2768293 | R9: 106 | S9: 55 | T9: =IF(N(S9)=0,"",Q9/S9) -> 50332.6 | U9: =IF(E9=0,"",IF(AND(N(C9)>0,F9="",G9=""),"Belum direalisasi",IF(AND(N(D9)>0,H9=""),"EDC belum settle",IF(ABS(O9)>50000,"Cek selisih tunai","OK")))) -> OK
A10: 46028 | B10: =MONTH(A10) -> 1 | C10: 860700 | D10: 2325050 | E10: =N(C10)+N(D10) -> 3185750 | F10: 119000 | G10: 254000 | H10: 2120601 | I10: =N(F10)+N(G10)+N(H10) -> 2493601 | J10: =IF(AND(F10="",G10=""),0,N(C10)-N(F10)-N(G10)) -> 487700 | K10: =IF(H10="",0,N(D10)-N(H10)) -> 204449 | L10: 0 | M10: 350000 | N10: 137700 | O10: =IF(AND(F10="",G10=""),0,J10-N(L10)-N(M10)-N(N10)) -> 0 | P10: =K10+O10 -> 204449 | Q10: =E10-P10 -> 2981301 | R10: 125 | S10: 54 | T10: =IF(N(S10)=0,"",Q10/S10) -> 55209.278 | U10: =IF(E10=0,"",IF(AND(N(C10)>0,F10="",G10=""),"Belum direalisasi",IF(AND(N(D10)>0,H10=""),"EDC belum settle",IF(ABS(O10)>50000,"Cek selisih tunai","OK")))) -> OK
A11: 46029 | B11: =MONTH(A11) -> 1 | C11: 549000 | D11: 1839600 | E11: =N(C11)+N(D11) -> 2388600 | F11: 50000 | G11: 374000 | H11: 2010432 | I11: =N(F11)+N(G11)+N(H11) -> 2434432 | J11: =IF(AND(F11="",G11=""),0,N(C11)-N(F11)-N(G11)) -> 125000 | K11: =IF(H11="",0,N(D11)-N(H11)) -> -170832 | L11: 0 | M11: 125000 | N11: 0 | O11: =IF(AND(F11="",G11=""),0,J11-N(L11)-N(M11)-N(N11)) -> 0 | P11: =K11+O11 -> -170832 | Q11: =E11-P11 -> 2559432 | R11: 106 | S11: 51 | T11: =IF(N(S11)=0,"",Q11/S11) -> 50184.941 | U11: =IF(E11=0,"",IF(AND(N(C11)>0,F11="",G11=""),"Belum direalisasi",IF(AND(N(D11)>0,H11=""),"EDC belum settle",IF(ABS(O11)>50000,"Cek selisih tunai","OK")))) -> OK
A12: 46030 | B12: =MONTH(A12) -> 1 | C12: 484300 | D12: 1499200 | E12: =N(C12)+N(D12) -> 1983500 | F12: 25000 | G12: 210000 | H12: 1513530 | I12: =N(F12)+N(G12)+N(H12) -> 1748530 | J12: =IF(AND(F12="",G12=""),0,N(C12)-N(F12)-N(G12)) -> 249300 | K12: =IF(H12="",0,N(D12)-N(H12)) -> -14330 | L12: 0 | M12: 180000 | N12: 69300 | O12: =IF(AND(F12="",G12=""),0,J12-N(L12)-N(M12)-N(N12)) -> 0 | P12: =K12+O12 -> -14330 | Q12: =E12-P12 -> 1997830 | R12: 78 | S12: 50 | T12: =IF(N(S12)=0,"",Q12/S12) -> 39956.6 | U12: =IF(E12=0,"",IF(AND(N(C12)>0,F12="",G12=""),"Belum direalisasi",IF(AND(N(D12)>0,H12=""),"EDC belum settle",IF(ABS(O12)>50000,"Cek selisih tunai","OK")))) -> OK
A13: 46031 | B13: =MONTH(A13) -> 1 | C13: 745000 | D13: 2292500 | E13: =N(C13)+N(D13) -> 3037500 | F13: 50000 | G13: 700000 | H13: 2276452 | I13: =N(F13)+N(G13)+N(H13) -> 3026452 | J13: =IF(AND(F13="",G13=""),0,N(C13)-N(F13)-N(G13)) -> -5000 | K13: =IF(H13="",0,N(D13)-N(H13)) -> 16048 | L13: 0 | M13: 0 | N13: 0 | O13: =IF(AND(F13="",G13=""),0,J13-N(L13)-N(M13)-N(N13)) -> -5000 | P13: =K13+O13 -> 11048 | Q13: =E13-P13 -> 3026452 | R13: 126 | S13: 64 | T13: =IF(N(S13)=0,"",Q13/S13) -> 47288.312 | U13: =IF(E13=0,"",IF(AND(N(C13)>0,F13="",G13=""),"Belum direalisasi",IF(AND(N(D13)>0,H13=""),"EDC belum settle",IF(ABS(O13)>50000,"Cek selisih tunai","OK")))) -> OK
A14: 46032 | B14: =MONTH(A14) -> 1 | C14: 1519000 | D14: 3166500 | E14: =N(C14)+N(D14) -> 4685500 | F14: 377000 | G14: 1137000 | H14: 3166677 | I14: =N(F14)+N(G14)+N(H14) -> 4680677 | J14: =IF(AND(F14="",G14=""),0,N(C14)-N(F14)-N(G14)) -> 5000 | K14: =IF(H14="",0,N(D14)-N(H14)) -> -177 | L14: 0 | M14: 0 | N14: 0 | O14: =IF(AND(F14="",G14=""),0,J14-N(L14)-N(M14)-N(N14)) -> 5000 | P14: =K14+O14 -> 4823 | Q14: =E14-P14 -> 4680677 | R14: 184 | S14: 94 | T14: =IF(N(S14)=0,"",Q14/S14) -> 49794.436 | U14: =IF(E14=0,"",IF(AND(N(C14)>0,F14="",G14=""),"Belum direalisasi",IF(AND(N(D14)>0,H14=""),"EDC belum settle",IF(ABS(O14)>50000,"Cek selisih tunai","OK")))) -> OK
A15: 46033 | B15: =MONTH(A15) -> 1 | C15: 1125500 | D15: 2846650 | E15: =N(C15)+N(D15) -> 3972150 | F15: 293000 | G15: 832000 | H15: 2775087 | I15: =N(F15)+N(G15)+N(H15) -> 3900087 | J15: =IF(AND(F15="",G15=""),0,N(C15)-N(F15)-N(G15)) -> 500 | K15: =IF(H15="",0,N(D15)-N(H15)) -> 71563 | L15: 0 | M15: 0 | N15: 0 | O15: =IF(AND(F15="",G15=""),0,J15-N(L15)-N(M15)-N(N15)) -> 500 | P15: =K15+O15 -> 72063 | Q15: =E15-P15 -> 3900087 | R15: 135 | S15: 80 | T15: =IF(N(S15)=0,"",Q15/S15) -> 48751.088 | U15: =IF(E15=0,"",IF(AND(N(C15)>0,F15="",G15=""),"Belum direalisasi",IF(AND(N(D15)>0,H15=""),"EDC belum settle",IF(ABS(O15)>50000,"Cek selisih tunai","OK")))) -> OK
A16: 46034 | B16: =MONTH(A16) -> 1 | C16: 700250 | D16: 2207900 | E16: =N(C16)+N(D16) -> 2908150 | F16: 88000 | G16: 612000 | H16: 2244366 | I16: =N(F16)+N(G16)+N(H16) -> 2944366 | J16: =IF(AND(F16="",G16=""),0,N(C16)-N(F16)-N(G16)) -> 250 | K16: =IF(H16="",0,N(D16)-N(H16)) -> -36466 | L16: 0 | M16: 0 | N16: 0 | O16: =IF(AND(F16="",G16=""),0,J16-N(L16)-N(M16)-N(N16)) -> 250 | P16: =K16+O16 -> -36216 | Q16: =E16-P16 -> 2944366 | R16: 114 | S16: 59 | T16: =IF(N(S16)=0,"",Q16/S16) -> 49904.508 | U16: =IF(E16=0,"",IF(AND(N(C16)>0,F16="",G16=""),"Belum direalisasi",IF(AND(N(D16)>0,H16=""),"EDC belum settle",IF(ABS(O16)>50000,"Cek selisih tunai","OK")))) -> OK
... A94: 46112 | B94: =MONTH(A94) -> 3 | C94: 728500 | D94: 1811400 | E94: =N(C94)+N(D94) -> 2539900 | F94: 230000 | G94: 499000 | H94: 1913205 | I94: =N(F94)+N(G94)+N(H94) -> 2642205 | J94: =IF(AND(F94="",G94=""),0,N(C94)-N(F94)-N(G94)) -> -500 | K94: =IF(H94="",0,N(D94)-N(H94)) -> -101805 | L94: 0 | M94: 0 | N94: 0 | O94: =IF(AND(F94="",G94=""),0,J94-N(L94)-N(M94)-N(N94)) -> -500 | P94: =K94+O94 -> -102305 | Q94: =E94-P94 -> 2642205 | R94: 95 | S94: 57 | T94: =IF(N(S94)=0,"",Q94/S94) -> 46354.474 | U94: =IF(E94=0,"",IF(AND(N(C94)>0,F94="",G94=""),"Belum direalisasi",IF(AND(N(D94)>0,H94=""),"EDC belum settle",IF(ABS(O94)>50000,"Cek selisih tunai","OK")))) -> OK
A95: 46113 | B95: =MONTH(A95) -> 4 | C95: 2190500 | D95: 2633700 | E95: =N(C95)+N(D95) -> 4824200 | F95: 670000 | G95: 1070000 | H95: 2633700 | I95: =N(F95)+N(G95)+N(H95) -> 4373700 | J95: =IF(AND(F95="",G95=""),0,N(C95)-N(F95)-N(G95)) -> 450500 | K95: =IF(H95="",0,N(D95)-N(H95)) -> 0 | M95: 427500 | O95: =IF(AND(F95="",G95=""),0,J95-N(L95)-N(M95)-N(N95)) -> 23000 | P95: =K95+O95 -> 23000 | Q95: =E95-P95 -> 4801200 | R95: 194 | S95: 88 | T95: =IF(N(S95)=0,"",Q95/S95) -> 54559.091 | U95: =IF(E95=0,"",IF(AND(N(C95)>0,F95="",G95=""),"Belum direalisasi",IF(AND(N(D95)>0,H95=""),"EDC belum settle",IF(ABS(O95)>50000,"Cek selisih tunai","OK")))) -> OK
A96: 46114 | B96: =MONTH(A96) -> 4 | C96: 1033000 | D96: 2253000 | E96: =N(C96)+N(D96) -> 3286000 | F96: 235000 | G96: 752000 | H96: 2252037 | I96: =N(F96)+N(G96)+N(H96) -> 3239037 | J96: =IF(AND(F96="",G96=""),0,N(C96)-N(F96)-N(G96)) -> 46000 | K96: =IF(H96="",0,N(D96)-N(H96)) -> 963 | N96: 45000 | O96: =IF(AND(F96="",G96=""),0,J96-N(L96)-N(M96)-N(N96)) -> 1000 | P96: =K96+O96 -> 1963 | Q96: =E96-P96 -> 3284037 | R96: 136 | S96: 75 | T96: =IF(N(S96)=0,"",Q96/S96) -> 43787.16 | U96: =IF(E96=0,"",IF(AND(N(C96)>0,F96="",G96=""),"Belum direalisasi",IF(AND(N(D96)>0,H96=""),"EDC belum settle",IF(ABS(O96)>50000,"Cek selisih tunai","OK")))) -> OK
A97: 46115 | B97: =MONTH(A97) -> 4 | C97: 1590600 | D97: 4565200 | E97: =N(C97)+N(D97) -> 6155800 | F97: 365000 | G97: 1082000 | H97: 4565200 | I97: =N(F97)+N(G97)+N(H97) -> 6012200 | J97: =IF(AND(F97="",G97=""),0,N(C97)-N(F97)-N(G97)) -> 143600 | K97: =IF(H97="",0,N(D97)-N(H97)) -> 0 | L97: 22500 | M97: 121500 | O97: =IF(AND(F97="",G97=""),0,J97-N(L97)-N(M97)-N(N97)) -> -400 | P97: =K97+O97 -> -400 | Q97: =E97-P97 -> 6156200 | R97: 232 | S97: 109 | T97: =IF(N(S97)=0,"",Q97/S97) -> 56478.899 | U97: =IF(E97=0,"",IF(AND(N(C97)>0,F97="",G97=""),"Belum direalisasi",IF(AND(N(D97)>0,H97=""),"EDC belum settle",IF(ABS(O97)>50000,"Cek selisih tunai","OK")))) -> OK
A98: 46116 | B98: =MONTH(A98) -> 4 | C98: 1224000 | D98: 3041450 | E98: =N(C98)+N(D98) -> 4265450 | F98: 207000 | G98: 992000 | H98: 3040950 | I98: =N(F98)+N(G98)+N(H98) -> 4239950 | J98: =IF(AND(F98="",G98=""),0,N(C98)-N(F98)-N(G98)) -> 25000 | K98: =IF(H98="",0,N(D98)-N(H98)) -> 500 | L98: 27000 | O98: =IF(AND(F98="",G98=""),0,J98-N(L98)-N(M98)-N(N98)) -> -2000 | P98: =K98+O98 -> -1500 | Q98: =E98-P98 -> 4266950 | R98: 163 | S98: 79 | T98: =IF(N(S98)=0,"",Q98/S98) -> 54012.025 | U98: =IF(E98=0,"",IF(AND(N(C98)>0,F98="",G98=""),"Belum direalisasi",IF(AND(N(D98)>0,H98=""),"EDC belum settle",IF(ABS(O98)>50000,"Cek selisih tunai","OK")))) -> OK
A99: 46117 | B99: =MONTH(A99) -> 4 | C99: 1127400 | D99: 2474250 | E99: =N(C99)+N(D99) -> 3601650 | F99: 154000 | G99: 887000 | H99: 2474250 | I99: =N(F99)+N(G99)+N(H99) -> 3515250 | J99: =IF(AND(F99="",G99=""),0,N(C99)-N(F99)-N(G99)) -> 86400 | K99: =IF(H99="",0,N(D99)-N(H99)) -> 0 | N99: 86900 | O99: =IF(AND(F99="",G99=""),0,J99-N(L99)-N(M99)-N(N99)) -> -500 | P99: =K99+O99 -> -500 | Q99: =E99-P99 -> 3602150 | R99: 136 | S99: 86 | T99: =IF(N(S99)=0,"",Q99/S99) -> 41885.465 | U99: =IF(E99=0,"",IF(AND(N(C99)>0,F99="",G99=""),"Belum direalisasi",IF(AND(N(D99)>0,H99=""),"EDC belum settle",IF(ABS(O99)>50000,"Cek selisih tunai","OK")))) -> OK
A100: 46118 | B100: =MONTH(A100) -> 4 | C100: 1296800 | D100: 2363500 | E100: =N(C100)+N(D100) -> 3660300 | F100: 300000 | G100: 939000 | H100: 2363500 | I100: =N(F100)+N(G100)+N(H100) -> 3602500 | J100: =IF(AND(F100="",G100=""),0,N(C100)-N(F100)-N(G100)) -> 57800 | K100: =IF(H100="",0,N(D100)-N(H100)) -> 0 | M100: 57500 | O100: =IF(AND(F100="",G100=""),0,J100-N(L100)-N(M100)-N(N100)) -> 300 | P100: =K100+O100 -> 300 | Q100: =E100-P100 -> 3660000 | R100: 136 | S100: 78 | T100: =IF(N(S100)=0,"",Q100/S100) -> 46923.077 | U100: =IF(E100=0,"",IF(AND(N(C100)>0,F100="",G100=""),"Belum direalisasi",IF(AND(N(D100)>0,H100=""),"EDC belum settle",IF(ABS(O100)>50000,"Cek selisih tunai","OK")))) -> OK
A101: 46119 | B101: =MONTH(A101) -> 4 | C101: 462000 | D101: 1447100 | E101: =N(C101)+N(D101) -> 1909100 | F101: 197000 | G101: 265000 | H101: 1447100 | I101: =N(F101)+N(G101)+N(H101) -> 1909100 | J101: =IF(AND(F101="",G101=""),0,N(C101)-N(F101)-N(G101)) -> 0 | K101: =IF(H101="",0,N(D101)-N(H101)) -> 0 | O101: =IF(AND(F101="",G101=""),0,J101-N(L101)-N(M101)-N(N101)) -> 0 | P101: =K101+O101 -> 0 | Q101: =E101-P101 -> 1909100 | R101: 71 | S101: 42 | T101: =IF(N(S101)=0,"",Q101/S101) -> 45454.762 | U101: =IF(E101=0,"",IF(AND(N(C101)>0,F101="",G101=""),"Belum direalisasi",IF(AND(N(D101)>0,H101=""),"EDC belum settle",IF(ABS(O101)>50000,"Cek selisih tunai","OK")))) -> OK
A102: 46120 | B102: =MONTH(A102) -> 4 | C102: 837000 | D102: 1831100 | E102: =N(C102)+N(D102) -> 2668100 | F102: 248000 | G102: 589000 | H102: 1831100 | I102: =N(F102)+N(G102)+N(H102) -> 2668100 | J102: =IF(AND(F102="",G102=""),0,N(C102)-N(F102)-N(G102)) -> 0 | K102: =IF(H102="",0,N(D102)-N(H102)) -> 0 | O102: =IF(AND(F102="",G102=""),0,J102-N(L102)-N(M102)-N(N102)) -> 0 | P102: =K102+O102 -> 0 | Q102: =E102-P102 -> 2668100 | R102: 103 | S102: 64 | T102: =IF(N(S102)=0,"",Q102/S102) -> 41689.062 | U102: =IF(E102=0,"",IF(AND(N(C102)>0,F102="",G102=""),"Belum direalisasi",IF(AND(N(D102)>0,H102=""),"EDC belum settle",IF(ABS(O102)>50000,"Cek selisih tunai","OK")))) -> OK
A103: 46121 | B103: =MONTH(A103) -> 4 | C103: 936000 | D103: 2674900 | E103: =N(C103)+N(D103) -> 3610900 | F103: 213000 | G103: 723000 | H103: 2673774 | I103: =N(F103)+N(G103)+N(H103) -> 3609774 | J103: =IF(AND(F103="",G103=""),0,N(C103)-N(F103)-N(G103)) -> 0 | K103: =IF(H103="",0,N(D103)-N(H103)) -> 1126 | O103: =IF(AND(F103="",G103=""),0,J103-N(L103)-N(M103)-N(N103)) -> 0 | P103: =K103+O103 -> 1126 | Q103: =E103-P103 -> 3609774 | R103: 144 | S103: 77 | T103: =IF(N(S103)=0,"",Q103/S103) -> 46880.182 | U103: =IF(E103=0,"",IF(AND(N(C103)>0,F103="",G103=""),"Belum direalisasi",IF(AND(N(D103)>0,H103=""),"EDC belum settle",IF(ABS(O103)>50000,"Cek selisih tunai","OK")))) -> OK
A104: 46122 | B104: =MONTH(A104) -> 4 | C104: 964000 | D104: 2139650 | E104: =N(C104)+N(D104) -> 3103650 | F104: 273000 | G104: 691000 | H104: 2139650 | I104: =N(F104)+N(G104)+N(H104) -> 3103650 | J104: =IF(AND(F104="",G104=""),0,N(C104)-N(F104)-N(G104)) -> 0 | K104: =IF(H104="",0,N(D104)-N(H104)) -> 0 | O104: =IF(AND(F104="",G104=""),0,J104-N(L104)-N(M104)-N(N104)) -> 0 | P104: =K104+O104 -> 0 | Q104: =E104-P104 -> 3103650 | R104: 124 | S104: 60 | T104: =IF(N(S104)=0,"",Q104/S104) -> 51727.5 | U104: =IF(E104=0,"",IF(AND(N(C104)>0,F104="",G104=""),"Belum direalisasi",IF(AND(N(D104)>0,H104=""),"EDC belum settle",IF(ABS(O104)>50000,"Cek selisih tunai","OK")))) -> OK
A105: 46123 | B105: =MONTH(A105) -> 4 | C105: 1297500 | D105: 2673900 | E105: =N(C105)+N(D105) -> 3971400 | F105: 351000 | G105: 901500 | H105: 2673322 | I105: =N(F105)+N(G105)+N(H105) -> 3925822 | J105: =IF(AND(F105="",G105=""),0,N(C105)-N(F105)-N(G105)) -> 45000 | K105: =IF(H105="",0,N(D105)-N(H105)) -> 578 | L105: 22500 | N105: 22500 | O105: =IF(AND(F105="",G105=""),0,J105-N(L105)-N(M105)-N(N105)) -> 0 | P105: =K105+O105 -> 578 | Q105: =E105-P105 -> 3970822 | R105: 152 | S105: 87 | T105: =IF(N(S105)=0,"",Q105/S105) -> 45641.632 | U105: =IF(E105=0,"",IF(AND(N(C105)>0,F105="",G105=""),"Belum direalisasi",IF(AND(N(D105)>0,H105=""),"EDC belum settle",IF(ABS(O105)>50000,"Cek selisih tunai","OK")))) -> OK
A106: 46124 | B106: =MONTH(A106) -> 4 | C106: 622500 | D106: 1896500 | E106: =N(C106)+N(D106) -> 2519000 | F106: 575000 | G106: 25000 | H106: 1896500 | I106: =N(F106)+N(G106)+N(H106) -> 2496500 | J106: =IF(AND(F106="",G106=""),0,N(C106)-N(F106)-N(G106)) -> 22500 | K106: =IF(H106="",0,N(D106)-N(H106)) -> 0 | L106: 22500 | O106: =IF(AND(F106="",G106=""),0,J106-N(L106)-N(M106)-N(N106)) -> 0 | P106: =K106+O106 -> 0 | Q106: =E106-P106 -> 2519000 | R106: 95 | S106: 44 | T106: =IF(N(S106)=0,"",Q106/S106) -> 57250 | U106: =IF(E106=0,"",IF(AND(N(C106)>0,F106="",G106=""),"Belum direalisasi",IF(AND(N(D106)>0,H106=""),"EDC belum settle",IF(ABS(O106)>50000,"Cek selisih tunai","OK")))) -> OK
A107: 46125 | B107: =MONTH(A107) -> 4 | C107: 575300 | D107: 1748900 | E107: =N(C107)+N(D107) -> 2324200 | F107: 33000 | G107: 543000 | H107: 1748900 | I107: =N(F107)+N(G107)+N(H107) -> 2324900 | J107: =IF(AND(F107="",G107=""),0,N(C107)-N(F107)-N(G107)) -> -700 | K107: =IF(H107="",0,N(D107)-N(H107)) -> 0 | O107: =IF(AND(F107="",G107=""),0,J107-N(L107)-N(M107)-N(N107)) -> -700 | P107: =K107+O107 -> -700 | Q107: =E107-P107 -> 2324900 | R107: 87 | S107: 53 | T107: =IF(N(S107)=0,"",Q107/S107) -> 43866.038 | U107: =IF(E107=0,"",IF(AND(N(C107)>0,F107="",G107=""),"Belum direalisasi",IF(AND(N(D107)>0,H107=""),"EDC belum settle",IF(ABS(O107)>50000,"Cek selisih tunai","OK")))) -> OK
A108: 46126 | B108: =MONTH(A108) -> 4 | C108: 571000 | D108: 1398200 | E108: =N(C108)+N(D108) -> 1969200 | F108: 251000 | G108: 320000 | H108: 1398200 | I108: =N(F108)+N(G108)+N(H108) -> 1969200 | J108: =IF(AND(F108="",G108=""),0,N(C108)-N(F108)-N(G108)) -> 0 | K108: =IF(H108="",0,N(D108)-N(H108)) -> 0 | O108: =IF(AND(F108="",G108=""),0,J108-N(L108)-N(M108)-N(N108)) -> 0 | P108: =K108+O108 -> 0 | Q108: =E108-P108 -> 1969200 | R108: 74 | S108: 46 | T108: =IF(N(S108)=0,"",Q108/S108) -> 42808.696 | U108: =IF(E108=0,"",IF(AND(N(C108)>0,F108="",G108=""),"Belum direalisasi",IF(AND(N(D108)>0,H108=""),"EDC belum settle",IF(ABS(O108)>50000,"Cek selisih tunai","OK")))) -> OK
A109: 46127 | B109: =MONTH(A109) -> 4 | C109: 941000 | D109: 1663000 | E109: =N(C109)+N(D109) -> 2604000 | F109: 418000 | G109: 522000 | H109: 1663000 | I109: =N(F109)+N(G109)+N(H109) -> 2603000 | J109: =IF(AND(F109="",G109=""),0,N(C109)-N(F109)-N(G109)) -> 1000 | K109: =IF(H109="",0,N(D109)-N(H109)) -> 0 | O109: =IF(AND(F109="",G109=""),0,J109-N(L109)-N(M109)-N(N109)) -> 1000 | P109: =K109+O109 -> 1000 | Q109: =E109-P109 -> 2603000 | R109: 98 | S109: 60 | T109: =IF(N(S109)=0,"",Q109/S109) -> 43383.333 | U109: =IF(E109=0,"",IF(AND(N(C109)>0,F109="",G109=""),"Belum direalisasi",IF(AND(N(D109)>0,H109=""),"EDC belum settle",IF(ABS(O109)>50000,"Cek selisih tunai","OK")))) -> OK
A110: 46128 | B110: =MONTH(A110) -> 4 | C110: 1157000 | D110: 2008200 | E110: =N(C110)+N(D110) -> 3165200 | F110: 262000 | G110: 895000 | H110: 2008200 | I110: =N(F110)+N(G110)+N(H110) -> 3165200 | J110: =IF(AND(F110="",G110=""),0,N(C110)-N(F110)-N(G110)) -> 0 | K110: =IF(H110="",0,N(D110)-N(H110)) -> 0 | O110: =IF(AND(F110="",G110=""),0,J110-N(L110)-N(M110)-N(N110)) -> 0 | P110: =K110+O110 -> 0 | Q110: =E110-P110 -> 3165200 | R110: 125 | S110: 61 | T110: =IF(N(S110)=0,"",Q110/S110) -> 51888.525 | U110: =IF(E110=0,"",IF(AND(N(C110)>0,F110="",G110=""),"Belum direalisasi",IF(AND(N(D110)>0,H110=""),"EDC belum settle",IF(ABS(O110)>50000,"Cek selisih tunai","OK")))) -> OK
A111: 46129 | B111: =MONTH(A111) -> 4 | C111: 762000 | D111: 3035650 | E111: =N(C111)+N(D111) -> 3797650 | F111: 80000 | G111: 682000 | H111: 3035650 | I111: =N(F111)+N(G111)+N(H111) -> 3797650 | J111: =IF(AND(F111="",G111=""),0,N(C111)-N(F111)-N(G111)) -> 0 | K111: =IF(H111="",0,N(D111)-N(H111)) -> 0 | O111: =IF(AND(F111="",G111=""),0,J111-N(L111)-N(M111)-N(N111)) -> 0 | P111: =K111+O111 -> 0 | Q111: =E111-P111 -> 3797650 | R111: 151 | S111: 88 | T111: =IF(N(S111)=0,"",Q111/S111) -> 43155.114 | U111: =IF(E111=0,"",IF(AND(N(C111)>0,F111="",G111=""),"Belum direalisasi",IF(AND(N(D111)>0,H111=""),"EDC belum settle",IF(ABS(O111)>50000,"Cek selisih tunai","OK")))) -> OK
A112: 46130 | B112: =MONTH(A112) -> 4 | C112: 1717500 | D112: 3946200 | E112: =N(C112)+N(D112) -> 5663700 | F112: 440000 | G112: 982000 | H112: 3946087 | I112: =N(F112)+N(G112)+N(H112) -> 5368087 | J112: =IF(AND(F112="",G112=""),0,N(C112)-N(F112)-N(G112)) -> 295500 | K112: =IF(H112="",0,N(D112)-N(H112)) -> 113 | L112: 85800 | M112: 87000 | N112: 122700 | O112: =IF(AND(F112="",G112=""),0,J112-N(L112)-N(M112)-N(N112)) -> 0 | P112: =K112+O112 -> 113 | Q112: =E112-P112 -> 5663587 | R112: 218 | S112: 116 | T112: =IF(N(S112)=0,"",Q112/S112) -> 48824.026 | U112: =IF(E112=0,"",IF(AND(N(C112)>0,F112="",G112=""),"Belum direalisasi",IF(AND(N(D112)>0,H112=""),"EDC belum settle",IF(ABS(O112)>50000,"Cek selisih tunai","OK")))) -> OK
A113: 46131 | B113: =MONTH(A113) -> 4 | C113: 1250500 | D113: 2588800 | E113: =N(C113)+N(D113) -> 3839300 | F113: 544000 | G113: 707000 | H113: 2588668 | I113: =N(F113)+N(G113)+N(H113) -> 3839668 | J113: =IF(AND(F113="",G113=""),0,N(C113)-N(F113)-N(G113)) -> -500 | K113: =IF(H113="",0,N(D113)-N(H113)) -> 132 | O113: =IF(AND(F113="",G113=""),0,J113-N(L113)-N(M113)-N(N113)) -> -500 | P113: =K113+O113 -> -368 | Q113: =E113-P113 -> 3839668 | R113: 148 | S113: 73 | T113: =IF(N(S113)=0,"",Q113/S113) -> 52598.192 | U113: =IF(E113=0,"",IF(AND(N(C113)>0,F113="",G113=""),"Belum direalisasi",IF(AND(N(D113)>0,H113=""),"EDC belum settle",IF(ABS(O113)>50000,"Cek selisih tunai","OK")))) -> OK
A114: 46132 | B114: =MONTH(A114) -> 4 | C114: 569000 | D114: 1257950 | E114: =N(C114)+N(D114) -> 1826950 | F114: 50000 | G114: 494000 | H114: 1257950 | I114: =N(F114)+N(G114)+N(H114) -> 1801950 | J114: =IF(AND(F114="",G114=""),0,N(C114)-N(F114)-N(G114)) -> 25000 | K114: =IF(H114="",0,N(D114)-N(H114)) -> 0 | O114: =IF(AND(F114="",G114=""),0,J114-N(L114)-N(M114)-N(N114)) -> 25000 | P114: =K114+O114 -> 25000 | Q114: =E114-P114 -> 1801950 | R114: 71 | S114: 40 | T114: =IF(N(S114)=0,"",Q114/S114) -> 45048.75 | U114: =IF(E114=0,"",IF(AND(N(C114)>0,F114="",G114=""),"Belum direalisasi",IF(AND(N(D114)>0,H114=""),"EDC belum settle",IF(ABS(O114)>50000,"Cek selisih tunai","OK")))) -> OK
A115: 46133 | B115: =MONTH(A115) -> 4 | C115: 659300 | D115: 1350650 | E115: =N(C115)+N(D115) -> 2009950 | F115: 72500 | G115: 430000 | H115: 1350618 | I115: =N(F115)+N(G115)+N(H115) -> 1853118 | J115: =IF(AND(F115="",G115=""),0,N(C115)-N(F115)-N(G115)) -> 156800 | K115: =IF(H115="",0,N(D115)-N(H115)) -> 32 | L115: 22500 | M115: 90000 | N115: 45000 | O115: =IF(AND(F115="",G115=""),0,J115-N(L115)-N(M115)-N(N115)) -> -700 | P115: =K115+O115 -> -668 | Q115: =E115-P115 -> 2010618 | R115: 81 | S115: 44 | T115: =IF(N(S115)=0,"",Q115/S115) -> 45695.864 | U115: =IF(E115=0,"",IF(AND(N(C115)>0,F115="",G115=""),"Belum direalisasi",IF(AND(N(D115)>0,H115=""),"EDC belum settle",IF(ABS(O115)>50000,"Cek selisih tunai","OK")))) -> OK
A116: 46134 | B116: =MONTH(A116) -> 4 | C116: 869200 | D116: 1602300 | E116: =N(C116)+N(D116) -> 2471500 | F116: 85000 | G116: 530000 | H116: 1601991 | I116: =N(F116)+N(G116)+N(H116) -> 2216991 | J116: =IF(AND(F116="",G116=""),0,N(C116)-N(F116)-N(G116)) -> 254200 | K116: =IF(H116="",0,N(D116)-N(H116)) -> 309 | M116: 155000 | N116: 98200 | O116: =IF(AND(F116="",G116=""),0,J116-N(L116)-N(M116)-N(N116)) -> 1000 | P116: =K116+O116 -> 1309 | Q116: =E116-P116 -> 2470191 | R116: 93 | S116: 46 | T116: =IF(N(S116)=0,"",Q116/S116) -> 53699.804 | U116: =IF(E116=0,"",IF(AND(N(C116)>0,F116="",G116=""),"Belum direalisasi",IF(AND(N(D116)>0,H116=""),"EDC belum settle",IF(ABS(O116)>50000,"Cek selisih tunai","OK")))) -> OK
A117: 46135 | B117: =MONTH(A117) -> 4 | C117: 622750 | D117: 1713900 | E117: =N(C117)+N(D117) -> 2336650 | F117: 275000 | G117: 348000 | H117: 1718900 | I117: =N(F117)+N(G117)+N(H117) -> 2341900 | J117: =IF(AND(F117="",G117=""),0,N(C117)-N(F117)-N(G117)) -> -250 | K117: =IF(H117="",0,N(D117)-N(H117)) -> -5000 | O117: =IF(AND(F117="",G117=""),0,J117-N(L117)-N(M117)-N(N117)) -> -250 | P117: =K117+O117 -> -5250 | Q117: =E117-P117 -> 2341900 | R117: 91 | S117: 48 | T117: =IF(N(S117)=0,"",Q117/S117) -> 48789.583 | U117: =IF(E117=0,"",IF(AND(N(C117)>0,F117="",G117=""),"Belum direalisasi",IF(AND(N(D117)>0,H117=""),"EDC belum settle",IF(ABS(O117)>50000,"Cek selisih tunai","OK")))) -> OK
A118: 46136 | B118: =MONTH(A118) -> 4 | C118: 813500 | D118: 1523000 | E118: =N(C118)+N(D118) -> 2336500 | F118: 110000 | G118: 599000 | H118: 1550410 | I118: =N(F118)+N(G118)+N(H118) -> 2259410 | J118: =IF(AND(F118="",G118=""),0,N(C118)-N(F118)-N(G118)) -> 104500 | K118: =IF(H118="",0,N(D118)-N(H118)) -> -27410 | L118: 49500 | M118: 25000 | N118: 30000 | O118: =IF(AND(F118="",G118=""),0,J118-N(L118)-N(M118)-N(N118)) -> 0 | P118: =K118+O118 -> -27410 | Q118: =E118-P118 -> 2363910 | R118: 91 | S118: 50 | T118: =IF(N(S118)=0,"",Q118/S118) -> 47278.2 | U118: =IF(E118=0,"",IF(AND(N(C118)>0,F118="",G118=""),"Belum direalisasi",IF(AND(N(D118)>0,H118=""),"EDC belum settle",IF(ABS(O118)>50000,"Cek selisih tunai","OK")))) -> OK
A119: 46137 | B119: =MONTH(A119) -> 4 | C119: 1873800 | D119: 2568700 | E119: =N(C119)+N(D119) -> 4442500 | F119: 400000 | G119: 1361000 | H119: 2568662 | I119: =N(F119)+N(G119)+N(H119) -> 4329662 | J119: =IF(AND(F119="",G119=""),0,N(C119)-N(F119)-N(G119)) -> 112800 | K119: =IF(H119="",0,N(D119)-N(H119)) -> 38 | N119: 113200 | O119: =IF(AND(F119="",G119=""),0,J119-N(L119)-N(M119)-N(N119)) -> -400 | P119: =K119+O119 -> -362 | Q119: =E119-P119 -> 4442862 | R119: 170 | S119: 92 | T119: =IF(N(S119)=0,"",Q119/S119) -> 48291.978 | U119: =IF(E119=0,"",IF(AND(N(C119)>0,F119="",G119=""),"Belum direalisasi",IF(AND(N(D119)>0,H119=""),"EDC belum settle",IF(ABS(O119)>50000,"Cek selisih tunai","OK")))) -> OK
A120: 46138 | B120: =MONTH(A120) -> 4 | C120: 838700 | D120: 2306200 | E120: =N(C120)+N(D120) -> 3144900 | F120: 329000 | G120: 510000 | H120: 2177200 | I120: =N(F120)+N(G120)+N(H120) -> 3016200 | J120: =IF(AND(F120="",G120=""),0,N(C120)-N(F120)-N(G120)) -> -300 | K120: =IF(H120="",0,N(D120)-N(H120)) -> 129000 | O120: =IF(AND(F120="",G120=""),0,J120-N(L120)-N(M120)-N(N120)) -> -300 | P120: =K120+O120 -> 128700 | Q120: =E120-P120 -> 3016200 | R120: 120 | S120: 72 | T120: =IF(N(S120)=0,"",Q120/S120) -> 41891.667 | U120: =IF(E120=0,"",IF(AND(N(C120)>0,F120="",G120=""),"Belum direalisasi",IF(AND(N(D120)>0,H120=""),"EDC belum settle",IF(ABS(O120)>50000,"Cek selisih tunai","OK")))) -> OK
A121: 46139 | B121: =MONTH(A121) -> 4 | C121: 804000 | D121: 2379950 | E121: =N(C121)+N(D121) -> 3183950 | F121: 50000 | G121: 754000 | H121: 2321950 | I121: =N(F121)+N(G121)+N(H121) -> 3125950 | J121: =IF(AND(F121="",G121=""),0,N(C121)-N(F121)-N(G121)) -> 0 | K121: =IF(H121="",0,N(D121)-N(H121)) -> 58000 | O121: =IF(AND(F121="",G121=""),0,J121-N(L121)-N(M121)-N(N121)) -> 0 | P121: =K121+O121 -> 58000 | Q121: =E121-P121 -> 3125950 | R121: 126 | S121: 62 | T121: =IF(N(S121)=0,"",Q121/S121) -> 50418.548 | U121: =IF(E121=0,"",IF(AND(N(C121)>0,F121="",G121=""),"Belum direalisasi",IF(AND(N(D121)>0,H121=""),"EDC belum settle",IF(ABS(O121)>50000,"Cek selisih tunai","OK")))) -> OK
A122: 46140 | B122: =MONTH(A122) -> 4 | C122: 339600 | D122: 1665200 | E122: =N(C122)+N(D122) -> 2004800 | F122: 47000 | G122: 197000 | H122: 1851919 | I122: =N(F122)+N(G122)+N(H122) -> 2095919 | J122: =IF(AND(F122="",G122=""),0,N(C122)-N(F122)-N(G122)) -> 95600 | K122: =IF(H122="",0,N(D122)-N(H122)) -> -186719 | M122: 22500 | N122: 72900 | O122: =IF(AND(F122="",G122=""),0,J122-N(L122)-N(M122)-N(N122)) -> 200 | P122: =K122+O122 -> -186519 | Q122: =E122-P122 -> 2191319 | R122: 79 | S122: 48 | T122: =IF(N(S122)=0,"",Q122/S122) -> 45652.479 | U122: =IF(E122=0,"",IF(AND(N(C122)>0,F122="",G122=""),"Belum direalisasi",IF(AND(N(D122)>0,H122=""),"EDC belum settle",IF(ABS(O122)>50000,"Cek selisih tunai","OK")))) -> OK
A123: 46141 | B123: =MONTH(A123) -> 4 | C123: 834200 | D123: 1394000 | E123: =N(C123)+N(D123) -> 2228200 | F123: 157000 | G123: 543000 | H123: 1394000 | I123: =N(F123)+N(G123)+N(H123) -> 2094000 | J123: =IF(AND(F123="",G123=""),0,N(C123)-N(F123)-N(G123)) -> 134200 | K123: =IF(H123="",0,N(D123)-N(H123)) -> 0 | N123: 134700 | O123: =IF(AND(F123="",G123=""),0,J123-N(L123)-N(M123)-N(N123)) -> -500 | P123: =K123+O123 -> -500 | Q123: =E123-P123 -> 2228700 | R123: 86 | S123: 46 | T123: =IF(N(S123)=0,"",Q123/S123) -> 48450 | U123: =IF(E123=0,"",IF(AND(N(C123)>0,F123="",G123=""),"Belum direalisasi",IF(AND(N(D123)>0,H123=""),"EDC belum settle",IF(ABS(O123)>50000,"Cek selisih tunai","OK")))) -> OK
A124: 46142 | B124: =MONTH(A124) -> 4 | C124: 466000 | D124: 1178100 | E124: =N(C124)+N(D124) -> 1644100 | F124: 100000 | G124: 366000 | H124: 1178100 | I124: =N(F124)+N(G124)+N(H124) -> 1644100 | J124: =IF(AND(F124="",G124=""),0,N(C124)-N(F124)-N(G124)) -> 0 | K124: =IF(H124="",0,N(D124)-N(H124)) -> 0 | O124: =IF(AND(F124="",G124=""),0,J124-N(L124)-N(M124)-N(N124)) -> 0 | P124: =K124+O124 -> 0 | Q124: =E124-P124 -> 1644100 | R124: 61 | S124: 34 | T124: =IF(N(S124)=0,"",Q124/S124) -> 48355.882 | U124: =IF(E124=0,"",IF(AND(N(C124)>0,F124="",G124=""),"Belum direalisasi",IF(AND(N(D124)>0,H124=""),"EDC belum settle",IF(ABS(O124)>50000,"Cek selisih tunai","OK")))) -> OK
A125: 46143 | B125: =MONTH(A125) -> 5 | C125: 1649250 | D125: 3324900 | E125: =N(C125)+N(D125) -> 4974150 | F125: 595000 | G125: 906000 | H125: 3324901 | I125: =N(F125)+N(G125)+N(H125) -> 4825901 | J125: =IF(AND(F125="",G125=""),0,N(C125)-N(F125)-N(G125)) -> 148250 | K125: =IF(H125="",0,N(D125)-N(H125)) -> -1 | L125: 126000 | M125: 22500 | O125: =IF(AND(F125="",G125=""),0,J125-N(L125)-N(M125)-N(N125)) -> -250 | P125: =K125+O125 -> -251 | Q125: =E125-P125 -> 4974401 | R125: 195 | S125: 104 | T125: =IF(N(S125)=0,"",Q125/S125) -> 47830.779 | U125: =IF(E125=0,"",IF(AND(N(C125)>0,F125="",G125=""),"Belum direalisasi",IF(AND(N(D125)>0,H125=""),"EDC belum settle",IF(ABS(O125)>50000,"Cek selisih tunai","OK")))) -> OK
A126: 46144 | B126: =MONTH(A126) -> 5 | C126: 1929700 | D126: 4069350 | E126: =N(C126)+N(D126) -> 5999050 | F126: 792000 | G126: 994000 | H126: 4069250 | I126: =N(F126)+N(G126)+N(H126) -> 5855250 | J126: =IF(AND(F126="",G126=""),0,N(C126)-N(F126)-N(G126)) -> 143700 | K126: =IF(H126="",0,N(D126)-N(H126)) -> 100 | M126: 51000 | N126: 95400 | O126: =IF(AND(F126="",G126=""),0,J126-N(L126)-N(M126)-N(N126)) -> -2700 | P126: =K126+O126 -> -2600 | Q126: =E126-P126 -> 6001650 | R126: 248 | S126: 133 | T126: =IF(N(S126)=0,"",Q126/S126) -> 45125.188 | U126: =IF(E126=0,"",IF(AND(N(C126)>0,F126="",G126=""),"Belum direalisasi",IF(AND(N(D126)>0,H126=""),"EDC belum settle",IF(ABS(O126)>50000,"Cek selisih tunai","OK")))) -> OK
A127: 46145 | B127: =MONTH(A127) -> 5 | C127: 1952550 | D127: 4792850 | E127: =N(C127)+N(D127) -> 6745400 | F127: 855000 | G127: 983000 | H127: 4817600 | I127: =N(F127)+N(G127)+N(H127) -> 6655600 | J127: =IF(AND(F127="",G127=""),0,N(C127)-N(F127)-N(G127)) -> 114550 | K127: =IF(H127="",0,N(D127)-N(H127)) -> -24750 | N127: 114300 | O127: =IF(AND(F127="",G127=""),0,J127-N(L127)-N(M127)-N(N127)) -> 250 | P127: =K127+O127 -> -24500 | Q127: =E127-P127 -> 6769900 | R127: 265 | S127: 142 | T127: =IF(N(S127)=0,"",Q127/S127) -> 47675.352 | U127: =IF(E127=0,"",IF(AND(N(C127)>0,F127="",G127=""),"Belum direalisasi",IF(AND(N(D127)>0,H127=""),"EDC belum settle",IF(ABS(O127)>50000,"Cek selisih tunai","OK")))) -> OK
A128: 46146 | B128: =MONTH(A128) -> 5 | C128: 923500 | D128: 1898800 | E128: =N(C128)+N(D128) -> 2822300 | F128: 365000 | G128: 296100 | H128: 1898723 | I128: =N(F128)+N(G128)+N(H128) -> 2559823 | J128: =IF(AND(F128="",G128=""),0,N(C128)-N(F128)-N(G128)) -> 262400 | K128: =IF(H128="",0,N(D128)-N(H128)) -> 77 | L128: 31500 | N128: 231400 | O128: =IF(AND(F128="",G128=""),0,J128-N(L128)-N(M128)-N(N128)) -> -500 | P128: =K128+O128 -> -423 | Q128: =E128-P128 -> 2822723 | R128: 107 | S128: 56 | T128: =IF(N(S128)=0,"",Q128/S128) -> 50405.768 | U128: =IF(E128=0,"",IF(AND(N(C128)>0,F128="",G128=""),"Belum direalisasi",IF(AND(N(D128)>0,H128=""),"EDC belum settle",IF(ABS(O128)>50000,"Cek selisih tunai","OK")))) -> OK
A129: 46147 | B129: =MONTH(A129) -> 5 | C129: 1033000 | D129: 2113450 | E129: =N(C129)+N(D129) -> 3146450 | F129: 127000 | G129: 884000 | H129: 2110330 | I129: =N(F129)+N(G129)+N(H129) -> 3121330 | J129: =IF(AND(F129="",G129=""),0,N(C129)-N(F129)-N(G129)) -> 22000 | K129: =IF(H129="",0,N(D129)-N(H129)) -> 3120 | M129: 22500 | O129: =IF(AND(F129="",G129=""),0,J129-N(L129)-N(M129)-N(N129)) -> -500 | P129: =K129+O129 -> 2620 | Q129: =E129-P129 -> 3143830 | R129: 122 | S129: 79 | T129: =IF(N(S129)=0,"",Q129/S129) -> 39795.316 | U129: =IF(E129=0,"",IF(AND(N(C129)>0,F129="",G129=""),"Belum direalisasi",IF(AND(N(D129)>0,H129=""),"EDC belum settle",IF(ABS(O129)>50000,"Cek selisih tunai","OK")))) -> OK
A130: 46148 | B130: =MONTH(A130) -> 5 | C130: 572000 | D130: 2590750 | E130: =N(C130)+N(D130) -> 3162750 | F130: 269000 | G130: 303000 | H130: 2589532 | I130: =N(F130)+N(G130)+N(H130) -> 3161532 | J130: =IF(AND(F130="",G130=""),0,N(C130)-N(F130)-N(G130)) -> 0 | K130: =IF(H130="",0,N(D130)-N(H130)) -> 1218 | O130: =IF(AND(F130="",G130=""),0,J130-N(L130)-N(M130)-N(N130)) -> 0 | P130: =K130+O130 -> 1218 | Q130: =E130-P130 -> 3161532 | R130: 123 | S130: 67 | T130: =IF(N(S130)=0,"",Q130/S130) -> 47187.045 | U130: =IF(E130=0,"",IF(AND(N(C130)>0,F130="",G130=""),"Belum direalisasi",IF(AND(N(D130)>0,H130=""),"EDC belum settle",IF(ABS(O130)>50000,"Cek selisih tunai","OK")))) -> OK
A131: 46149 | B131: =MONTH(A131) -> 5 | C131: 737400 | D131: 814550 | E131: =N(C131)+N(D131) -> 1551950 | F131: 50000 | G131: 654000 | H131: 841550 | I131: =N(F131)+N(G131)+N(H131) -> 1545550 | J131: =IF(AND(F131="",G131=""),0,N(C131)-N(F131)-N(G131)) -> 33400 | K131: =IF(H131="",0,N(D131)-N(H131)) -> -27000 | L131: 33000 | O131: =IF(AND(F131="",G131=""),0,J131-N(L131)-N(M131)-N(N131)) -> 400 | P131: =K131+O131 -> -26600 | Q131: =E131-P131 -> 1578550 | R131: 68 | S131: 28 | T131: =IF(N(S131)=0,"",Q131/S131) -> 56376.786 | U131: =IF(E131=0,"",IF(AND(N(C131)>0,F131="",G131=""),"Belum direalisasi",IF(AND(N(D131)>0,H131=""),"EDC belum settle",IF(ABS(O131)>50000,"Cek selisih tunai","OK")))) -> OK
A132: 46150 | B132: =MONTH(A132) -> 5 | C132: 1348050 | D132: 2251250 | E132: =N(C132)+N(D132) -> 3599300 | F132: 226000 | G132: 1122000 | H132: 2251250 | I132: =N(F132)+N(G132)+N(H132) -> 3599250 | J132: =IF(AND(F132="",G132=""),0,N(C132)-N(F132)-N(G132)) -> 50 | K132: =IF(H132="",0,N(D132)-N(H132)) -> 0 | O132: =IF(AND(F132="",G132=""),0,J132-N(L132)-N(M132)-N(N132)) -> 50 | P132: =K132+O132 -> 50 | Q132: =E132-P132 -> 3599250 | R132: 139 | S132: 76 | T132: =IF(N(S132)=0,"",Q132/S132) -> 47358.553 | U132: =IF(E132=0,"",IF(AND(N(C132)>0,F132="",G132=""),"Belum direalisasi",IF(AND(N(D132)>0,H132=""),"EDC belum settle",IF(ABS(O132)>50000,"Cek selisih tunai","OK")))) -> OK
A133: 46151 | B133: =MONTH(A133) -> 5 | C133: 716950 | D133: 2296800 | E133: =N(C133)+N(D133) -> 3013750 | F133: 185000 | G133: 532000 | H133: 2296716 | I133: =N(F133)+N(G133)+N(H133) -> 3013716 | J133: =IF(AND(F133="",G133=""),0,N(C133)-N(F133)-N(G133)) -> -50 | K133: =IF(H133="",0,N(D133)-N(H133)) -> 84 | O133: =IF(AND(F133="",G133=""),0,J133-N(L133)-N(M133)-N(N133)) -> -50 | P133: =K133+O133 -> 34 | Q133: =E133-P133 -> 3013716 | R133: 114 | S133: 66 | T133: =IF(N(S133)=0,"",Q133/S133) -> 45662.364 | U133: =IF(E133=0,"",IF(AND(N(C133)>0,F133="",G133=""),"Belum direalisasi",IF(AND(N(D133)>0,H133=""),"EDC belum settle",IF(ABS(O133)>50000,"Cek selisih tunai","OK")))) -> OK
A134: 46152 | B134: =MONTH(A134) -> 5 | C134: 1491300 | D134: 2280100 | E134: =N(C134)+N(D134) -> 3771400 | F134: 471000 | G134: 880000 | H134: 2280100 | I134: =N(F134)+N(G134)+N(H134) -> 3631100 | J134: =IF(AND(F134="",G134=""),0,N(C134)-N(F134)-N(G134)) -> 140300 | K134: =IF(H134="",0,N(D134)-N(H134)) -> 0 | N134: 141300 | O134: =IF(AND(F134="",G134=""),0,J134-N(L134)-N(M134)-N(N134)) -> -1000 | P134: =K134+O134 -> -1000 | Q134: =E134-P134 -> 3772400 | R134: 151 | S134: 85 | T134: =IF(N(S134)=0,"",Q134/S134) -> 44381.176 | U134: =IF(E134=0,"",IF(AND(N(C134)>0,F134="",G134=""),"Belum direalisasi",IF(AND(N(D134)>0,H134=""),"EDC belum settle",IF(ABS(O134)>50000,"Cek selisih tunai","OK")))) -> OK
A135: 46153 | B135: =MONTH(A135) -> 5 | C135: 350000 | D135: 1272600 | E135: =N(C135)+N(D135) -> 1622600 | F135: 130000 | G135: 220000 | H135: 1271070 | I135: =N(F135)+N(G135)+N(H135) -> 1621070 | J135: =IF(AND(F135="",G135=""),0,N(C135)-N(F135)-N(G135)) -> 0 | K135: =IF(H135="",0,N(D135)-N(H135)) -> 1530 | O135: =IF(AND(F135="",G135=""),0,J135-N(L135)-N(M135)-N(N135)) -> 0 | P135: =K135+O135 -> 1530 | Q135: =E135-P135 -> 1621070 | R135: 67 | S135: 38 | T135: =IF(N(S135)=0,"",Q135/S135) -> 42659.737 | U135: =IF(E135=0,"",IF(AND(N(C135)>0,F135="",G135=""),"Belum direalisasi",IF(AND(N(D135)>0,H135=""),"EDC belum settle",IF(ABS(O135)>50000,"Cek selisih tunai","OK")))) -> OK
A136: 46154 | B136: =MONTH(A136) -> 5 | C136: 471600 | D136: 1880600 | E136: =N(C136)+N(D136) -> 2352200 | F136: 141000 | G136: 330000 | H136: 1880600 | I136: =N(F136)+N(G136)+N(H136) -> 2351600 | J136: =IF(AND(F136="",G136=""),0,N(C136)-N(F136)-N(G136)) -> 600 | K136: =IF(H136="",0,N(D136)-N(H136)) -> 0 | O136: =IF(AND(F136="",G136=""),0,J136-N(L136)-N(M136)-N(N136)) -> 600 | P136: =K136+O136 -> 600 | Q136: =E136-P136 -> 2351600 | R136: 95 | S136: 53 | T136: =IF(N(S136)=0,"",Q136/S136) -> 44369.811 | U136: =IF(E136=0,"",IF(AND(N(C136)>0,F136="",G136=""),"Belum direalisasi",IF(AND(N(D136)>0,H136=""),"EDC belum settle",IF(ABS(O136)>50000,"Cek selisih tunai","OK")))) -> OK
A137: 46155 | B137: =MONTH(A137) -> 5 | C137: 613800 | D137: 1706350 | E137: =N(C137)+N(D137) -> 2320150 | F137: 204000 | G137: 246000 | H137: 1705830 | I137: =N(F137)+N(G137)+N(H137) -> 2155830 | J137: =IF(AND(F137="",G137=""),0,N(C137)-N(F137)-N(G137)) -> 163800 | K137: =IF(H137="",0,N(D137)-N(H137)) -> 520 | L137: 37800 | N137: 126000 | O137: =IF(AND(F137="",G137=""),0,J137-N(L137)-N(M137)-N(N137)) -> 0 | P137: =K137+O137 -> 520 | Q137: =E137-P137 -> 2319630 | R137: 95 | S137: 52 | T137: =IF(N(S137)=0,"",Q137/S137) -> 44608.269 | U137: =IF(E137=0,"",IF(AND(N(C137)>0,F137="",G137=""),"Belum direalisasi",IF(AND(N(D137)>0,H137=""),"EDC belum settle",IF(ABS(O137)>50000,"Cek selisih tunai","OK")))) -> OK
A138: 46156 | B138: =MONTH(A138) -> 5 | C138: 1206800 | D138: 2528900 | E138: =N(C138)+N(D138) -> 3735700 | F138: 247500 | G138: 854000 | H138: 2493900 | I138: =N(F138)+N(G138)+N(H138) -> 3595400 | J138: =IF(AND(F138="",G138=""),0,N(C138)-N(F138)-N(G138)) -> 105300 | K138: =IF(H138="",0,N(D138)-N(H138)) -> 35000 | N138: 105400 | O138: =IF(AND(F138="",G138=""),0,J138-N(L138)-N(M138)-N(N138)) -> -100 | P138: =K138+O138 -> 34900 | Q138: =E138-P138 -> 3700800 | R138: 141 | S138: 78 | T138: =IF(N(S138)=0,"",Q138/S138) -> 47446.154 | U138: =IF(E138=0,"",IF(AND(N(C138)>0,F138="",G138=""),"Belum direalisasi",IF(AND(N(D138)>0,H138=""),"EDC belum settle",IF(ABS(O138)>50000,"Cek selisih tunai","OK")))) -> OK
A139: 46157 | B139: =MONTH(A139) -> 5 | C139: 842500 | D139: 2958700 | E139: =N(C139)+N(D139) -> 3801200 | F139: 117000 | G139: 725000 | H139: 2958524 | I139: =N(F139)+N(G139)+N(H139) -> 3800524 | J139: =IF(AND(F139="",G139=""),0,N(C139)-N(F139)-N(G139)) -> 500 | K139: =IF(H139="",0,N(D139)-N(H139)) -> 176 | O139: =IF(AND(F139="",G139=""),0,J139-N(L139)-N(M139)-N(N139)) -> 500 | P139: =K139+O139 -> 676 | Q139: =E139-P139 -> 3800524 | R139: 142 | S139: 68 | T139: =IF(N(S139)=0,"",Q139/S139) -> 55890.059 | U139: =IF(E139=0,"",IF(AND(N(C139)>0,F139="",G139=""),"Belum direalisasi",IF(AND(N(D139)>0,H139=""),"EDC belum settle",IF(ABS(O139)>50000,"Cek selisih tunai","OK")))) -> OK
A140: 46158 | B140: =MONTH(A140) -> 5 | C140: 1265200 | D140: 3268950 | E140: =N(C140)+N(D140) -> 4534150 | F140: 77000 | G140: 892500 | H140: 3267320 | I140: =N(F140)+N(G140)+N(H140) -> 4236820 | J140: =IF(AND(F140="",G140=""),0,N(C140)-N(F140)-N(G140)) -> 295700 | K140: =IF(H140="",0,N(D140)-N(H140)) -> 1630 | N140: 295200 | O140: =IF(AND(F140="",G140=""),0,J140-N(L140)-N(M140)-N(N140)) -> 500 | P140: =K140+O140 -> 2130 | Q140: =E140-P140 -> 4532020 | R140: 176 | S140: 86 | T140: =IF(N(S140)=0,"",Q140/S140) -> 52697.907 | U140: =IF(E140=0,"",IF(AND(N(C140)>0,F140="",G140=""),"Belum direalisasi",IF(AND(N(D140)>0,H140=""),"EDC belum settle",IF(ABS(O140)>50000,"Cek selisih tunai","OK")))) -> OK
A141: 46159 | B141: =MONTH(A141) -> 5 | C141: 692000 | D141: 2559250 | E141: =N(C141)+N(D141) -> 3251250 | F141: 60000 | G141: 632000 | H141: 2559250 | I141: =N(F141)+N(G141)+N(H141) -> 3251250 | J141: =IF(AND(F141="",G141=""),0,N(C141)-N(F141)-N(G141)) -> 0 | K141: =IF(H141="",0,N(D141)-N(H141)) -> 0 | O141: =IF(AND(F141="",G141=""),0,J141-N(L141)-N(M141)-N(N141)) -> 0 | P141: =K141+O141 -> 0 | Q141: =E141-P141 -> 3251250 | R141: 116 | S141: 59 | T141: =IF(N(S141)=0,"",Q141/S141) -> 55105.932 | U141: =IF(E141=0,"",IF(AND(N(C141)>0,F141="",G141=""),"Belum direalisasi",IF(AND(N(D141)>0,H141=""),"EDC belum settle",IF(ABS(O141)>50000,"Cek selisih tunai","OK")))) -> OK
A142: 46160 | B142: =MONTH(A142) -> 5 | C142: 634000 | D142: 3228200 | E142: =N(C142)+N(D142) -> 3862200 | F142: 189000 | G142: 445000 | H142: 3227260 | I142: =N(F142)+N(G142)+N(H142) -> 3861260 | J142: =IF(AND(F142="",G142=""),0,N(C142)-N(F142)-N(G142)) -> 0 | K142: =IF(H142="",0,N(D142)-N(H142)) -> 940 | O142: =IF(AND(F142="",G142=""),0,J142-N(L142)-N(M142)-N(N142)) -> 0 | P142: =K142+O142 -> 940 | Q142: =E142-P142 -> 3861260 | R142: 146 | S142: 69 | T142: =IF(N(S142)=0,"",Q142/S142) -> 55960.29 | U142: =IF(E142=0,"",IF(AND(N(C142)>0,F142="",G142=""),"Belum direalisasi",IF(AND(N(D142)>0,H142=""),"EDC belum settle",IF(ABS(O142)>50000,"Cek selisih tunai","OK")))) -> OK
A143: 46161 | B143: =MONTH(A143) -> 5 | C143: 712150 | D143: 2029500 | E143: =N(C143)+N(D143) -> 2741650 | F143: 253000 | G143: 460000 | H143: 2029425 | I143: =N(F143)+N(G143)+N(H143) -> 2742425 | J143: =IF(AND(F143="",G143=""),0,N(C143)-N(F143)-N(G143)) -> -850 | K143: =IF(H143="",0,N(D143)-N(H143)) -> 75 | O143: =IF(AND(F143="",G143=""),0,J143-N(L143)-N(M143)-N(N143)) -> -850 | P143: =K143+O143 -> -775 | Q143: =E143-P143 -> 2742425 | R143: 102 | S143: 66 | T143: =IF(N(S143)=0,"",Q143/S143) -> 41551.894 | U143: =IF(E143=0,"",IF(AND(N(C143)>0,F143="",G143=""),"Belum direalisasi",IF(AND(N(D143)>0,H143=""),"EDC belum settle",IF(ABS(O143)>50000,"Cek selisih tunai","OK")))) -> OK
A144: 46162 | B144: =MONTH(A144) -> 5 | C144: 816000 | D144: 1565500 | E144: =N(C144)+N(D144) -> 2381500 | F144: 361000 | G144: 455000 | H144: 1565230 | I144: =N(F144)+N(G144)+N(H144) -> 2381230 | J144: =IF(AND(F144="",G144=""),0,N(C144)-N(F144)-N(G144)) -> 0 | K144: =IF(H144="",0,N(D144)-N(H144)) -> 270 | O144: =IF(AND(F144="",G144=""),0,J144-N(L144)-N(M144)-N(N144)) -> 0 | P144: =K144+O144 -> 270 | Q144: =E144-P144 -> 2381230 | R144: 85 | S144: 49 | T144: =IF(N(S144)=0,"",Q144/S144) -> 48596.531 | U144: =IF(E144=0,"",IF(AND(N(C144)>0,F144="",G144=""),"Belum direalisasi",IF(AND(N(D144)>0,H144=""),"EDC belum settle",IF(ABS(O144)>50000,"Cek selisih tunai","OK")))) -> OK
A145: 46163 | B145: =MONTH(A145) -> 5 | C145: 807000 | D145: 1331600 | E145: =N(C145)+N(D145) -> 2138600 | F145: 260000 | G145: 547000 | H145: 1331600 | I145: =N(F145)+N(G145)+N(H145) -> 2138600 | J145: =IF(AND(F145="",G145=""),0,N(C145)-N(F145)-N(G145)) -> 0 | K145: =IF(H145="",0,N(D145)-N(H145)) -> 0 | O145: =IF(AND(F145="",G145=""),0,J145-N(L145)-N(M145)-N(N145)) -> 0 | P145: =K145+O145 -> 0 | Q145: =E145-P145 -> 2138600 | R145: 81 | S145: 52 | T145: =IF(N(S145)=0,"",Q145/S145) -> 41126.923 | U145: =IF(E145=0,"",IF(AND(N(C145)>0,F145="",G145=""),"Belum direalisasi",IF(AND(N(D145)>0,H145=""),"EDC belum settle",IF(ABS(O145)>50000,"Cek selisih tunai","OK")))) -> OK
A146: 46164 | B146: =MONTH(A146) -> 5 | C146: 987000 | D146: 2656850 | E146: =N(C146)+N(D146) -> 3643850 | F146: 188000 | G146: 800000 | H146: 2606670 | I146: =N(F146)+N(G146)+N(H146) -> 3594670 | J146: =IF(AND(F146="",G146=""),0,N(C146)-N(F146)-N(G146)) -> -1000 | K146: =IF(H146="",0,N(D146)-N(H146)) -> 50180 | O146: =IF(AND(F146="",G146=""),0,J146-N(L146)-N(M146)-N(N146)) -> -1000 | P146: =K146+O146 -> 49180 | Q146: =E146-P146 -> 3594670 | R146: 141 | S146: 81 | T146: =IF(N(S146)=0,"",Q146/S146) -> 44378.642 | U146: =IF(E146=0,"",IF(AND(N(C146)>0,F146="",G146=""),"Belum direalisasi",IF(AND(N(D146)>0,H146=""),"EDC belum settle",IF(ABS(O146)>50000,"Cek selisih tunai","OK")))) -> OK
A147: 46165 | B147: =MONTH(A147) -> 5 | C147: 1558400 | D147: 3189000 | E147: =N(C147)+N(D147) -> 4747400 | F147: 419000 | G147: 964000 | H147: 3297459 | I147: =N(F147)+N(G147)+N(H147) -> 4680459 | J147: =IF(AND(F147="",G147=""),0,N(C147)-N(F147)-N(G147)) -> 175400 | K147: =IF(H147="",0,N(D147)-N(H147)) -> -108459 | N147: 175800 | O147: =IF(AND(F147="",G147=""),0,J147-N(L147)-N(M147)-N(N147)) -> -400 | P147: =K147+O147 -> -108859 | Q147: =E147-P147 -> 4856259 | R147: 170 | S147: 79 | T147: =IF(N(S147)=0,"",Q147/S147) -> 61471.633 | U147: =IF(E147=0,"",IF(AND(N(C147)>0,F147="",G147=""),"Belum direalisasi",IF(AND(N(D147)>0,H147=""),"EDC belum settle",IF(ABS(O147)>50000,"Cek selisih tunai","OK")))) -> OK
A148: 46166 | B148: =MONTH(A148) -> 5 | C148: 985200 | D148: 2749000 | E148: =N(C148)+N(D148) -> 3734200 | F148: 223000 | G148: 762000 | H148: 2692000 | I148: =N(F148)+N(G148)+N(H148) -> 3677000 | J148: =IF(AND(F148="",G148=""),0,N(C148)-N(F148)-N(G148)) -> 200 | K148: =IF(H148="",0,N(D148)-N(H148)) -> 57000 | O148: =IF(AND(F148="",G148=""),0,J148-N(L148)-N(M148)-N(N148)) -> 200 | P148: =K148+O148 -> 57200 | Q148: =E148-P148 -> 3677000 | R148: 137 | S148: 79 | T148: =IF(N(S148)=0,"",Q148/S148) -> 46544.304 | U148: =IF(E148=0,"",IF(AND(N(C148)>0,F148="",G148=""),"Belum direalisasi",IF(AND(N(D148)>0,H148=""),"EDC belum settle",IF(ABS(O148)>50000,"Cek selisih tunai","OK")))) -> OK
A149: 46167 | B149: =MONTH(A149) -> 5 | C149: 555650 | D149: 2437700 | E149: =N(C149)+N(D149) -> 2993350 | F149: 0 | G149: 556000 | H149: 2437346 | I149: =N(F149)+N(G149)+N(H149) -> 2993346 | J149: =IF(AND(F149="",G149=""),0,N(C149)-N(F149)-N(G149)) -> -350 | K149: =IF(H149="",0,N(D149)-N(H149)) -> 354 | O149: =IF(AND(F149="",G149=""),0,J149-N(L149)-N(M149)-N(N149)) -> -350 | P149: =K149+O149 -> 4 | Q149: =E149-P149 -> 2993346 | R149: 111 | S149: 68 | T149: =IF(N(S149)=0,"",Q149/S149) -> 44019.794 | U149: =IF(E149=0,"",IF(AND(N(C149)>0,F149="",G149=""),"Belum direalisasi",IF(AND(N(D149)>0,H149=""),"EDC belum settle",IF(ABS(O149)>50000,"Cek selisih tunai","OK")))) -> OK
A150: 46168 | B150: =MONTH(A150) -> 5 | C150: 1366550 | D150: 2481700 | E150: =N(C150)+N(D150) -> 3848250 | F150: 229000 | G150: 953000 | H150: 2481700 | I150: =N(F150)+N(G150)+N(H150) -> 3663700 | J150: =IF(AND(F150="",G150=""),0,N(C150)-N(F150)-N(G150)) -> 184550 | K150: =IF(H150="",0,N(D150)-N(H150)) -> 0 | N150: 184800 | O150: =IF(AND(F150="",G150=""),0,J150-N(L150)-N(M150)-N(N150)) -> -250 | P150: =K150+O150 -> -250 | Q150: =E150-P150 -> 3848500 | R150: 139 | S150: 77 | T150: =IF(N(S150)=0,"",Q150/S150) -> 49980.519 | U150: =IF(E150=0,"",IF(AND(N(C150)>0,F150="",G150=""),"Belum direalisasi",IF(AND(N(D150)>0,H150=""),"EDC belum settle",IF(ABS(O150)>50000,"Cek selisih tunai","OK")))) -> OK
A151: 46169 | B151: =MONTH(A151) -> 5 | C151: 681000 | D151: 2417300 | E151: =N(C151)+N(D151) -> 3098300 | F151: 0 | G151: 654000 | H151: 2446300 | I151: =N(F151)+N(G151)+N(H151) -> 3100300 | J151: =IF(AND(F151="",G151=""),0,N(C151)-N(F151)-N(G151)) -> 27000 | K151: =IF(H151="",0,N(D151)-N(H151)) -> -29000 | O151: =IF(AND(F151="",G151=""),0,J151-N(L151)-N(M151)-N(N151)) -> 27000 | P151: =K151+O151 -> -2000 | Q151: =E151-P151 -> 3100300 | R151: 112 | S151: 65 | T151: =IF(N(S151)=0,"",Q151/S151) -> 47696.923 | U151: =IF(E151=0,"",IF(AND(N(C151)>0,F151="",G151=""),"Belum direalisasi",IF(AND(N(D151)>0,H151=""),"EDC belum settle",IF(ABS(O151)>50000,"Cek selisih tunai","OK")))) -> OK
A152: 46170 | B152: =MONTH(A152) -> 5 | C152: 1216700 | D152: 2864800 | E152: =N(C152)+N(D152) -> 4081500 | F152: 87000 | G152: 1129000 | H152: 2864669 | I152: =N(F152)+N(G152)+N(H152) -> 4080669 | J152: =IF(AND(F152="",G152=""),0,N(C152)-N(F152)-N(G152)) -> 700 | K152: =IF(H152="",0,N(D152)-N(H152)) -> 131 | O152: =IF(AND(F152="",G152=""),0,J152-N(L152)-N(M152)-N(N152)) -> 700 | P152: =K152+O152 -> 831 | Q152: =E152-P152 -> 4080669 | R152: 151 | S152: 73 | T152: =IF(N(S152)=0,"",Q152/S152) -> 55899.575 | U152: =IF(E152=0,"",IF(AND(N(C152)>0,F152="",G152=""),"Belum direalisasi",IF(AND(N(D152)>0,H152=""),"EDC belum settle",IF(ABS(O152)>50000,"Cek selisih tunai","OK")))) -> OK
A153: 46171 | B153: =MONTH(A153) -> 5 | C153: 986300 | D153: 3580600 | E153: =N(C153)+N(D153) -> 4566900 | F153: 325000 | G153: 661000 | H153: 3584719 | I153: =N(F153)+N(G153)+N(H153) -> 4570719 | J153: =IF(AND(F153="",G153=""),0,N(C153)-N(F153)-N(G153)) -> 300 | K153: =IF(H153="",0,N(D153)-N(H153)) -> -4119 | O153: =IF(AND(F153="",G153=""),0,J153-N(L153)-N(M153)-N(N153)) -> 300 | P153: =K153+O153 -> -3819 | Q153: =E153-P153 -> 4570719 | R153: 165 | S153: 87 | T153: =IF(N(S153)=0,"",Q153/S153) -> 52537 | U153: =IF(E153=0,"",IF(AND(N(C153)>0,F153="",G153=""),"Belum direalisasi",IF(AND(N(D153)>0,H153=""),"EDC belum settle",IF(ABS(O153)>50000,"Cek selisih tunai","OK")))) -> OK
A154: 46172 | B154: =MONTH(A154) -> 5 | C154: 2203700 | D154: 2732250 | E154: =N(C154)+N(D154) -> 4935950 | F154: 350000 | G154: 1685000 | H154: 2732250 | I154: =N(F154)+N(G154)+N(H154) -> 4767250 | J154: =IF(AND(F154="",G154=""),0,N(C154)-N(F154)-N(G154)) -> 168700 | K154: =IF(H154="",0,N(D154)-N(H154)) -> 0 | N154: 167400 | O154: =IF(AND(F154="",G154=""),0,J154-N(L154)-N(M154)-N(N154)) -> 1300 | P154: =K154+O154 -> 1300 | Q154: =E154-P154 -> 4934650 | R154: 181 | S154: 87 | T154: =IF(N(S154)=0,"",Q154/S154) -> 56720.115 | U154: =IF(E154=0,"",IF(AND(N(C154)>0,F154="",G154=""),"Belum direalisasi",IF(AND(N(D154)>0,H154=""),"EDC belum settle",IF(ABS(O154)>50000,"Cek selisih tunai","OK")))) -> OK
A155: 46173 | B155: =MONTH(A155) -> 5 | C155: 1330750 | D155: 2788800 | E155: =N(C155)+N(D155) -> 4119550 | F155: 297000 | G155: 1010000 | H155: 2788800 | I155: =N(F155)+N(G155)+N(H155) -> 4095800 | J155: =IF(AND(F155="",G155=""),0,N(C155)-N(F155)-N(G155)) -> 23750 | K155: =IF(H155="",0,N(D155)-N(H155)) -> 0 | N155: 22500 | O155: =IF(AND(F155="",G155=""),0,J155-N(L155)-N(M155)-N(N155)) -> 1250 | P155: =K155+O155 -> 1250 | Q155: =E155-P155 -> 4118300 | R155: 147 | S155: 76 | T155: =IF(N(S155)=0,"",Q155/S155) -> 54188.158 | U155: =IF(E155=0,"",IF(AND(N(C155)>0,F155="",G155=""),"Belum direalisasi",IF(AND(N(D155)>0,H155=""),"EDC belum settle",IF(ABS(O155)>50000,"Cek selisih tunai","OK")))) -> OK
A156: 46174 | B156: =MONTH(A156) -> 6 | C156: 513000 | D156: 3298550 | E156: =N(C156)+N(D156) -> 3811550 | F156: 84000 | G156: 385000 | H156: 3325424 | I156: =N(F156)+N(G156)+N(H156) -> 3794424 | J156: =IF(AND(F156="",G156=""),0,N(C156)-N(F156)-N(G156)) -> 44000 | K156: =IF(H156="",0,N(D156)-N(H156)) -> -26874 | L156: 22500 | M156: 22500 | O156: =IF(AND(F156="",G156=""),0,J156-N(L156)-N(M156)-N(N156)) -> -1000 | P156: =K156+O156 -> -27874 | Q156: =E156-P156 -> 3839424 | R156: 145 | S156: 79 | T156: =IF(N(S156)=0,"",Q156/S156) -> 48600.304 | U156: =IF(E156=0,"",IF(AND(N(C156)>0,F156="",G156=""),"Belum direalisasi",IF(AND(N(D156)>0,H156=""),"EDC belum settle",IF(ABS(O156)>50000,"Cek selisih tunai","OK")))) -> OK
A157: 46175 | B157: =MONTH(A157) -> 6 | C157: 435300 | D157: 2218600 | E157: =N(C157)+N(D157) -> 2653900 | F157: 154000 | G157: 174000 | H157: 2218550 | I157: =N(F157)+N(G157)+N(H157) -> 2546550 | J157: =IF(AND(F157="",G157=""),0,N(C157)-N(F157)-N(G157)) -> 107300 | K157: =IF(H157="",0,N(D157)-N(H157)) -> 50 | L157: 22500 | M157: 22500 | N157: 63000 | O157: =IF(AND(F157="",G157=""),0,J157-N(L157)-N(M157)-N(N157)) -> -700 | P157: =K157+O157 -> -650 | Q157: =E157-P157 -> 2654550 | R157: 100 | S157: 54 | T157: =IF(N(S157)=0,"",Q157/S157) -> 49158.333 | U157: =IF(E157=0,"",IF(AND(N(C157)>0,F157="",G157=""),"Belum direalisasi",IF(AND(N(D157)>0,H157=""),"EDC belum settle",IF(ABS(O157)>50000,"Cek selisih tunai","OK")))) -> OK
A158: 46176 | B158: =MONTH(A158) -> 6 | C158: 475500 | D158: 2259000 | E158: =N(C158)+N(D158) -> 2734500 | F158: 27000 | G158: 384000 | H158: 2199922 | I158: =N(F158)+N(G158)+N(H158) -> 2610922 | J158: =IF(AND(F158="",G158=""),0,N(C158)-N(F158)-N(G158)) -> 64500 | K158: =IF(H158="",0,N(D158)-N(H158)) -> 59078 | L158: 64500 | O158: =IF(AND(F158="",G158=""),0,J158-N(L158)-N(M158)-N(N158)) -> 0 | P158: =K158+O158 -> 59078 | Q158: =E158-P158 -> 2675422 | R158: 97 | S158: 61 | T158: =IF(N(S158)=0,"",Q158/S158) -> 43859.377 | U158: =IF(E158=0,"",IF(AND(N(C158)>0,F158="",G158=""),"Belum direalisasi",IF(AND(N(D158)>0,H158=""),"EDC belum settle",IF(ABS(O158)>50000,"Cek selisih tunai","OK")))) -> OK
A159: 46177 | B159: =MONTH(A159) -> 6 | C159: 762000 | D159: 3250100 | E159: =N(C159)+N(D159) -> 4012100 | F159: 266000 | G159: 496000 | H159: 3288405 | I159: =N(F159)+N(G159)+N(H159) -> 4050405 | J159: =IF(AND(F159="",G159=""),0,N(C159)-N(F159)-N(G159)) -> 0 | K159: =IF(H159="",0,N(D159)-N(H159)) -> -38305 | O159: =IF(AND(F159="",G159=""),0,J159-N(L159)-N(M159)-N(N159)) -> 0 | P159: =K159+O159 -> -38305 | Q159: =E159-P159 -> 4050405 | R159: 142 | S159: 80 | T159: =IF(N(S159)=0,"",Q159/S159) -> 50630.062 | U159: =IF(E159=0,"",IF(AND(N(C159)>0,F159="",G159=""),"Belum direalisasi",IF(AND(N(D159)>0,H159=""),"EDC belum settle",IF(ABS(O159)>50000,"Cek selisih tunai","OK")))) -> OK
A160: 46178 | B160: =MONTH(A160) -> 6 | C160: 428000 | D160: 2477600 | E160: =N(C160)+N(D160) -> 2905600 | F160: 102000 | G160: 326000 | H160: 2477600 | I160: =N(F160)+N(G160)+N(H160) -> 2905600 | J160: =IF(AND(F160="",G160=""),0,N(C160)-N(F160)-N(G160)) -> 0 | K160: =IF(H160="",0,N(D160)-N(H160)) -> 0 | O160: =IF(AND(F160="",G160=""),0,J160-N(L160)-N(M160)-N(N160)) -> 0 | P160: =K160+O160 -> 0 | Q160: =E160-P160 -> 2905600 | R160: 107 | S160: 58 | T160: =IF(N(S160)=0,"",Q160/S160) -> 50096.552 | U160: =IF(E160=0,"",IF(AND(N(C160)>0,F160="",G160=""),"Belum direalisasi",IF(AND(N(D160)>0,H160=""),"EDC belum settle",IF(ABS(O160)>50000,"Cek selisih tunai","OK")))) -> OK
A161: 46179 | B161: =MONTH(A161) -> 6 | C161: 669000 | D161: 3911550 | E161: =N(C161)+N(D161) -> 4580550 | F161: 172000 | G161: 497000 | H161: 3911457 | I161: =N(F161)+N(G161)+N(H161) -> 4580457 | J161: =IF(AND(F161="",G161=""),0,N(C161)-N(F161)-N(G161)) -> 0 | K161: =IF(H161="",0,N(D161)-N(H161)) -> 93 | O161: =IF(AND(F161="",G161=""),0,J161-N(L161)-N(M161)-N(N161)) -> 0 | P161: =K161+O161 -> 93 | Q161: =E161-P161 -> 4580457 | R161: 171 | S161: 103 | T161: =IF(N(S161)=0,"",Q161/S161) -> 44470.456 | U161: =IF(E161=0,"",IF(AND(N(C161)>0,F161="",G161=""),"Belum direalisasi",IF(AND(N(D161)>0,H161=""),"EDC belum settle",IF(ABS(O161)>50000,"Cek selisih tunai","OK")))) -> OK
A162: 46180 | B162: =MONTH(A162) -> 6 | C162: 993450 | D162: 2230750 | E162: =N(C162)+N(D162) -> 3224200 | F162: 220000 | G162: 670000 | H162: 2230712 | I162: =N(F162)+N(G162)+N(H162) -> 3120712 | J162: =IF(AND(F162="",G162=""),0,N(C162)-N(F162)-N(G162)) -> 103450 | K162: =IF(H162="",0,N(D162)-N(H162)) -> 38 | N162: 103500 | O162: =IF(AND(F162="",G162=""),0,J162-N(L162)-N(M162)-N(N162)) -> -50 | P162: =K162+O162 -> -12 | Q162: =E162-P162 -> 3224212 | R162: 119 | S162: 61 | T162: =IF(N(S162)=0,"",Q162/S162) -> 52855.934 | U162: =IF(E162=0,"",IF(AND(N(C162)>0,F162="",G162=""),"Belum direalisasi",IF(AND(N(D162)>0,H162=""),"EDC belum settle",IF(ABS(O162)>50000,"Cek selisih tunai","OK")))) -> OK
A163: 46181 | B163: =MONTH(A163) -> 6 | C163: 999000 | D163: 2398800 | E163: =N(C163)+N(D163) -> 3397800 | F163: 449000 | G163: 550000 | H163: 2398740 | I163: =N(F163)+N(G163)+N(H163) -> 3397740 | J163: =IF(AND(F163="",G163=""),0,N(C163)-N(F163)-N(G163)) -> 0 | K163: =IF(H163="",0,N(D163)-N(H163)) -> 60 | O163: =IF(AND(F163="",G163=""),0,J163-N(L163)-N(M163)-N(N163)) -> 0 | P163: =K163+O163 -> 60 | Q163: =E163-P163 -> 3397740 | R163: 128 | S163: 79 | T163: =IF(N(S163)=0,"",Q163/S163) -> 43009.367 | U163: =IF(E163=0,"",IF(AND(N(C163)>0,F163="",G163=""),"Belum direalisasi",IF(AND(N(D163)>0,H163=""),"EDC belum settle",IF(ABS(O163)>50000,"Cek selisih tunai","OK")))) -> OK
A164: 46182 | B164: =MONTH(A164) -> 6 | C164: 687600 | D164: 2855950 | E164: =N(C164)+N(D164) -> 3543550 | F164: 115000 | G164: 547000 | H164: 2855950 | I164: =N(F164)+N(G164)+N(H164) -> 3517950 | J164: =IF(AND(F164="",G164=""),0,N(C164)-N(F164)-N(G164)) -> 25600 | K164: =IF(H164="",0,N(D164)-N(H164)) -> 0 | L164: 24300 | O164: =IF(AND(F164="",G164=""),0,J164-N(L164)-N(M164)-N(N164)) -> 1300 | P164: =K164+O164 -> 1300 | Q164: =E164-P164 -> 3542250 | R164: 134 | S164: 71 | T164: =IF(N(S164)=0,"",Q164/S164) -> 49890.845 | U164: =IF(E164=0,"",IF(AND(N(C164)>0,F164="",G164=""),"Belum direalisasi",IF(AND(N(D164)>0,H164=""),"EDC belum settle",IF(ABS(O164)>50000,"Cek selisih tunai","OK")))) -> OK
A165: 46183 | B165: =MONTH(A165) -> 6 | C165: 691700 | D165: 1397550 | E165: =N(C165)+N(D165) -> 2089250 | F165: 376000 | G165: 266000 | H165: 1396933 | I165: =N(F165)+N(G165)+N(H165) -> 2038933 | J165: =IF(AND(F165="",G165=""),0,N(C165)-N(F165)-N(G165)) -> 49700 | K165: =IF(H165="",0,N(D165)-N(H165)) -> 617 | L165: 48600 | O165: =IF(AND(F165="",G165=""),0,J165-N(L165)-N(M165)-N(N165)) -> 1100 | P165: =K165+O165 -> 1717 | Q165: =E165-P165 -> 2087533 | R165: 78 | S165: 48 | T165: =IF(N(S165)=0,"",Q165/S165) -> 43490.271 | U165: =IF(E165=0,"",IF(AND(N(C165)>0,F165="",G165=""),"Belum direalisasi",IF(AND(N(D165)>0,H165=""),"EDC belum settle",IF(ABS(O165)>50000,"Cek selisih tunai","OK")))) -> OK
A166: 46184 | B166: =MONTH(A166) -> 6 | C166: 958000 | D166: 2345150 | E166: =N(C166)+N(D166) -> 3303150 | F166: 367000 | G166: 591000 | H166: 2312650 | I166: =N(F166)+N(G166)+N(H166) -> 3270650 | J166: =IF(AND(F166="",G166=""),0,N(C166)-N(F166)-N(G166)) -> 0 | K166: =IF(H166="",0,N(D166)-N(H166)) -> 32500 | O166: =IF(AND(F166="",G166=""),0,J166-N(L166)-N(M166)-N(N166)) -> 0 | P166: =K166+O166 -> 32500 | Q166: =E166-P166 -> 3270650 | R166: 119 | S166: 68 | T166: =IF(N(S166)=0,"",Q166/S166) -> 48097.794 | U166: =IF(E166=0,"",IF(AND(N(C166)>0,F166="",G166=""),"Belum direalisasi",IF(AND(N(D166)>0,H166=""),"EDC belum settle",IF(ABS(O166)>50000,"Cek selisih tunai","OK")))) -> OK
A167: 46185 | B167: =MONTH(A167) -> 6 | C167: 1005000 | D167: 2823300 | E167: =N(C167)+N(D167) -> 3828300 | F167: 655000 | G167: 394000 | H167: 2796300 | I167: =N(F167)+N(G167)+N(H167) -> 3845300 | J167: =IF(AND(F167="",G167=""),0,N(C167)-N(F167)-N(G167)) -> -44000 | K167: =IF(H167="",0,N(D167)-N(H167)) -> 27000 | O167: =IF(AND(F167="",G167=""),0,J167-N(L167)-N(M167)-N(N167)) -> -44000 | P167: =K167+O167 -> -17000 | Q167: =E167-P167 -> 3845300 | R167: 151 | S167: 93 | T167: =IF(N(S167)=0,"",Q167/S167) -> 41347.312 | U167: =IF(E167=0,"",IF(AND(N(C167)>0,F167="",G167=""),"Belum direalisasi",IF(AND(N(D167)>0,H167=""),"EDC belum settle",IF(ABS(O167)>50000,"Cek selisih tunai","OK")))) -> OK
A168: 46186 | B168: =MONTH(A168) -> 6 | C168: 1762300 | D168: 4260800 | E168: =N(C168)+N(D168) -> 6023100 | F168: 520000 | G168: 1037000 | H168: 4287714 | I168: =N(F168)+N(G168)+N(H168) -> 5844714 | J168: =IF(AND(F168="",G168=""),0,N(C168)-N(F168)-N(G168)) -> 205300 | K168: =IF(H168="",0,N(D168)-N(H168)) -> -26914 | M168: 69300 | N168: 109000 | O168: =IF(AND(F168="",G168=""),0,J168-N(L168)-N(M168)-N(N168)) -> 27000 | P168: =K168+O168 -> 86 | Q168: =E168-P168 -> 6023014 | R168: 224 | S168: 121 | T168: =IF(N(S168)=0,"",Q168/S168) -> 49776.975 | U168: =IF(E168=0,"",IF(AND(N(C168)>0,F168="",G168=""),"Belum direalisasi",IF(AND(N(D168)>0,H168=""),"EDC belum settle",IF(ABS(O168)>50000,"Cek selisih tunai","OK")))) -> OK
A169: 46187 | B169: =MONTH(A169) -> 6 | C169: 1168000 | D169: 3679100 | E169: =N(C169)+N(D169) -> 4847100 | F169: 396000 | G169: 584000 | H169: 3679100 | I169: =N(F169)+N(G169)+N(H169) -> 4659100 | J169: =IF(AND(F169="",G169=""),0,N(C169)-N(F169)-N(G169)) -> 188000 | K169: =IF(H169="",0,N(D169)-N(H169)) -> 0 | L169: 50000 | O169: =IF(AND(F169="",G169=""),0,J169-N(L169)-N(M169)-N(N169)) -> 138000 | P169: =K169+O169 -> 138000 | Q169: =E169-P169 -> 4709100 | R169: 183 | S169: 106 | T169: =IF(N(S169)=0,"",Q169/S169) -> 44425.472 | U169: =IF(E169=0,"",IF(AND(N(C169)>0,F169="",G169=""),"Belum direalisasi",IF(AND(N(D169)>0,H169=""),"EDC belum settle",IF(ABS(O169)>50000,"Cek selisih tunai","OK")))) -> Cek selisih tunai
A170: 46188 | B170: =MONTH(A170) -> 6 | C170: 1425500 | D170: 2660800 | E170: =N(C170)+N(D170) -> 4086300 | F170: 613000 | G170: 806000 | H170: 2660800 | I170: =N(F170)+N(G170)+N(H170) -> 4079800 | J170: =IF(AND(F170="",G170=""),0,N(C170)-N(F170)-N(G170)) -> 6500 | K170: =IF(H170="",0,N(D170)-N(H170)) -> 0 | M170: 25000 | N170: 119700 | O170: =IF(AND(F170="",G170=""),0,J170-N(L170)-N(M170)-N(N170)) -> -138200 | P170: =K170+O170 -> -138200 | Q170: =E170-P170 -> 4224500 | R170: 146 | S170: 77 | T170: =IF(N(S170)=0,"",Q170/S170) -> 54863.636 | U170: =IF(E170=0,"",IF(AND(N(C170)>0,F170="",G170=""),"Belum direalisasi",IF(AND(N(D170)>0,H170=""),"EDC belum settle",IF(ABS(O170)>50000,"Cek selisih tunai","OK")))) -> Cek selisih tunai
A171: 46189 | B171: =MONTH(A171) -> 6 | C171: 1421100 | D171: 3261000 | E171: =N(C171)+N(D171) -> 4682100 | F171: 726000 | G171: 640000 | H171: 3261300 | I171: =N(F171)+N(G171)+N(H171) -> 4627300 | J171: =IF(AND(F171="",G171=""),0,N(C171)-N(F171)-N(G171)) -> 55100 | K171: =IF(H171="",0,N(D171)-N(H171)) -> -300 | O171: =IF(AND(F171="",G171=""),0,J171-N(L171)-N(M171)-N(N171)) -> 55100 | P171: =K171+O171 -> 54800 | Q171: =E171-P171 -> 4627300 | R171: 176 | S171: 102 | T171: =IF(N(S171)=0,"",Q171/S171) -> 45365.686 | U171: =IF(E171=0,"",IF(AND(N(C171)>0,F171="",G171=""),"Belum direalisasi",IF(AND(N(D171)>0,H171=""),"EDC belum settle",IF(ABS(O171)>50000,"Cek selisih tunai","OK")))) -> Cek selisih tunai
A172: 46190 | B172: =MONTH(A172) -> 6 | C172: 861000 | D172: 2716550 | E172: =N(C172)+N(D172) -> 3577550 | F172: 599000 | G172: 276000 | H172: 2719550 | I172: =N(F172)+N(G172)+N(H172) -> 3594550 | J172: =IF(AND(F172="",G172=""),0,N(C172)-N(F172)-N(G172)) -> -14000 | K172: =IF(H172="",0,N(D172)-N(H172)) -> -3000 | L172: 8000 | O172: =IF(AND(F172="",G172=""),0,J172-N(L172)-N(M172)-N(N172)) -> -22000 | P172: =K172+O172 -> -25000 | Q172: =E172-P172 -> 3602550 | R172: 139 | S172: 90 | T172: =IF(N(S172)=0,"",Q172/S172) -> 40028.333 | U172: =IF(E172=0,"",IF(AND(N(C172)>0,F172="",G172=""),"Belum direalisasi",IF(AND(N(D172)>0,H172=""),"EDC belum settle",IF(ABS(O172)>50000,"Cek selisih tunai","OK")))) -> OK
A173: 46191 | B173: =MONTH(A173) -> 6 | C173: 688600 | D173: 2158100 | E173: =N(C173)+N(D173) -> 2846700 | F173: 60000 | G173: 589000 | H173: 2158059 | I173: =N(F173)+N(G173)+N(H173) -> 2807059 | J173: =IF(AND(F173="",G173=""),0,N(C173)-N(F173)-N(G173)) -> 39600 | K173: =IF(H173="",0,N(D173)-N(H173)) -> 41 | L173: 39600 | O173: =IF(AND(F173="",G173=""),0,J173-N(L173)-N(M173)-N(N173)) -> 0 | P173: =K173+O173 -> 41 | Q173: =E173-P173 -> 2846659 | R173: 105 | S173: 61 | T173: =IF(N(S173)=0,"",Q173/S173) -> 46666.541 | U173: =IF(E173=0,"",IF(AND(N(C173)>0,F173="",G173=""),"Belum direalisasi",IF(AND(N(D173)>0,H173=""),"EDC belum settle",IF(ABS(O173)>50000,"Cek selisih tunai","OK")))) -> OK
A174: 46192 | B174: =MONTH(A174) -> 6 | C174: 826500 | D174: 2837800 | E174: =N(C174)+N(D174) -> 3664300 | F174: 302000 | G174: 525000 | H174: 2837800 | I174: =N(F174)+N(G174)+N(H174) -> 3664800 | J174: =IF(AND(F174="",G174=""),0,N(C174)-N(F174)-N(G174)) -> -500 | K174: =IF(H174="",0,N(D174)-N(H174)) -> 0 | O174: =IF(AND(F174="",G174=""),0,J174-N(L174)-N(M174)-N(N174)) -> -500 | P174: =K174+O174 -> -500 | Q174: =E174-P174 -> 3664800 | R174: 130 | S174: 77 | T174: =IF(N(S174)=0,"",Q174/S174) -> 47594.805 | U174: =IF(E174=0,"",IF(AND(N(C174)>0,F174="",G174=""),"Belum direalisasi",IF(AND(N(D174)>0,H174=""),"EDC belum settle",IF(ABS(O174)>50000,"Cek selisih tunai","OK")))) -> OK
A175: 46193 | B175: =MONTH(A175) -> 6 | C175: 1744800 | D175: 4108850 | E175: =N(C175)+N(D175) -> 5853650 | F175: 522000 | G175: 1176000 | H175: 4108652 | I175: =N(F175)+N(G175)+N(H175) -> 5806652 | J175: =IF(AND(F175="",G175=""),0,N(C175)-N(F175)-N(G175)) -> 46800 | K175: =IF(H175="",0,N(D175)-N(H175)) -> 198 | L175: 24500 | N175: 22500 | O175: =IF(AND(F175="",G175=""),0,J175-N(L175)-N(M175)-N(N175)) -> -200 | P175: =K175+O175 -> -2 | Q175: =E175-P175 -> 5853652 | R175: 209 | S175: 120 | T175: =IF(N(S175)=0,"",Q175/S175) -> 48780.433 | U175: =IF(E175=0,"",IF(AND(N(C175)>0,F175="",G175=""),"Belum direalisasi",IF(AND(N(D175)>0,H175=""),"EDC belum settle",IF(ABS(O175)>50000,"Cek selisih tunai","OK")))) -> OK
A176: 46194 | B176: =MONTH(A176) -> 6 | C176: 888950 | D176: 2132450 | E176: =N(C176)+N(D176) -> 3021400 | F176: 291000 | G176: 501000 | H176: 2186955 | I176: =N(F176)+N(G176)+N(H176) -> 2978955 | J176: =IF(AND(F176="",G176=""),0,N(C176)-N(F176)-N(G176)) -> 96950 | K176: =IF(H176="",0,N(D176)-N(H176)) -> -54505 | L176: 50400 | N176: 46800 | O176: =IF(AND(F176="",G176=""),0,J176-N(L176)-N(M176)-N(N176)) -> -250 | P176: =K176+O176 -> -54755 | Q176: =E176-P176 -> 3076155 | R176: 111 | S176: 64 | T176: =IF(N(S176)=0,"",Q176/S176) -> 48064.922 | U176: =IF(E176=0,"",IF(AND(N(C176)>0,F176="",G176=""),"Belum direalisasi",IF(AND(N(D176)>0,H176=""),"EDC belum settle",IF(ABS(O176)>50000,"Cek selisih tunai","OK")))) -> OK
A177: 46195 | B177: =MONTH(A177) -> 6 | C177: 759000 | D177: 1307550 | E177: =N(C177)+N(D177) -> 2066550 | F177: 200000 | G177: 422000 | H177: 1252550 | I177: =N(F177)+N(G177)+N(H177) -> 1874550 | J177: =IF(AND(F177="",G177=""),0,N(C177)-N(F177)-N(G177)) -> 137000 | K177: =IF(H177="",0,N(D177)-N(H177)) -> 55000 | N177: 136000 | O177: =IF(AND(F177="",G177=""),0,J177-N(L177)-N(M177)-N(N177)) -> 1000 | P177: =K177+O177 -> 56000 | Q177: =E177-P177 -> 2010550 | R177: 76 | S177: 41 | T177: =IF(N(S177)=0,"",Q177/S177) -> 49037.805 | U177: =IF(E177=0,"",IF(AND(N(C177)>0,F177="",G177=""),"Belum direalisasi",IF(AND(N(D177)>0,H177=""),"EDC belum settle",IF(ABS(O177)>50000,"Cek selisih tunai","OK")))) -> OK
A178: 46196 | B178: =MONTH(A178) -> 6 | C178: 671500 | D178: 1886300 | E178: =N(C178)+N(D178) -> 2557800 | F178: 235000 | G178: 436500 | H178: 1886300 | I178: =N(F178)+N(G178)+N(H178) -> 2557800 | J178: =IF(AND(F178="",G178=""),0,N(C178)-N(F178)-N(G178)) -> 0 | K178: =IF(H178="",0,N(D178)-N(H178)) -> 0 | O178: =IF(AND(F178="",G178=""),0,J178-N(L178)-N(M178)-N(N178)) -> 0 | P178: =K178+O178 -> 0 | Q178: =E178-P178 -> 2557800 | R178: 90 | S178: 48 | T178: =IF(N(S178)=0,"",Q178/S178) -> 53287.5 | U178: =IF(E178=0,"",IF(AND(N(C178)>0,F178="",G178=""),"Belum direalisasi",IF(AND(N(D178)>0,H178=""),"EDC belum settle",IF(ABS(O178)>50000,"Cek selisih tunai","OK")))) -> OK
...

Sheet JURNAL
A1: JURNAL TRANSAKSI
A2: Satu baris = satu transaksi (akun debet, akun kredit, nominal). Isi kolom A–I saja; kolom abu-abu adalah rumus bantu. Baris OTOMATIS/PENYESUAIAN jangan diubah.
A4: No. Bukti | B4: Tanggal | C4: Akun Debet | D4: Akun Kredit | E4: Nominal | F4: Keterangan | G4: Tag Event | H4: Sub Akun / Pihak | I4: Jenis | J4: Bln | K4: Thn | L4: Akun Lawan Kas | M4: Arus Kas (+/−) | N4: Baris AK | O4: Kel. Debet | P4: Kel. Kredit | Q4: BB# | R4: Cek
A5: JU-0001 | B5: 46023 | C5: Biaya Pemeliharaan | D5: Utang Usaha Jangka Panjang | E5: 1322000 | F5: Tagihan maintenance Kopi Parang dari FM Wood tahun 2025 | H5: FM Wood Maintenance | I5: UMUM | J5: =IF(B5="","",MONTH(B5)) -> 1 | K5: =IF(B5="","",YEAR(B5)) -> 2026 | L5: =IF(N(E5)=0,"",IF(COUNTIFS(AK_NAMA,C5,AK_KAT,"KAS")+COUNTIFS(AK_NAMA,D5,AK_KAT,"KAS")<>1,"",IF(COUNTIFS(AK_NAMA,C5,AK_KAT,"KAS")=1,D5,C5))) | M5: =IF(L5="",0,IF(L5=D5,E5,-E5)) -> 0 | N5: =IF(L5="","",IFERROR(INDEX(AK_BARIS,MATCH(L5,AK_NAMA,0)),"?")) | O5: =IF(C5="","",IFERROR(INDEX(AK_KEL,MATCH(C5,AK_NAMA,0)),"?")) -> BEBAN | P5: =IF(D5="","",IFERROR(INDEX(AK_KEL,MATCH(D5,AK_NAMA,0)),"?")) -> LIABILITAS | Q5: =N(Q4)+IF(AND(N(E5)<>0,K5=TAHUN,N(J5)<=BLN,OR(C5=BB_AKUN,D5=BB_AKUN)),1,0) -> 0 | R5: =IF(OR(C5&D5="",N(E5)=0),"",IF(OR(O5="?",P5="?"),"⚠ akun tidak dikenal",IF(C5=D5,"⚠ debet = kredit","")))
A6: JU-0002 | B6: 46024 | C6: Biaya Marketing & Promosi | D6: Kas Bank | E6: 5000000 | F6: Pembayaran promosi pengadaan acara gendut berlari acara tgl 11/01/26 | G6: Event Ragaria | I6: UMUM | J6: =IF(B6="","",MONTH(B6)) -> 1 | K6: =IF(B6="","",YEAR(B6)) -> 2026 | L6: =IF(N(E6)=0,"",IF(COUNTIFS(AK_NAMA,C6,AK_KAT,"KAS")+COUNTIFS(AK_NAMA,D6,AK_KAT,"KAS")<>1,"",IF(COUNTIFS(AK_NAMA,C6,AK_KAT,"KAS")=1,D6,C6))) -> Biaya Marketing & Promosi | M6: =IF(L6="",0,IF(L6=D6,E6,-E6)) -> -5000000 | N6: =IF(L6="","",IFERROR(INDEX(AK_BARIS,MATCH(L6,AK_NAMA,0)),"?")) -> OP6 | O6: =IF(C6="","",IFERROR(INDEX(AK_KEL,MATCH(C6,AK_NAMA,0)),"?")) -> BEBAN | P6: =IF(D6="","",IFERROR(INDEX(AK_KEL,MATCH(D6,AK_NAMA,0)),"?")) -> ASET | Q6: =N(Q5)+IF(AND(N(E6)<>0,K6=TAHUN,N(J6)<=BLN,OR(C6=BB_AKUN,D6=BB_AKUN)),1,0) -> 1 | R6: =IF(OR(C6&D6="",N(E6)=0),"",IF(OR(O6="?",P6="?"),"⚠ akun tidak dikenal",IF(C6=D6,"⚠ debet = kredit","")))
A7: JU-0003 | B7: 46024 | C7: Prive | D7: Kas Bank | E7: 2500000 | F7: Setoran kepada Owner Januari | I7: UMUM | J7: =IF(B7="","",MONTH(B7)) -> 1 | K7: =IF(B7="","",YEAR(B7)) -> 2026 | L7: =IF(N(E7)=0,"",IF(COUNTIFS(AK_NAMA,C7,AK_KAT,"KAS")+COUNTIFS(AK_NAMA,D7,AK_KAT,"KAS")<>1,"",IF(COUNTIFS(AK_NAMA,C7,AK_KAT,"KAS")=1,D7,C7))) -> Prive | M7: =IF(L7="",0,IF(L7=D7,E7,-E7)) -> -2500000 | N7: =IF(L7="","",IFERROR(INDEX(AK_BARIS,MATCH(L7,AK_NAMA,0)),"?")) -> FN1 | O7: =IF(C7="","",IFERROR(INDEX(AK_KEL,MATCH(C7,AK_NAMA,0)),"?")) -> EKUITAS | P7: =IF(D7="","",IFERROR(INDEX(AK_KEL,MATCH(D7,AK_NAMA,0)),"?")) -> ASET | Q7: =N(Q6)+IF(AND(N(E7)<>0,K7=TAHUN,N(J7)<=BLN,OR(C7=BB_AKUN,D7=BB_AKUN)),1,0) -> 2 | R7: =IF(OR(C7&D7="",N(E7)=0),"",IF(OR(O7="?",P7="?"),"⚠ akun tidak dikenal",IF(C7=D7,"⚠ debet = kredit","")))
A8: JU-0004 | B8: 46025 | C8: Dana Sosial & CSR | D8: Kas Bank | E8: 800000 | F8: Pembayaran nasi gudeg berkah 50box | I8: UMUM | J8: =IF(B8="","",MONTH(B8)) -> 1 | K8: =IF(B8="","",YEAR(B8)) -> 2026 | L8: =IF(N(E8)=0,"",IF(COUNTIFS(AK_NAMA,C8,AK_KAT,"KAS")+COUNTIFS(AK_NAMA,D8,AK_KAT,"KAS")<>1,"",IF(COUNTIFS(AK_NAMA,C8,AK_KAT,"KAS")=1,D8,C8))) -> Dana Sosial & CSR | M8: =IF(L8="",0,IF(L8=D8,E8,-E8)) -> -800000 | N8: =IF(L8="","",IFERROR(INDEX(AK_BARIS,MATCH(L8,AK_NAMA,0)),"?")) -> OP6 | O8: =IF(C8="","",IFERROR(INDEX(AK_KEL,MATCH(C8,AK_NAMA,0)),"?")) -> BEBAN | P8: =IF(D8="","",IFERROR(INDEX(AK_KEL,MATCH(D8,AK_NAMA,0)),"?")) -> ASET | Q8: =N(Q7)+IF(AND(N(E8)<>0,K8=TAHUN,N(J8)<=BLN,OR(C8=BB_AKUN,D8=BB_AKUN)),1,0) -> 3 | R8: =IF(OR(C8&D8="",N(E8)=0),"",IF(OR(O8="?",P8="?"),"⚠ akun tidak dikenal",IF(C8=D8,"⚠ debet = kredit","")))
A9: JU-0005 | B9: 46025 | C9: Biaya Bahan Baku | D9: Kas Bank | E9: 442000 | F9: Belanja tahu walik 50 pack dan ongkir | I9: UMUM | J9: =IF(B9="","",MONTH(B9)) -> 1 | K9: =IF(B9="","",YEAR(B9)) -> 2026 | L9: =IF(N(E9)=0,"",IF(COUNTIFS(AK_NAMA,C9,AK_KAT,"KAS")+COUNTIFS(AK_NAMA,D9,AK_KAT,"KAS")<>1,"",IF(COUNTIFS(AK_NAMA,C9,AK_KAT,"KAS")=1,D9,C9))) -> Biaya Bahan Baku | M9: =IF(L9="",0,IF(L9=D9,E9,-E9)) -> -442000 | N9: =IF(L9="","",IFERROR(INDEX(AK_BARIS,MATCH(L9,AK_NAMA,0)),"?")) -> OP3 | O9: =IF(C9="","",IFERROR(INDEX(AK_KEL,MATCH(C9,AK_NAMA,0)),"?")) -> BEBAN | P9: =IF(D9="","",IFERROR(INDEX(AK_KEL,MATCH(D9,AK_NAMA,0)),"?")) -> ASET | Q9: =N(Q8)+IF(AND(N(E9)<>0,K9=TAHUN,N(J9)<=BLN,OR(C9=BB_AKUN,D9=BB_AKUN)),1,0) -> 4 | R9: =IF(OR(C9&D9="",N(E9)=0),"",IF(OR(O9="?",P9="?"),"⚠ akun tidak dikenal",IF(C9=D9,"⚠ debet = kredit","")))
A10: JU-0006 | B10: 46025 | C10: Biaya Bahan Baku | D10: Kas Bank | E10: 494000 | F10: Belanja susu fresmilk gf 2 karton isi 24pcs | I10: UMUM | J10: =IF(B10="","",MONTH(B10)) -> 1 | K10: =IF(B10="","",YEAR(B10)) -> 2026 | L10: =IF(N(E10)=0,"",IF(COUNTIFS(AK_NAMA,C10,AK_KAT,"KAS")+COUNTIFS(AK_NAMA,D10,AK_KAT,"KAS")<>1,"",IF(COUNTIFS(AK_NAMA,C10,AK_KAT,"KAS")=1,D10,C10))) -> Biaya Bahan Baku | M10: =IF(L10="",0,IF(L10=D10,E10,-E10)) -> -494000 | N10: =IF(L10="","",IFERROR(INDEX(AK_BARIS,MATCH(L10,AK_NAMA,0)),"?")) -> OP3 | O10: =IF(C10="","",IFERROR(INDEX(AK_KEL,MATCH(C10,AK_NAMA,0)),"?")) -> BEBAN | P10: =IF(D10="","",IFERROR(INDEX(AK_KEL,MATCH(D10,AK_NAMA,0)),"?")) -> ASET | Q10: =N(Q9)+IF(AND(N(E10)<>0,K10=TAHUN,N(J10)<=BLN,OR(C10=BB_AKUN,D10=BB_AKUN)),1,0) -> 5 | R10: =IF(OR(C10&D10="",N(E10)=0),"",IF(OR(O10="?",P10="?"),"⚠ akun tidak dikenal",IF(C10=D10,"⚠ debet = kredit","")))
A11: JU-0007 | B11: 46026 | C11: Kas Bank | D11: Kas Tunai | E11: 1000000 | F11: Pindah dana Tunai - BCA | I11: UMUM | J11: =IF(B11="","",MONTH(B11)) -> 1 | K11: =IF(B11="","",YEAR(B11)) -> 2026 | L11: =IF(N(E11)=0,"",IF(COUNTIFS(AK_NAMA,C11,AK_KAT,"KAS")+COUNTIFS(AK_NAMA,D11,AK_KAT,"KAS")<>1,"",IF(COUNTIFS(AK_NAMA,C11,AK_KAT,"KAS")=1,D11,C11))) | M11: =IF(L11="",0,IF(L11=D11,E11,-E11)) -> 0 | N11: =IF(L11="","",IFERROR(INDEX(AK_BARIS,MATCH(L11,AK_NAMA,0)),"?")) | O11: =IF(C11="","",IFERROR(INDEX(AK_KEL,MATCH(C11,AK_NAMA,0)),"?")) -> ASET | P11: =IF(D11="","",IFERROR(INDEX(AK_KEL,MATCH(D11,AK_NAMA,0)),"?")) -> ASET | Q11: =N(Q10)+IF(AND(N(E11)<>0,K11=TAHUN,N(J11)<=BLN,OR(C11=BB_AKUN,D11=BB_AKUN)),1,0) -> 6 | R11: =IF(OR(C11&D11="",N(E11)=0),"",IF(OR(O11="?",P11="?"),"⚠ akun tidak dikenal",IF(C11=D11,"⚠ debet = kredit","")))
A12: JU-0008 | B12: 46026 | C12: Biaya Penyajian | D12: Kas Bank | E12: 190000 | F12: Belanja tutup strawless PET 1 box isi 1000pcs | I12: UMUM | J12: =IF(B12="","",MONTH(B12)) -> 1 | K12: =IF(B12="","",YEAR(B12)) -> 2026 | L12: =IF(N(E12)=0,"",IF(COUNTIFS(AK_NAMA,C12,AK_KAT,"KAS")+COUNTIFS(AK_NAMA,D12,AK_KAT,"KAS")<>1,"",IF(COUNTIFS(AK_NAMA,C12,AK_KAT,"KAS")=1,D12,C12))) -> Biaya Penyajian | M12: =IF(L12="",0,IF(L12=D12,E12,-E12)) -> -190000 | N12: =IF(L12="","",IFERROR(INDEX(AK_BARIS,MATCH(L12,AK_NAMA,0)),"?")) -> OP3 | O12: =IF(C12="","",IFERROR(INDEX(AK_KEL,MATCH(C12,AK_NAMA,0)),"?")) -> BEBAN | P12: =IF(D12="","",IFERROR(INDEX(AK_KEL,MATCH(D12,AK_NAMA,0)),"?")) -> ASET | Q12: =N(Q11)+IF(AND(N(E12)<>0,K12=TAHUN,N(J12)<=BLN,OR(C12=BB_AKUN,D12=BB_AKUN)),1,0) -> 7 | R12: =IF(OR(C12&D12="",N(E12)=0),"",IF(OR(O12="?",P12="?"),"⚠ akun tidak dikenal",IF(C12=D12,"⚠ debet = kredit","")))
A13: JU-0009 | B13: 46027 | C13: Biaya Bahan Baku | D13: Kas Bank | E13: 1496000 | F13: Pembayaran croissant buttersome batch 132-136 (25Des-4Jan) 67pcs | I13: UMUM | J13: =IF(B13="","",MONTH(B13)) -> 1 | K13: =IF(B13="","",YEAR(B13)) -> 2026 | L13: =IF(N(E13)=0,"",IF(COUNTIFS(AK_NAMA,C13,AK_KAT,"KAS")+COUNTIFS(AK_NAMA,D13,AK_KAT,"KAS")<>1,"",IF(COUNTIFS(AK_NAMA,C13,AK_KAT,"KAS")=1,D13,C13))) -> Biaya Bahan Baku | M13: =IF(L13="",0,IF(L13=D13,E13,-E13)) -> -1496000 | N13: =IF(L13="","",IFERROR(INDEX(AK_BARIS,MATCH(L13,AK_NAMA,0)),"?")) -> OP3 | O13: =IF(C13="","",IFERROR(INDEX(AK_KEL,MATCH(C13,AK_NAMA,0)),"?")) -> BEBAN | P13: =IF(D13="","",IFERROR(INDEX(AK_KEL,MATCH(D13,AK_NAMA,0)),"?")) -> ASET | Q13: =N(Q12)+IF(AND(N(E13)<>0,K13=TAHUN,N(J13)<=BLN,OR(C13=BB_AKUN,D13=BB_AKUN)),1,0) -> 8 | R13: =IF(OR(C13&D13="",N(E13)=0),"",IF(OR(O13="?",P13="?"),"⚠ akun tidak dikenal",IF(C13=D13,"⚠ debet = kredit","")))
A14: JU-0010 | B14: 46027 | C14: Biaya Marketing & Promosi | D14: Kas Bank | E14: 90000 | F14: Membayar jasa print cetak stiker untuk botol kombucha event Ragaria 128pcs | G14: Event Ragaria | I14: UMUM | J14: =IF(B14="","",MONTH(B14)) -> 1 | K14: =IF(B14="","",YEAR(B14)) -> 2026 | L14: =IF(N(E14)=0,"",IF(COUNTIFS(AK_NAMA,C14,AK_KAT,"KAS")+COUNTIFS(AK_NAMA,D14,AK_KAT,"KAS")<>1,"",IF(COUNTIFS(AK_NAMA,C14,AK_KAT,"KAS")=1,D14,C14))) -> Biaya Marketing & Promosi | M14: =IF(L14="",0,IF(L14=D14,E14,-E14)) -> -90000 | N14: =IF(L14="","",IFERROR(INDEX(AK_BARIS,MATCH(L14,AK_NAMA,0)),"?")) -> OP6 | O14: =IF(C14="","",IFERROR(INDEX(AK_KEL,MATCH(C14,AK_NAMA,0)),"?")) -> BEBAN | P14: =IF(D14="","",IFERROR(INDEX(AK_KEL,MATCH(D14,AK_NAMA,0)),"?")) -> ASET | Q14: =N(Q13)+IF(AND(N(E14)<>0,K14=TAHUN,N(J14)<=BLN,OR(C14=BB_AKUN,D14=BB_AKUN)),1,0) -> 9 | R14: =IF(OR(C14&D14="",N(E14)=0),"",IF(OR(O14="?",P14="?"),"⚠ akun tidak dikenal",IF(C14=D14,"⚠ debet = kredit","")))
A15: JU-0011 | B15: 46027 | C15: Biaya Operasional Harian | D15: Kas Warung | E15: 200000 | F15: Belanja untuk acara bakar2 akhir tahun (31/12/25) | I15: UMUM | J15: =IF(B15="","",MONTH(B15)) -> 1 | K15: =IF(B15="","",YEAR(B15)) -> 2026 | L15: =IF(N(E15)=0,"",IF(COUNTIFS(AK_NAMA,C15,AK_KAT,"KAS")+COUNTIFS(AK_NAMA,D15,AK_KAT,"KAS")<>1,"",IF(COUNTIFS(AK_NAMA,C15,AK_KAT,"KAS")=1,D15,C15))) -> Biaya Operasional Harian | M15: =IF(L15="",0,IF(L15=D15,E15,-E15)) -> -200000 | N15: =IF(L15="","",IFERROR(INDEX(AK_BARIS,MATCH(L15,AK_NAMA,0)),"?")) -> OP6 | O15: =IF(C15="","",IFERROR(INDEX(AK_KEL,MATCH(C15,AK_NAMA,0)),"?")) -> BEBAN | P15: =IF(D15="","",IFERROR(INDEX(AK_KEL,MATCH(D15,AK_NAMA,0)),"?")) -> ASET | Q15: =N(Q14)+IF(AND(N(E15)<>0,K15=TAHUN,N(J15)<=BLN,OR(C15=BB_AKUN,D15=BB_AKUN)),1,0) -> 9 | R15: =IF(OR(C15&D15="",N(E15)=0),"",IF(OR(O15="?",P15="?"),"⚠ akun tidak dikenal",IF(C15=D15,"⚠ debet = kredit","")))
A16: JU-0012 | B16: 46027 | C16: Biaya Bahan Baku | D16: Kas Warung | E16: 16000 | F16: Belanja es batu 3 pack (1/01) | I16: UMUM | J16: =IF(B16="","",MONTH(B16)) -> 1 | K16: =IF(B16="","",YEAR(B16)) -> 2026 | L16: =IF(N(E16)=0,"",IF(COUNTIFS(AK_NAMA,C16,AK_KAT,"KAS")+COUNTIFS(AK_NAMA,D16,AK_KAT,"KAS")<>1,"",IF(COUNTIFS(AK_NAMA,C16,AK_KAT,"KAS")=1,D16,C16))) -> Biaya Bahan Baku | M16: =IF(L16="",0,IF(L16=D16,E16,-E16)) -> -16000 | N16: =IF(L16="","",IFERROR(INDEX(AK_BARIS,MATCH(L16,AK_NAMA,0)),"?")) -> OP3 | O16: =IF(C16="","",IFERROR(INDEX(AK_KEL,MATCH(C16,AK_NAMA,0)),"?")) -> BEBAN | P16: =IF(D16="","",IFERROR(INDEX(AK_KEL,MATCH(D16,AK_NAMA,0)),"?")) -> ASET | Q16: =N(Q15)+IF(AND(N(E16)<>0,K16=TAHUN,N(J16)<=BLN,OR(C16=BB_AKUN,D16=BB_AKUN)),1,0) -> 9 | R16: =IF(OR(C16&D16="",N(E16)=0),"",IF(OR(O16="?",P16="?"),"⚠ akun tidak dikenal",IF(C16=D16,"⚠ debet = kredit","")))
A17: JU-0013 | B17: 46027 | C17: Biaya Bahan Baku | D17: Kas Warung | E17: 22000 | F17: Belanja gas lpg 3kg (1/01) | I17: UMUM | J17: =IF(B17="","",MONTH(B17)) -> 1 | K17: =IF(B17="","",YEAR(B17)) -> 2026 | L17: =IF(N(E17)=0,"",IF(COUNTIFS(AK_NAMA,C17,AK_KAT,"KAS")+COUNTIFS(AK_NAMA,D17,AK_KAT,"KAS")<>1,"",IF(COUNTIFS(AK_NAMA,C17,AK_KAT,"KAS")=1,D17,C17))) -> Biaya Bahan Baku | M17: =IF(L17="",0,IF(L17=D17,E17,-E17)) -> -22000 | N17: =IF(L17="","",IFERROR(INDEX(AK_BARIS,MATCH(L17,AK_NAMA,0)),"?")) -> OP3 | O17: =IF(C17="","",IFERROR(INDEX(AK_KEL,MATCH(C17,AK_NAMA,0)),"?")) -> BEBAN | P17: =IF(D17="","",IFERROR(INDEX(AK_KEL,MATCH(D17,AK_NAMA,0)),"?")) -> ASET | Q17: =N(Q16)+IF(AND(N(E17)<>0,K17=TAHUN,N(J17)<=BLN,OR(C17=BB_AKUN,D17=BB_AKUN)),1,0) -> 9 | R17: =IF(OR(C17&D17="",N(E17)=0),"",IF(OR(O17="?",P17="?"),"⚠ akun tidak dikenal",IF(C17=D17,"⚠ debet = kredit","")))
A18: JU-0014 | B18: 46027 | C18: Biaya Operasional Harian | D18: Kas Warung | E18: 10000 | F18: Belanja sunlight 2 pack (1/01) | I18: UMUM | J18: =IF(B18="","",MONTH(B18)) -> 1 | K18: =IF(B18="","",YEAR(B18)) -> 2026 | L18: =IF(N(E18)=0,"",IF(COUNTIFS(AK_NAMA,C18,AK_KAT,"KAS")+COUNTIFS(AK_NAMA,D18,AK_KAT,"KAS")<>1,"",IF(COUNTIFS(AK_NAMA,C18,AK_KAT,"KAS")=1,D18,C18))) -> Biaya Operasional Harian | M18: =IF(L18="",0,IF(L18=D18,E18,-E18)) -> -10000 | N18: =IF(L18="","",IFERROR(INDEX(AK_BARIS,MATCH(L18,AK_NAMA,0)),"?")) -> OP6 | O18: =IF(C18="","",IFERROR(INDEX(AK_KEL,MATCH(C18,AK_NAMA,0)),"?")) -> BEBAN | P18: =IF(D18="","",IFERROR(INDEX(AK_KEL,MATCH(D18,AK_NAMA,0)),"?")) -> ASET | Q18: =N(Q17)+IF(AND(N(E18)<>0,K18=TAHUN,N(J18)<=BLN,OR(C18=BB_AKUN,D18=BB_AKUN)),1,0) -> 9 | R18: =IF(OR(C18&D18="",N(E18)=0),"",IF(OR(O18="?",P18="?"),"⚠ akun tidak dikenal",IF(C18=D18,"⚠ debet = kredit","")))
A19: JU-0015 | B19: 46027 | C19: Biaya Bahan Baku | D19: Kas Warung | E19: 30000 | F19: Belanja es batu 3 pack (2/01) | I19: UMUM | J19: =IF(B19="","",MONTH(B19)) -> 1 | K19: =IF(B19="","",YEAR(B19)) -> 2026 | L19: =IF(N(E19)=0,"",IF(COUNTIFS(AK_NAMA,C19,AK_KAT,"KAS")+COUNTIFS(AK_NAMA,D19,AK_KAT,"KAS")<>1,"",IF(COUNTIFS(AK_NAMA,C19,AK_KAT,"KAS")=1,D19,C19))) -> Biaya Bahan Baku | M19: =IF(L19="",0,IF(L19=D19,E19,-E19)) -> -30000 | N19: =IF(L19="","",IFERROR(INDEX(AK_BARIS,MATCH(L19,AK_NAMA,0)),"?")) -> OP3 | O19: =IF(C19="","",IFERROR(INDEX(AK_KEL,MATCH(C19,AK_NAMA,0)),"?")) -> BEBAN | P19: =IF(D19="","",IFERROR(INDEX(AK_KEL,MATCH(D19,AK_NAMA,0)),"?")) -> ASET | Q19: =N(Q18)+IF(AND(N(E19)<>0,K19=TAHUN,N(J19)<=BLN,OR(C19=BB_AKUN,D19=BB_AKUN)),1,0) -> 9 | R19: =IF(OR(C19&D19="",N(E19)=0),"",IF(OR(O19="?",P19="?"),"⚠ akun tidak dikenal",IF(C19=D19,"⚠ debet = kredit","")))
A20: JU-0016 | B20: 46027 | C20: Biaya Marketing & Promosi | D20: Kas Warung | E20: 57500 | F20: Membayar jasa print cetak pamflet untuk sponsorship event Maharia tgl 16 (3/01) | G20: Event Maharia | I20: UMUM | J20: =IF(B20="","",MONTH(B20)) -> 1 | K20: =IF(B20="","",YEAR(B20)) -> 2026 | L20: =IF(N(E20)=0,"",IF(COUNTIFS(AK_NAMA,C20,AK_KAT,"KAS")+COUNTIFS(AK_NAMA,D20,AK_KAT,"KAS")<>1,"",IF(COUNTIFS(AK_NAMA,C20,AK_KAT,"KAS")=1,D20,C20))) -> Biaya Marketing & Promosi | M20: =IF(L20="",0,IF(L20=D20,E20,-E20)) -> -57500 | N20: =IF(L20="","",IFERROR(INDEX(AK_BARIS,MATCH(L20,AK_NAMA,0)),"?")) -> OP6 | O20: =IF(C20="","",IFERROR(INDEX(AK_KEL,MATCH(C20,AK_NAMA,0)),"?")) -> BEBAN | P20: =IF(D20="","",IFERROR(INDEX(AK_KEL,MATCH(D20,AK_NAMA,0)),"?")) -> ASET | Q20: =N(Q19)+IF(AND(N(E20)<>0,K20=TAHUN,N(J20)<=BLN,OR(C20=BB_AKUN,D20=BB_AKUN)),1,0) -> 9 | R20: =IF(OR(C20&D20="",N(E20)=0),"",IF(OR(O20="?",P20="?"),"⚠ akun tidak dikenal",IF(C20=D20,"⚠ debet = kredit","")))
A21: JU-0017 | B21: 46027 | C21: Biaya Bahan Baku | D21: Kas Warung | E21: 30000 | F21: Belanja es batu 3 pack (3/01) | I21: UMUM | J21: =IF(B21="","",MONTH(B21)) -> 1 | K21: =IF(B21="","",YEAR(B21)) -> 2026 | L21: =IF(N(E21)=0,"",IF(COUNTIFS(AK_NAMA,C21,AK_KAT,"KAS")+COUNTIFS(AK_NAMA,D21,AK_KAT,"KAS")<>1,"",IF(COUNTIFS(AK_NAMA,C21,AK_KAT,"KAS")=1,D21,C21))) -> Biaya Bahan Baku | M21: =IF(L21="",0,IF(L21=D21,E21,-E21)) -> -30000 | N21: =IF(L21="","",IFERROR(INDEX(AK_BARIS,MATCH(L21,AK_NAMA,0)),"?")) -> OP3 | O21: =IF(C21="","",IFERROR(INDEX(AK_KEL,MATCH(C21,AK_NAMA,0)),"?")) -> BEBAN | P21: =IF(D21="","",IFERROR(INDEX(AK_KEL,MATCH(D21,AK_NAMA,0)),"?")) -> ASET | Q21: =N(Q20)+IF(AND(N(E21)<>0,K21=TAHUN,N(J21)<=BLN,OR(C21=BB_AKUN,D21=BB_AKUN)),1,0) -> 9 | R21: =IF(OR(C21&D21="",N(E21)=0),"",IF(OR(O21="?",P21="?"),"⚠ akun tidak dikenal",IF(C21=D21,"⚠ debet = kredit","")))
A22: JU-0018 | B22: 46027 | C22: Biaya Bahan Baku | D22: Kas Warung | E22: 36000 | F22: Belanja es batu 4 pack (5/01) | I22: UMUM | J22: =IF(B22="","",MONTH(B22)) -> 1 | K22: =IF(B22="","",YEAR(B22)) -> 2026 | L22: =IF(N(E22)=0,"",IF(COUNTIFS(AK_NAMA,C22,AK_KAT,"KAS")+COUNTIFS(AK_NAMA,D22,AK_KAT,"KAS")<>1,"",IF(COUNTIFS(AK_NAMA,C22,AK_KAT,"KAS")=1,D22,C22))) -> Biaya Bahan Baku | M22: =IF(L22="",0,IF(L22=D22,E22,-E22)) -> -36000 | N22: =IF(L22="","",IFERROR(INDEX(AK_BARIS,MATCH(L22,AK_NAMA,0)),"?")) -> OP3 | O22: =IF(C22="","",IFERROR(INDEX(AK_KEL,MATCH(C22,AK_NAMA,0)),"?")) -> BEBAN | P22: =IF(D22="","",IFERROR(INDEX(AK_KEL,MATCH(D22,AK_NAMA,0)),"?")) -> ASET | Q22: =N(Q21)+IF(AND(N(E22)<>0,K22=TAHUN,N(J22)<=BLN,OR(C22=BB_AKUN,D22=BB_AKUN)),1,0) -> 9 | R22: =IF(OR(C22&D22="",N(E22)=0),"",IF(OR(O22="?",P22="?"),"⚠ akun tidak dikenal",IF(C22=D22,"⚠ debet = kredit","")))
A23: JU-0019 | B23: 46027 | C23: Biaya Operasional Harian | D23: Kas Warung | E23: 22000 | F23: Membayar bensin untuk belanja (5/01) | I23: UMUM | J23: =IF(B23="","",MONTH(B23)) -> 1 | K23: =IF(B23="","",YEAR(B23)) -> 2026 | L23: =IF(N(E23)=0,"",IF(COUNTIFS(AK_NAMA,C23,AK_KAT,"KAS")+COUNTIFS(AK_NAMA,D23,AK_KAT,"KAS")<>1,"",IF(COUNTIFS(AK_NAMA,C23,AK_KAT,"KAS")=1,D23,C23))) -> Biaya Operasional Harian | M23: =IF(L23="",0,IF(L23=D23,E23,-E23)) -> -22000 | N23: =IF(L23="","",IFERROR(INDEX(AK_BARIS,MATCH(L23,AK_NAMA,0)),"?")) -> OP6 | O23: =IF(C23="","",IFERROR(INDEX(AK_KEL,MATCH(C23,AK_NAMA,0)),"?")) -> BEBAN | P23: =IF(D23="","",IFERROR(INDEX(AK_KEL,MATCH(D23,AK_NAMA,0)),"?")) -> ASET | Q23: =N(Q22)+IF(AND(N(E23)<>0,K23=TAHUN,N(J23)<=BLN,OR(C23=BB_AKUN,D23=BB_AKUN)),1,0) -> 9 | R23: =IF(OR(C23&D23="",N(E23)=0),"",IF(OR(O23="?",P23="?"),"⚠ akun tidak dikenal",IF(C23=D23,"⚠ debet = kredit","")))
A24: JU-0020 | B24: 46027 | C24: Kas Warung | D24: Kas Tunai | E24: 1000000 | F24: Pindah dana tunai ke kas warung (keperluan darurat dan evt ragaria tgl 11) | I24: UMUM | J24: =IF(B24="","",MONTH(B24)) -> 1 | K24: =IF(B24="","",YEAR(B24)) -> 2026 | L24: =IF(N(E24)=0,"",IF(COUNTIFS(AK_NAMA,C24,AK_KAT,"KAS")+COUNTIFS(AK_NAMA,D24,AK_KAT,"KAS")<>1,"",IF(COUNTIFS(AK_NAMA,C24,AK_KAT,"KAS")=1,D24,C24))) | M24: =IF(L24="",0,IF(L24=D24,E24,-E24)) -> 0 | N24: =IF(L24="","",IFERROR(INDEX(AK_BARIS,MATCH(L24,AK_NAMA,0)),"?")) | O24: =IF(C24="","",IFERROR(INDEX(AK_KEL,MATCH(C24,AK_NAMA,0)),"?")) -> ASET | P24: =IF(D24="","",IFERROR(INDEX(AK_KEL,MATCH(D24,AK_NAMA,0)),"?")) -> ASET | Q24: =N(Q23)+IF(AND(N(E24)<>0,K24=TAHUN,N(J24)<=BLN,OR(C24=BB_AKUN,D24=BB_AKUN)),1,0) -> 9 | R24: =IF(OR(C24&D24="",N(E24)=0),"",IF(OR(O24="?",P24="?"),"⚠ akun tidak dikenal",IF(C24=D24,"⚠ debet = kredit","")))
A25: JU-0021 | B25: 46027 | C25: Kas Tunai | D25: Kas Warung | E25: 86000 | F25: Pindah dana kas warung ke tunai (kembalian lebih 9.5k sdg ditukar di laporan berikutnya) | I25: UMUM | J25: =IF(B25="","",MONTH(B25)) -> 1 | K25: =IF(B25="","",YEAR(B25)) -> 2026 | L25: =IF(N(E25)=0,"",IF(COUNTIFS(AK_NAMA,C25,AK_KAT,"KAS")+COUNTIFS(AK_NAMA,D25,AK_KAT,"KAS")<>1,"",IF(COUNTIFS(AK_NAMA,C25,AK_KAT,"KAS")=1,D25,C25))) | M25: =IF(L25="",0,IF(L25=D25,E25,-E25)) -> 0 | N25: =IF(L25="","",IFERROR(INDEX(AK_BARIS,MATCH(L25,AK_NAMA,0)),"?")) | O25: =IF(C25="","",IFERROR(INDEX(AK_KEL,MATCH(C25,AK_NAMA,0)),"?")) -> ASET | P25: =IF(D25="","",IFERROR(INDEX(AK_KEL,MATCH(D25,AK_NAMA,0)),"?")) -> ASET | Q25: =N(Q24)+IF(AND(N(E25)<>0,K25=TAHUN,N(J25)<=BLN,OR(C25=BB_AKUN,D25=BB_AKUN)),1,0) -> 9 | R25: =IF(OR(C25&D25="",N(E25)=0),"",IF(OR(O25="?",P25="?"),"⚠ akun tidak dikenal",IF(C25=D25,"⚠ debet = kredit","")))
A26: JU-0022 | B26: 46028 | C26: Kas Bank | D26: Pendapatan non Cafe | E26: 540000 | F26: Pemasukan penjualan tiket 06/01 event Maharia tgl 16/01 | G26: Event Maharia | I26: UMUM | J26: =IF(B26="","",MONTH(B26)) -> 1 | K26: =IF(B26="","",YEAR(B26)) -> 2026 | L26: =IF(N(E26)=0,"",IF(COUNTIFS(AK_NAMA,C26,AK_KAT,"KAS")+COUNTIFS(AK_NAMA,D26,AK_KAT,"KAS")<>1,"",IF(COUNTIFS(AK_NAMA,C26,AK_KAT,"KAS")=1,D26,C26))) -> Pendapatan non Cafe | M26: =IF(L26="",0,IF(L26=D26,E26,-E26)) -> 540000 | N26: =IF(L26="","",IFERROR(INDEX(AK_BARIS,MATCH(L26,AK_NAMA,0)),"?")) -> OP1 | O26: =IF(C26="","",IFERROR(INDEX(AK_KEL,MATCH(C26,AK_NAMA,0)),"?")) -> ASET | P26: =IF(D26="","",IFERROR(INDEX(AK_KEL,MATCH(D26,AK_NAMA,0)),"?")) -> PENDAPATAN | Q26: =N(Q25)+IF(AND(N(E26)<>0,K26=TAHUN,N(J26)<=BLN,OR(C26=BB_AKUN,D26=BB_AKUN)),1,0) -> 10 | R26: =IF(OR(C26&D26="",N(E26)=0),"",IF(OR(O26="?",P26="?"),"⚠ akun tidak dikenal",IF(C26=D26,"⚠ debet = kredit","")))
A27: JU-0023 | B27: 46028 | C27: Biaya Bahan Baku | D27: Kas Bank | E27: 521000 | F27: Pembayaran bagel buttersome batch 4-5 41pcs | I27: UMUM | J27: =IF(B27="","",MONTH(B27)) -> 1 | K27: =IF(B27="","",YEAR(B27)) -> 2026 | L27: =IF(N(E27)=0,"",IF(COUNTIFS(AK_NAMA,C27,AK_KAT,"KAS")+COUNTIFS(AK_NAMA,D27,AK_KAT,"KAS")<>1,"",IF(COUNTIFS(AK_NAMA,C27,AK_KAT,"KAS")=1,D27,C27))) -> Biaya Bahan Baku | M27: =IF(L27="",0,IF(L27=D27,E27,-E27)) -> -521000 | N27: =IF(L27="","",IFERROR(INDEX(AK_BARIS,MATCH(L27,AK_NAMA,0)),"?")) -> OP3 | O27: =IF(C27="","",IFERROR(INDEX(AK_KEL,MATCH(C27,AK_NAMA,0)),"?")) -> BEBAN | P27: =IF(D27="","",IFERROR(INDEX(AK_KEL,MATCH(D27,AK_NAMA,0)),"?")) -> ASET | Q27: =N(Q26)+IF(AND(N(E27)<>0,K27=TAHUN,N(J27)<=BLN,OR(C27=BB_AKUN,D27=BB_AKUN)),1,0) -> 11 | R27: =IF(OR(C27&D27="",N(E27)=0),"",IF(OR(O27="?",P27="?"),"⚠ akun tidak dikenal",IF(C27=D27,"⚠ debet = kredit","")))
A28: JU-0024 | B28: 46028 | C28: Biaya Operasional Harian | D28: Kas Bank | E28: 90000 | F28: Belanja sabun cuci piring soume premium 5L x2 | I28: UMUM | J28: =IF(B28="","",MONTH(B28)) -> 1 | K28: =IF(B28="","",YEAR(B28)) -> 2026 | L28: =IF(N(E28)=0,"",IF(COUNTIFS(AK_NAMA,C28,AK_KAT,"KAS")+COUNTIFS(AK_NAMA,D28,AK_KAT,"KAS")<>1,"",IF(COUNTIFS(AK_NAMA,C28,AK_KAT,"KAS")=1,D28,C28))) -> Biaya Operasional Harian | M28: =IF(L28="",0,IF(L28=D28,E28,-E28)) -> -90000 | N28: =IF(L28="","",IFERROR(INDEX(AK_BARIS,MATCH(L28,AK_NAMA,0)),"?")) -> OP6 | O28: =IF(C28="","",IFERROR(INDEX(AK_KEL,MATCH(C28,AK_NAMA,0)),"?")) -> BEBAN | P28: =IF(D28="","",IFERROR(INDEX(AK_KEL,MATCH(D28,AK_NAMA,0)),"?")) -> ASET | Q28: =N(Q27)+IF(AND(N(E28)<>0,K28=TAHUN,N(J28)<=BLN,OR(C28=BB_AKUN,D28=BB_AKUN)),1,0) -> 12 | R28: =IF(OR(C28&D28="",N(E28)=0),"",IF(OR(O28="?",P28="?"),"⚠ akun tidak dikenal",IF(C28=D28,"⚠ debet = kredit","")))
A29: JU-0025 | B29: 46028 | C29: Biaya Marketing & Promosi | D29: Kas Bank | E29: 50000 | F29: Membayar iklan di tik tok | I29: UMUM | J29: =IF(B29="","",MONTH(B29)) -> 1 | K29: =IF(B29="","",YEAR(B29)) -> 2026 | L29: =IF(N(E29)=0,"",IF(COUNTIFS(AK_NAMA,C29,AK_KAT,"KAS")+COUNTIFS(AK_NAMA,D29,AK_KAT,"KAS")<>1,"",IF(COUNTIFS(AK_NAMA,C29,AK_KAT,"KAS")=1,D29,C29))) -> Biaya Marketing & Promosi | M29: =IF(L29="",0,IF(L29=D29,E29,-E29)) -> -50000 | N29: =IF(L29="","",IFERROR(INDEX(AK_BARIS,MATCH(L29,AK_NAMA,0)),"?")) -> OP6 | O29: =IF(C29="","",IFERROR(INDEX(AK_KEL,MATCH(C29,AK_NAMA,0)),"?")) -> BEBAN | P29: =IF(D29="","",IFERROR(INDEX(AK_KEL,MATCH(D29,AK_NAMA,0)),"?")) -> ASET | Q29: =N(Q28)+IF(AND(N(E29)<>0,K29=TAHUN,N(J29)<=BLN,OR(C29=BB_AKUN,D29=BB_AKUN)),1,0) -> 13 | R29: =IF(OR(C29&D29="",N(E29)=0),"",IF(OR(O29="?",P29="?"),"⚠ akun tidak dikenal",IF(C29=D29,"⚠ debet = kredit","")))
A30: JU-0026 | B30: 46029 | C30: Biaya Marketing & Promosi | D30: Kas Bank | E30: 4000000 | F30: Membayar DP Soloensis live performance at Maharia | G30: Event Maharia | I30: UMUM | J30: =IF(B30="","",MONTH(B30)) -> 1 | K30: =IF(B30="","",YEAR(B30)) -> 2026 | L30: =IF(N(E30)=0,"",IF(COUNTIFS(AK_NAMA,C30,AK_KAT,"KAS")+COUNTIFS(AK_NAMA,D30,AK_KAT,"KAS")<>1,"",IF(COUNTIFS(AK_NAMA,C30,AK_KAT,"KAS")=1,D30,C30))) -> Biaya Marketing & Promosi | M30: =IF(L30="",0,IF(L30=D30,E30,-E30)) -> -4000000 | N30: =IF(L30="","",IFERROR(INDEX(AK_BARIS,MATCH(L30,AK_NAMA,0)),"?")) -> OP6 | O30: =IF(C30="","",IFERROR(INDEX(AK_KEL,MATCH(C30,AK_NAMA,0)),"?")) -> BEBAN | P30: =IF(D30="","",IFERROR(INDEX(AK_KEL,MATCH(D30,AK_NAMA,0)),"?")) -> ASET | Q30: =N(Q29)+IF(AND(N(E30)<>0,K30=TAHUN,N(J30)<=BLN,OR(C30=BB_AKUN,D30=BB_AKUN)),1,0) -> 14 | R30: =IF(OR(C30&D30="",N(E30)=0),"",IF(OR(O30="?",P30="?"),"⚠ akun tidak dikenal",IF(C30=D30,"⚠ debet = kredit","")))
A31: JU-0027 | B31: 46029 | C31: Biaya Marketing & Promosi | D31: Kas Bank | E31: 13400000 | F31: Membayar DP orchestra vendor dan sound untuk event Maharia | G31: Event Maharia | I31: UMUM | J31: =IF(B31="","",MONTH(B31)) -> 1 | K31: =IF(B31="","",YEAR(B31)) -> 2026 | L31: =IF(N(E31)=0,"",IF(COUNTIFS(AK_NAMA,C31,AK_KAT,"KAS")+COUNTIFS(AK_NAMA,D31,AK_KAT,"KAS")<>1,"",IF(COUNTIFS(AK_NAMA,C31,AK_KAT,"KAS")=1,D31,C31))) -> Biaya Marketing & Promosi | M31: =IF(L31="",0,IF(L31=D31,E31,-E31)) -> -13400000 | N31: =IF(L31="","",IFERROR(INDEX(AK_BARIS,MATCH(L31,AK_NAMA,0)),"?")) -> OP6 | O31: =IF(C31="","",IFERROR(INDEX(AK_KEL,MATCH(C31,AK_NAMA,0)),"?")) -> BEBAN | P31: =IF(D31="","",IFERROR(INDEX(AK_KEL,MATCH(D31,AK_NAMA,0)),"?")) -> ASET | Q31: =N(Q30)+IF(AND(N(E31)<>0,K31=TAHUN,N(J31)<=BLN,OR(C31=BB_AKUN,D31=BB_AKUN)),1,0) -> 15 | R31: =IF(OR(C31&D31="",N(E31)=0),"",IF(OR(O31="?",P31="?"),"⚠ akun tidak dikenal",IF(C31=D31,"⚠ debet = kredit","")))
A32: JU-0028 | B32: 46029 | C32: Biaya Bahan Baku | D32: Kas Bank | E32: 500000 | F32: Belanja biji kopi yantos kerinci natural 200gr x4 pack | I32: UMUM | J32: =IF(B32="","",MONTH(B32)) -> 1 | K32: =IF(B32="","",YEAR(B32)) -> 2026 | L32: =IF(N(E32)=0,"",IF(COUNTIFS(AK_NAMA,C32,AK_KAT,"KAS")+COUNTIFS(AK_NAMA,D32,AK_KAT,"KAS")<>1,"",IF(COUNTIFS(AK_NAMA,C32,AK_KAT,"KAS")=1,D32,C32))) -> Biaya Bahan Baku | M32: =IF(L32="",0,IF(L32=D32,E32,-E32)) -> -500000 | N32: =IF(L32="","",IFERROR(INDEX(AK_BARIS,MATCH(L32,AK_NAMA,0)),"?")) -> OP3 | O32: =IF(C32="","",IFERROR(INDEX(AK_KEL,MATCH(C32,AK_NAMA,0)),"?")) -> BEBAN | P32: =IF(D32="","",IFERROR(INDEX(AK_KEL,MATCH(D32,AK_NAMA,0)),"?")) -> ASET | Q32: =N(Q31)+IF(AND(N(E32)<>0,K32=TAHUN,N(J32)<=BLN,OR(C32=BB_AKUN,D32=BB_AKUN)),1,0) -> 16 | R32: =IF(OR(C32&D32="",N(E32)=0),"",IF(OR(O32="?",P32="?"),"⚠ akun tidak dikenal",IF(C32=D32,"⚠ debet = kredit","")))
A33: JU-0029 | B33: 46029 | C33: Biaya Lainnya | D33: Kas Bank | E33: 358 | F33: Biaya transfer flip | I33: UMUM | J33: =IF(B33="","",MONTH(B33)) -> 1 | K33: =IF(B33="","",YEAR(B33)) -> 2026 | L33: =IF(N(E33)=0,"",IF(COUNTIFS(AK_NAMA,C33,AK_KAT,"KAS")+COUNTIFS(AK_NAMA,D33,AK_KAT,"KAS")<>1,"",IF(COUNTIFS(AK_NAMA,C33,AK_KAT,"KAS")=1,D33,C33))) -> Biaya Lainnya | M33: =IF(L33="",0,IF(L33=D33,E33,-E33)) -> -358 | N33: =IF(L33="","",IFERROR(INDEX(AK_BARIS,MATCH(L33,AK_NAMA,0)),"?")) -> OP2 | O33: =IF(C33="","",IFERROR(INDEX(AK_KEL,MATCH(C33,AK_NAMA,0)),"?")) -> BEBAN | P33: =IF(D33="","",IFERROR(INDEX(AK_KEL,MATCH(D33,AK_NAMA,0)),"?")) -> ASET | Q33: =N(Q32)+IF(AND(N(E33)<>0,K33=TAHUN,N(J33)<=BLN,OR(C33=BB_AKUN,D33=BB_AKUN)),1,0) -> 17 | R33: =IF(OR(C33&D33="",N(E33)=0),"",IF(OR(O33="?",P33="?"),"⚠ akun tidak dikenal",IF(C33=D33,"⚠ debet = kredit","")))
A34: JU-0030 | B34: 46029 | C34: Biaya Marketing & Promosi | D34: Kas Bank | E34: 233100 | F34: Membayar hosting website langganan 1 tahun | I34: UMUM | J34: =IF(B34="","",MONTH(B34)) -> 1 | K34: =IF(B34="","",YEAR(B34)) -> 2026 | L34: =IF(N(E34)=0,"",IF(COUNTIFS(AK_NAMA,C34,AK_KAT,"KAS")+COUNTIFS(AK_NAMA,D34,AK_KAT,"KAS")<>1,"",IF(COUNTIFS(AK_NAMA,C34,AK_KAT,"KAS")=1,D34,C34))) -> Biaya Marketing & Promosi | M34: =IF(L34="",0,IF(L34=D34,E34,-E34)) -> -233100 | N34: =IF(L34="","",IFERROR(INDEX(AK_BARIS,MATCH(L34,AK_NAMA,0)),"?")) -> OP6 | O34: =IF(C34="","",IFERROR(INDEX(AK_KEL,MATCH(C34,AK_NAMA,0)),"?")) -> BEBAN | P34: =IF(D34="","",IFERROR(INDEX(AK_KEL,MATCH(D34,AK_NAMA,0)),"?")) -> ASET | Q34: =N(Q33)+IF(AND(N(E34)<>0,K34=TAHUN,N(J34)<=BLN,OR(C34=BB_AKUN,D34=BB_AKUN)),1,0) -> 18 | R34: =IF(OR(C34&D34="",N(E34)=0),"",IF(OR(O34="?",P34="?"),"⚠ akun tidak dikenal",IF(C34=D34,"⚠ debet = kredit","")))
A35: JU-0031 | B35: 46029 | C35: Biaya Lainnya | D35: Kas Bank | E35: 325 | F35: Biaya transfer flip | I35: UMUM | J35: =IF(B35="","",MONTH(B35)) -> 1 | K35: =IF(B35="","",YEAR(B35)) -> 2026 | L35: =IF(N(E35)=0,"",IF(COUNTIFS(AK_NAMA,C35,AK_KAT,"KAS")+COUNTIFS(AK_NAMA,D35,AK_KAT,"KAS")<>1,"",IF(COUNTIFS(AK_NAMA,C35,AK_KAT,"KAS")=1,D35,C35))) -> Biaya Lainnya | M35: =IF(L35="",0,IF(L35=D35,E35,-E35)) -> -325 | N35: =IF(L35="","",IFERROR(INDEX(AK_BARIS,MATCH(L35,AK_NAMA,0)),"?")) -> OP2 | O35: =IF(C35="","",IFERROR(INDEX(AK_KEL,MATCH(C35,AK_NAMA,0)),"?")) -> BEBAN | P35: =IF(D35="","",IFERROR(INDEX(AK_KEL,MATCH(D35,AK_NAMA,0)),"?")) -> ASET | Q35: =N(Q34)+IF(AND(N(E35)<>0,K35=TAHUN,N(J35)<=BLN,OR(C35=BB_AKUN,D35=BB_AKUN)),1,0) -> 19 | R35: =IF(OR(C35&D35="",N(E35)=0),"",IF(OR(O35="?",P35="?"),"⚠ akun tidak dikenal",IF(C35=D35,"⚠ debet = kredit","")))
A36: JU-0032 | B36: 46029 | C36: Kas Bank | D36: Pendapatan non Cafe | E36: 940000 | F36: Pemasukan penjualan tiket 07/01 event Maharia tgl 16/01 | G36: Event Maharia | I36: UMUM | J36: =IF(B36="","",MONTH(B36)) -> 1 | K36: =IF(B36="","",YEAR(B36)) -> 2026 | L36: =IF(N(E36)=0,"",IF(COUNTIFS(AK_NAMA,C36,AK_KAT,"KAS")+COUNTIFS(AK_NAMA,D36,AK_KAT,"KAS")<>1,"",IF(COUNTIFS(AK_NAMA,C36,AK_KAT,"KAS")=1,D36,C36))) -> Pendapatan non Cafe | M36: =IF(L36="",0,IF(L36=D36,E36,-E36)) -> 940000 | N36: =IF(L36="","",IFERROR(INDEX(AK_BARIS,MATCH(L36,AK_NAMA,0)),"?")) -> OP1 | O36: =IF(C36="","",IFERROR(INDEX(AK_KEL,MATCH(C36,AK_NAMA,0)),"?")) -> ASET | P36: =IF(D36="","",IFERROR(INDEX(AK_KEL,MATCH(D36,AK_NAMA,0)),"?")) -> PENDAPATAN | Q36: =N(Q35)+IF(AND(N(E36)<>0,K36=TAHUN,N(J36)<=BLN,OR(C36=BB_AKUN,D36=BB_AKUN)),1,0) -> 20 | R36: =IF(OR(C36&D36="",N(E36)=0),"",IF(OR(O36="?",P36="?"),"⚠ akun tidak dikenal",IF(C36=D36,"⚠ debet = kredit","")))
A37: JU-0033 | B37: 46030 | C37: Biaya Bahan Baku | D37: Kas Bank | E37: 180000 | F37: Belanja isi ulang galon unlock water x10 galon | I37: UMUM | J37: =IF(B37="","",MONTH(B37)) -> 1 | K37: =IF(B37="","",YEAR(B37)) -> 2026 | L37: =IF(N(E37)=0,"",IF(COUNTIFS(AK_NAMA,C37,AK_KAT,"KAS")+COUNTIFS(AK_NAMA,D37,AK_KAT,"KAS")<>1,"",IF(COUNTIFS(AK_NAMA,C37,AK_KAT,"KAS")=1,D37,C37))) -> Biaya Bahan Baku | M37: =IF(L37="",0,IF(L37=D37,E37,-E37)) -> -180000 | N37: =IF(L37="","",IFERROR(INDEX(AK_BARIS,MATCH(L37,AK_NAMA,0)),"?")) -> OP3 | O37: =IF(C37="","",IFERROR(INDEX(AK_KEL,MATCH(C37,AK_NAMA,0)),"?")) -> BEBAN | P37: =IF(D37="","",IFERROR(INDEX(AK_KEL,MATCH(D37,AK_NAMA,0)),"?")) -> ASET | Q37: =N(Q36)+IF(AND(N(E37)<>0,K37=TAHUN,N(J37)<=BLN,OR(C37=BB_AKUN,D37=BB_AKUN)),1,0) -> 21 | R37: =IF(OR(C37&D37="",N(E37)=0),"",IF(OR(O37="?",P37="?"),"⚠ akun tidak dikenal",IF(C37=D37,"⚠ debet = kredit","")))
A38: JU-0034 | B38: 46030 | C38: Kas Bank | D38: Pendapatan non Cafe | E38: 520000 | F38: Pemasukan penjualan tiket 08/01 event Maharia tgl 16/01 | G38: Event Maharia | I38: UMUM | J38: =IF(B38="","",MONTH(B38)) -> 1 | K38: =IF(B38="","",YEAR(B38)) -> 2026 | L38: =IF(N(E38)=0,"",IF(COUNTIFS(AK_NAMA,C38,AK_KAT,"KAS")+COUNTIFS(AK_NAMA,D38,AK_KAT,"KAS")<>1,"",IF(COUNTIFS(AK_NAMA,C38,AK_KAT,"KAS")=1,D38,C38))) -> Pendapatan non Cafe | M38: =IF(L38="",0,IF(L38=D38,E38,-E38)) -> 520000 | N38: =IF(L38="","",IFERROR(INDEX(AK_BARIS,MATCH(L38,AK_NAMA,0)),"?")) -> OP1 | O38: =IF(C38="","",IFERROR(INDEX(AK_KEL,MATCH(C38,AK_NAMA,0)),"?")) -> ASET | P38: =IF(D38="","",IFERROR(INDEX(AK_KEL,MATCH(D38,AK_NAMA,0)),"?")) -> PENDAPATAN | Q38: =N(Q37)+IF(AND(N(E38)<>0,K38=TAHUN,N(J38)<=BLN,OR(C38=BB_AKUN,D38=BB_AKUN)),1,0) -> 22 | R38: =IF(OR(C38&D38="",N(E38)=0),"",IF(OR(O38="?",P38="?"),"⚠ akun tidak dikenal",IF(C38=D38,"⚠ debet = kredit","")))
